Workbook

Sheet MetaData
B2: Deltares/RWS Projectnaam: Kennisvragen Sluizen met uitwerking voor Sluis Panheel Datum: 12-08-2026 Auteurs: Deltares: Meinard Tiessen Esther van Baaren Rijkswaterstaat: Riva de Vries Iris Koekkoek Betrokkenen Rijkswaterstaat: Martine Jak-Brinkhuis Patrizia Bernardini Evelien Ploos Van Amstel Peter Jansen Wilco Meijerink Max Pouwels Assetmanagementteam RWS: Linneke van der Veeken Michel de Waal Kees corstens Carla Sengers Paul van Wijnkel Kees van Rooij Carina Verbeek Denise Buijk Jos Hendriks Betrokkenen TNO: Greta van Velzen Esra Bektas Betrokkenen Deltares: Tom Omahoney

Sheet Systeem
B1: Ligging sluiscomplex Panheel:
B2: Het sluiscomplex Panheel ligt in het kanaal Wessem-Nederweert (KWN), nabij de plaats Panheel. Het KWN is een 17 km lange vaarweg die de Maas verbindt met de Zuid-Willemsvaart en Noordervaart (bij Nederweert). Het hele kanalenstelsel wordt gevoed met Maaswater vanuit de Maas bij St Pieter. In natte periodes wordt het kanaal gevoed door lokale afloop, maar bij waterschaarste op de Maas kan deze ook worden gevoed via het gemaal bij Sluizencomplex Panheel. Het kanaal Wessem-Nederweert (KWN) staat in open verbinding met de Zuid-Willemsvaart en staat middels Sluizencomplex Panheel in verbinding met de Maas. De waterstand in het kanaal is hoger dan de waterstand in de Maas. Nabij het kanaal bevinden zich enkele beken die onder het kanaal doorstromen door middel van een sifon. Dit zijn de Tungelroyse Beek en de Uffelse Beek.
B4: Proces/ operatie van complex Panheel :
B5: Op het Sluiscomplex Panheel wordt geschut in de oude en nieuwe sluis.
B6: Bij een overschot aan Maaswater op het KWN wordt geschut met de nieuwe sluis (meer schutverlies)en gespuid via de nieuwe sluis buiten bedientijden (’s nachts).
B7: Bij te weinig aanvoer van Maaswater op het KWN wordt geschut met de oude sluis, wordt schutverlies beperkt door de spaarbekkens te gebruiken en/of zuinig te schutten (wachten tot de schutkolk vol schepen is), en/of wordt Maaswater gepompt naar het kanaal door het gemaal.
B8: De bediening vindt centraal plaats vanuit de bedienpost in Tilburg, maar kan ook vanaf de bedienpost aan de zuidzijde van het complex worden bediend. Hiervandaan worden beide sluizen en het gemaal bediend. Het nivelleren van de oude sluis (zonder spaarbekkens) duurt 7 tot 8 minuten, in de nieuwe sluis ca. 10 minuten.
B10: Functies van sluiscomplex Panheel:
B11: Schutfunctie: een bijdrage leveren aan de mogelijkheid om de scheepvaart binnen een bepaalde normtijd waterpanden te laten passeren. De schutsluizen leveren deze bijdrage door de scheepvaart binnen een bepaalde schuttijd een waterstandsverschil te laten overbruggen.
B12: Peilbeheer. Daarbij kan onderscheid gemaakt worden in de volgende subfuncties: Keren, spuien/ doorlaten water, schutverlies beperken dmv spaarbekkend en water pompen.
B13: Keerfunctie: de schutsluizen en het gemaal keren het niveauverschil tussen het KWN en de Maas. Op basis van de maatgevende waterstanden is er alleen sprake van keren waarbij het KWN-niveau hoger is dan het Maasniveau. Het sluizencomplex heeft zelf geen kerende functie.
B14: Spuifunctie: de nieuwe schutsluis wordt buiten de bedientijden ingezet om overtollig water af te voeren van het KWN. | M14: SchutSluizencomplex Panheel noord (oude kolk) 58C-001-01​
B15: Schutverlies beperkingfunctie: de spaarbekkens van de oude schutsluis worden in tijden van droogte gebruikt om het niveau op het kanalenstelsel zo min mogelijk te laten dalen. | M15: Sluizencomplex Panheel noord in het kanaal Wessem-Nederweert​
B16: Waterpompfunctie: het gemaal wordt in tijden van droogte gebruikt om water aan te voeren naar het kanalenstelsel. | M16: Limburg - Maasgouw
B18: De functie schutverlies beperken is in deze analyse alleen kwalitatief beschouwd.
B19: De bediening van Sluiscomplex Panheel zal naar verwachting in 2015 worden ondergebracht in de bediencentrale te Tilburg. Deze ontwikkeling is niet meegenomen in de analyse. | D19: Bron: E60-WKR-KA-1300035 - Rapport integrale RAMS analyse_Sluiscomplex Panheel_v4.0.pdf
B22: Zie document: Beschrijving_sluiscomplex_Panheel_(tabblad_1).docx
B26: Overzicht functies van systeem tot en met complex niveau
B27: Water vasthouden (peilbeheer)
B28: Keren water (waterveiligheid, kanaalzijde oevers tot aan de sluis, niet de sluis zelf)
B29: Spuien water/ Afvoeren van overtollig water (peilbeheer)
B30: Schutverlies beperken dmv spaarbekkens (peilbeheer)
B31: Water pompen (peilbeheer)
B32: Peilbeheer: Schutverlies beperken dmv spaarbekkens
B33: Waterkwaliteit
B34: Ecologie
B35: Cultuurhistorische waarde
B36: Faciliteren scheepvaart
... B53: De CEMT-klasse op het kanaal is klasse II (lengte 96 m, breedte 9,5 m, max. diepgang 2,10 m). De recreatievaartklasse is BM (ontsluiting voor motorboten). De nieuwe sluis is geschikt voor schepen t/m klasse II. Door de oude sluis kunnen alleen schepen tot 7,25 m breed. Uit interviews blijkt dat er eens per 14 dagen een schip passeert, dat te breed is voor de oude sluis.

Sheet Sluizencomplex
B1: Het Complex
B2: Het sluizencomplex Panheel heeft met bijna 8 meter het op twee na grootste verval van alle sluizen in Nederland. Het complex omvat een gemaal en twee sluizen: de oude, noordelijke sluis (gebouwd tussen 1925 en 1928, gerenoveerd in 1995) en de nieuwe, zuidelijke sluis ernaast (gebouwd tussen 1986 en 1992).
B3: De oude, noordelijke sluis is voor Nederland uniek in zijn soort. Naast de oude sluis liggen twee spaarbekkens en twee andere bassins zijn in de betonnen sluiswand uitgespaard. Door gebruik van deze spaarbekkens is het mogelijk ongeveer 60% van het water te besparen tijdens het schutproces (figuur 12). Dimensies van de oude sluis zijn 150 meter lang, 7,5 meter breed en 11,5m meter diep. De drempel diepte van de benedenkant (buiten) is -2,90 meter. De drempel diepte van de bovenkant (binnen) is -3,15 meter.
B4: De nieuwe, zuidelijke sluis, waaraan van 1986 tot 1992 is gebouwd, is aanzienlijk breder dan de oude (150 meter lang, 12,6 meter breed en 11,5 meter diep), waardoor deze geschikt is tot CEMT klasse IV schepen. (figuur 6). De drempel diepte van de benedenkant (buiten) is -4,20 meter. De drempel diepte van de bovenkant (binnen) is -3,95 meter.
B5: Naast het sluiscomplex is een pompgemaal gerealiseerd. Twee elektrische pompen met een vermogen van 440 kW elk, zorgen er eventueel voor dat het bij het schutten verloren gegane water wordt teruggepompt.
B6: De bediening van de twee sluizen en het gemaal vindt centraal plaats maar kan ook vanuit een bediengebouw dat zich aan de zuidzijde van de nieuwe sluis bevindt.
B7: Het gemaal bestaat uit de volgende onderdelen: 1. Instroomgedeelte en gemaal; 2. Gesloten koker; 3. Uitstroomgedeelte (let wel: Noord is naar onder): (figuur 8)
J10: Bron: RWSZN-2022-022938_Oudesluis_functioneren_spaarbekkens_incl_hoogtes.pdf
B25: Bron: E60-WKR-KA-1300035 - Rapport integrale RAMS analyse_Sluiscomplex Panheel_v4.0.pdf
B28: Zie document: Beschrijving_sluiscomplex_Panheel_(tabblad_1).docx
B31: Hydraulische randvoorwaarden - waterbeheer:
B33: Kanaal Wessem Nederweert (ten westen / noordwesten van het complex)
B34: Streefpeil /SP 28.65 m +NAP
B35: Minimaal Waterpeil /MIP1 28.52 m + NAP
B36: Minimaal Waterpeil /MIP2 28.40 m +NAP
B37: Maximaal Waterpeil /MAP1 28.70 m +NAP
B38: Maximaal Waterpeil /MAP2 28.72 m +NAP
B39: Waterstanden bij vullen en ledigen kolk met gebruik van spaarkomen;
B41: Stuwpand Linne (ten oosten / zuidoosten van het complex)
B42: Streefpeil /SP 20.85 m +NAP
... B45: Bron: Bijlage V streefpeilen

Sheet Complex-object 
A1: Complex | B1: Type functies complex | C1: Functies complex | D1: Eisen/wensen complex | E1: Object | F1: Functie object | G1: Eisen/wensen object | H1: Opmerkingen over eisen/wensen en relevantie voor functioneren sluis Panheel | I1: Bron
A2: Sluiscomplex als samenhangend geheel, opgebouwd uit meerdere componenten, bestaande uit twee schutsluizen en een pompgemaal. | B2: Peilbeheer en waterveiligheid | C2: Water vasthouden (peilbeheer) | D2: Het complex draagt bij aan het handhaven van gewenste waterstanden en debieten in het watersysteem Maas – Kanaal Wessem–Nederweert, onder zowel natte als droge omstandigheden. | E2: Sluiscomplex Panheel | F2: Handhaven van peilscheiding en sturen van waterstanden tussen Maas en KWN door: water te keren, water te spuien of door te laten, water actief terug te pompen, schutverlies te beperken De oude sluis functioneert als spaarsluis ten behoeve van waterbesparing. | G2: Stabiel streefpeil KWN | H2: Peilbeheer is een kernfunctie van Sluis Panheel. De combinatie van schutten, pompen en spaarbekkens maakt het complex strategisch voor zoetwaterverdeling richting het Brabantse kanaalsysteem. | I2: Basisspecificatie SS/ RINK
G3: Beperking van zoetwaterverlies bij schutten
G4: Voldoende zoetwater vasthouden tijdens droogte
C5: Keren water (waterveiligheid, kanaalzijde oevers tot aan de sluis, niet de sluis zelf) | D5: De schutsluizen en het gemaal keren het niveauverschil tussen het KWN en de Maas. Op basis van de maatgevende waterstanden is er alleen sprake van keren waarbij het KWN-niveau hoger is dan het Maasniveau. | E5: Sluiscomplex Panheel | F5: Keren hoogwater in gesloten stand. | G5: Streefpeil KWN: +28.65 en Maas MLW: +20.70 . Sluis Panheel houdt waterstandsverschillen tegen (± 7–8 m verval) | H5: Keren van hoogwater als het KWN-niveau hoger is dan bij het Maasniveau (beschermen tegen hoogwater vanuit bovenstrooms of benedenstrooms). De kerende functie kan bij beide sluizen als volgt falen: - Indien de sluis gesloten is kan dit gebeuren als beide hoofden niet meer keren, bijvoorbeeld doordat een deur of schuif bezwijkt. Indien de deuren bij het ene hoofd geopend zijn voor schutten, kan falen van het andere hoofd leiden tot een doorstroom opening, bijvoorbeeld door aanvaring in combinatie met falen van de aanvaarbescherming. - Bij het spuien in de nieuwe sluis kan de kerende functie ook falen indien de bedienaar per abuis een te grote spui-opening realiseert. Bij het spuien buiten bedientijd (’s nachts) wordt de waterstand gemonitord en het falen dus met enige vertraging geconstateerd. | I5: Basisspecificatie SS/ RINK
G6: Betrouwbaar sluiten bij hoogwater
G7: Geen formele faalkansnorm, wel hoge functionele betrouwbaarheid
C8: Spuien water/ Afvoeren van overtollig water (peilbeheer) | D8: Voldoende afvoeren hoog rivierdebiet om substantiële verhoging van hydraulische belasting op achterliggende primaire waterkeringen te voorkomen | E8: Sluiscomplex Panheel | F8: Afvoeren (hoog) rivierdebiet | G8: Spuifunctie: de nieuwe schutsluis wordt buiten de bedientijden ingezet om overtollig water af te voeren van het KWN. | H8: Spuien via de nieuwe sluis gebeurt meestal buiten de bedientijden (’s nachts) en vrijwel nooit op dagen dat het gemaal wordt gebruikt. Er wordt regelmatig ook nog overdag gespuid in bedientijd. Dit gebeurt naar schatting op 75% van de spuidagen en duurt gemiddeld 2 à 3 uur. Het spuiriool in de oude sluis heeft te weinig afvoercapaciteit voor de gebruikelijke spuibehoefte. Bij spuien in de nieuwe sluis worden de deurschuiven gedeeltelijk open gezet. Dergelijke schuiven worden in het schutproces altijd geheel geopend, niet gedeeltelijk. Het langdurig gedeeltelijk open staan van de schuiven levert mogelijk te zware belastingen op. | I8: Basisspecificatie SS/ RINK
B9: Leefbaarheid | C9: Schutverlies beperken dmv spaarbekkens (peilbeheer) | D9: Peilbeheer is een kernfunctie van Sluis Panheel. Met name in droogteperioden is de combinatie van schutten, spaarbekkens en pompen cruciaal voor het vasthouden en verdelen van zoetwater richting het Brabantse kanaalsysteem. | E9: Sluiscomplex Panheel | F9: Beperking van (zoetwater)verlies bij schutten | G9: Voldoende zoetwater vasthouden tijdens droogte | H9: De spaarbekkens van de oude schutsluis zijn op dit moment niet in gebruikt, maar zijn ontworpen om het niveau op het kanalenstelsel zo min mogelijk te laten dalen. 60% van schutwater kan worden hergebruikt middels de spaarbekkens. Dit is bedoeld om zoetwaterverlies te beperken in perioden van waterschaarste. | I9: Rams analyse/ ontw RVW ss
G10: Voldoende vaardiepte voor scheepvaart waarborgen
C11: Water pompen (peilbeheer) | D11: Door middel van pompcapaciteit kan onder droge omstandigheden water worden aangevoerd naar het kanalenstelsel, zodat gewenste peilen en watervoorziening gehandhaafd blijven. Het complex moet flexibel kunnen inspelen op variaties in rivierafvoer en veranderende hydrologische omstandigheden. | E11: Sluiscomplex Panheel | F11: Flexibel inspelen op variaties in rivierafvoer (nat/droog) | G11: Mogelijkheid tot actief waterbeheer bij droogte (inzet pomgemaal). | H11: Het gemaal wordt in tijden van droogte gebruikt om water aan te voeren naar het kanalenstelsel. Afhankelijk van weersomstandigheden is er veel verschil in de frequentie en duur van de operatie; soms wordt er wel tot 4 dagen continu gepompt. De maximale stilstandduur is ca. 2 maanden. Voor het bedieninterval wordt 1 maand gehanteerd. De kerende functie kan falen bij het gemaal wanneer aan het eind van het verpompen zowel de persschuif als de vlinderklep op 1 watergang niet sluiten. Bij energie-uitval sluit een vlinderklep niet ofwel als de black-out klep gesloten blijft (en de hydraulische druk dus niet wegvalt) ofwel als de overbrenging van het contragewicht faalt doordat de spie van de as afbreekt. | I11: Rams analyse/ ontw RVW ss
C12: Waterkwaliteit | D12: Geen verslechtering van waterkwaliteit in de sluis en kanaalbeheer; voldoen aan KRW-doelen. | E12: Sluiscomplex Panheel | F12: Bijdragen aan doorstroming en voorkomen van stagnatie. | G12: Bedieningsregime afgestemd op (voldoende) doorstroming | H12: Randvoorwaardelijke functie; niet primair sturend voor ontwerp, maar relevant voor beheer en bediening. | I12: Basisspecificatie SS
G13: Geen langdurige stilstand van watermassa’s
C14: Ecologie | D14: Behoud en waar mogelijk versterking van ecologische kwaliteit; voldoen aan Natura 2000 / KRW-ecologische doelen (waar relevant). | E14: Sluiscomplex Panheel | F14: Faciliteren van ecologische verbindingen en minimaliseren van negatieve effecten op habitats en soorten. | G14: Behouden van geschikt habitat in en rond het complex. Voorkomen van verstoring. | H14: Randvoorwaardelijke functie; niet primair sturend voor ontwerp, maar relevant voor beheer en bediening. Meekoppelkansen mogelijk bij onderhoud en aanpassing (bijv. vispassage of ecovriendelijke inrichting).
C15: Cultuurhistorische waarde | D15: Borging en herkenbaarheid van cultuurhistorisch waardevolle onderdelen van het complex. | E15: Sluiscomplex Panheel | F15: Drager van cultuurhistorische en historische waarden. | G15: Rekening houden met monumentale en cultuurhistorische waarden | H15: De oude sluis (gebouwd in 1925–1928) heeft cultuurhistorisch belang en een oranje status, wat betekent dat er wel waarde is, maar geen formele monumentenbescherming. | I15: Bouwhistorische verkenning & waardestelling sluis panheel kanaal wessem nederweert 22 maart 2022
G16: Behoud van karakteristieke constructieve en ruimtelijke kenmerken
G17: Beperkingen aan aanpassing, vervanging of buitengebruikstelling van de oude sluis
B18: Bereikbaarheid | C18: Faciliteren scheepvaart | D18: Betrouwbare en vlotte doorvaart tussen Maas en Kanaal Wessem–Nederweert. | E18: Sluiscomplex Panheel (Oude, noordelijke sluis en nieuwe, zuidelijke sluis) | F18: De schutsluis dient het maatgevende schip CEMT klasse 2 te kunnen laten passeren. Efficiënt schutproces. | G18: De oude, noordelijke sluis en nieuwe, zuidelijke sluis faciliteren beiden CEMT-klasse 2-scheepvaart. De oude sluis faciliteert schepen tot maximaal 7,25 meter breed, de nieuwe sluis faciliteerd schepen tot 9,5 meter breed. Recreatievaart tot en met categorie BM. | H18: Door de oude sluis kunnen alleen schepen tot 7,25 m breed. Uit interviews blijkt dat er eens per 14 dagen een schip passeert, dat te breed is voor de oude sluis. | I18: RAMS-analyse
G19: Voldoende vaardiepte voor scheepvaart waarborgen. Maatgevende afmetingen van circa 95 × 7,25 m en een maximale diepgang van circa 2,10 m.
G20: Beschikbaarheid van (minimaal) één kolk. | H20: Nut en noodzaak van twee kolken is onderwerp van heroverweging (kennisagenda).
D21: De schutsluis dient het scheepvaartaanbod vlot en veilig te kunnen schutten. | E21: Sluiskolken | F21: Schutfunctie (grote, kleine en recreatie schepen) | G21: De oude, noordelijke sluis en nieuwe, zuidelijke sluis faciliteren beiden CEMT-klasse 2-scheepvaart. Recreatievaart tot en met categorie BM. | H21: Schutten wordt gestaakt bij ijsgang, bij gevaarlijke situaties, of indien het peilbeheer dit vereist. Bij ijsgang is er geen watertekort, de functie verpompen wordt hierdoor dus niet gehinderd. | I21: RAMS-analyse
G22: Acceptabele wachttijden
G23: De schutsluis dient waterpeil te nivelleren, waarbij een rustige ligging van de schepen wordt verzekerd.
B24: Overige functies | C24: Faciliteren van de bediening | D24: Betrouwbare, veilige en robuuste bediening. | E24: Sluiscomplex Panheel | F24: Bediening op afstand (middels een interface bediencommando's geven); ondersteunen bieden aan beheer en onderhoud. | G24: Betrouwbare ICT en energievoorziening | H24: Het falen van een onderdeel uit de bediening en besturing is ofwel centraal, met hinder voor alle functies passeren/spuien/verpompen, ofwel lokaal. | I24: Basisspecficatie SS/ RINK
G25: Cybersecurity
G26: Ondersteuning inspectie en onderhoud
C27: Calamiteiten | D27: Ondersteunen robuust functioneren watersysteem bij verstoringen. | E27: Sluiscomplex Panheel | F27: Beschikbaarheid bij calamiteiten elders in het systeem. | G27: Flexibel inzetbaar (spuien, pompen en sluiten) en redunantie. | H27: Redundantie via twee kolken is onderwerp van afweging.

Sheet Driver-overzicht
A1: Categorie | B1: Type / Driver | C1: Toelichting | D1: Informatie en verandering | E1: Verwachte relevantie voor Object Sluizencomplex Panheel | F1: Toelichting | G1: Bron | H1: Samenhang andere NK's | J1: De schaal van relevantie (impact op het kunstwerk)
A2: Autonome situatie | B2: Huidige (en ontwerp) staat | C2: Wat waren/zijn de uitgangsposities van het ontwerp van Sluizencomplex Panheel en weten we wat de status nu is? (aldus Ontw RVW SS: belasting: waterstand, windopzet, schutgolven, scheepsgolven, combinatie) | D2: Ontwerp gebaseerd op binnenvaart, peilbeheer en waterverdeling tussen Maas en kanaalsysteem. Belastingen bestaan uit waterstandsverschillen, schutwerkingen, scheepsbelasting en mechanische belasting van bewegingswerken (geen windopzet/golfbelasting vanuit zee). | E2: Groot | F2: Sluizencomplex Panheel is een actief waterstaatkundig object met continue wisselende belastingen door schutten en peilbeheer; dit vormt de basis voor alle verdere verouderings- en faalmechanismen. | G2: Expert kennis RWS | J2: Klein | K2: Verwaarloosbare driver
B3: Vermoeiing | C3: Afname sterkte door (af)wisselende belasting (periodieke belasting op de stalen delen, bijvoorbeeld door golven in combinatie met de waterstand) | D3: Met name relevant voor deuren, aandrijvingen en staalconstructies door hoge schutfrequentie en cyclische belasting. | E3: Mogelijk groot | F3: In tegenstelling tot keringen met incidentele belasting treedt bij Panheel continue vermoeiing op. Dit maakt vermoeiingsschade een belangrijk aandachtspunt voor levensduur en onderhoudsstrategie. | G3: Expert kennis TNO | J3: Mogelijk klein | K3: Nog onbekend welke invloed de driver precies heeft; minder prioriteit om uit te zoeken
B4: Slijtage | C4: Eroderen (slijten) van materialen door het inzetten van de sluis | D4: Slijtage door schutten en bewegende delen is structureel aanwezig maar beheersbaar met regulier onderhoud. | E4: Mogelijk klein | F4: Hoewel slijtage continu optreedt, is deze bij tijdig onderhoud goed te beheersen. Het vormt vooral een aandachtspunt bij uitstel van onderhoud of intensiever gebruik. | G4: Expert kennis TNO | J4: Middel | K4: Relevante driver
B5: Schade (aanvaar, temperatuursinvloeden) | C5: Calamiteit die zorgt voor lokale schade/verzwakking. | D5: Aanvaringen en storingen hebben direct effect op beschikbaarheid en waterverdeling; impact groter dan bij een passieve waterkering. | E5: Mogelijk groot | F5: Door de functionele rol van Panheel in zowel scheepvaart als waterverdeling zijn de gevolgen van lokale schade groter dan bij een passieve waterkering. | J5: Mogelijk groot | K5: Nog onbekend welke invloed de driver precies heeft; meer prioriteit om uit te zoeken
B6: Degradatie | C6: Algemene degradatie door verschillende processen die zorgen voor afname in sterkte van materialen in het complex | D6: Algemene materiaaldegradatie door ouderdom, belastinghistorie en interactie tussen beton, staal en water. | E6: Mogelijk groot | F6: Gezien de leeftijd van delen van het complex (oude en nieuwe kolk) ligt cumulatieve degradatie voor de hand en beïnvloedt dit direct de restlevensduur. | G6: Expert kennis TNO en RWS | J6: Groot | K6: Zeer relevante driver
A7: Klimaat- en natuurlijke processen | B7: Zeespiegelstijging | C7: Stijging van het gemiddelde zeeniveau | D7: De zeespiegelstijging bedraagt volgens huidige projecties circa +16 tot +38 cm in 2050 en +26 tot +124 cm in 2100 (afhankelijk van scenario). Sluizencomplex Panheel ligt diep landinwaarts en ondervindt geen directe invloed van zeespiegelstijging. | E7: Klein | F7: Zeespiegelstijging leidt niet tot directe wijziging van belastingen op Sluizencomplex Panheel, omdat het object niet wordt blootgesteld aan getij, zoutwater of mariene golfbelasting. Indirecte effecten zijn alleen mogelijk via langetermijnveranderingen in afvoerregimes en waterverdeling op systeemniveau, maar die worden primair gedreven door rivierafvoer en niet door zeespiegelstand. | G7: KNMI2023
B8: Verandering windklimaat | C8: Windsnelheid, windrichting, windextremen | D8: Voor Nederland wordt tot 2100 weinig verandering in gemiddelde windsnelheid en -richting verwacht. Wel kunnen extreme windstoten bij zware buien toenemen en komt wind uit zuidwestelijke richtingen mogelijk iets vaker voor. | E8: Klein | F8: Windbelasting is slechts zeer beperkte driver voor Sluizencomplex Panheel. Er zijn geen grote wateroppervlakken waarbij windopzet of windgolven maatgevend zijn voor ontwerp of functioneren. Wind kan alleen een operationele rol spelen (bijvoorbeeld bij bediening of scheepvaart), maar heeft geen significante invloed op constructieve veiligheid of veroudering. | G8: KNMI2023
B9: Verandering golfklimaat Noordzee | C9: Veranderingen in golfhoogte, - periode, en/of -richting | D9: Veranderingen in het golfklimaat zijn relevant voor kust- en estuariumobjecten. Voor Sluizencomplex Panheel is er geen golfbelasting vanuit zee en geen significante windgolfontwikkeling op het kanaal of in de kolk. | E9: Klein | F9: De hydraulische belasting bij Sluizencomplex Panheel wordt volledig gedomineerd door schutprocessen en scheepsbewegingen (schutgolven en scheepsgolven). Klimaatgedreven veranderingen in golfklimaat spelen hier geen rol. | G9: DeWinter2012; DeWinter2013;
B10: Toename piekafvoer Maas & Rijn | C10: Toename van jaarlijkse piekwaarden | D10: 2050 +5 tot +10%; 2100 -2 tot +30% in jaarlijkse maxima van het debiet in de Rijn. Voor de Maas is dit -8% - 2% en -8 - 20%. | E10: Mogelijk groot | F10: Hoewel Panheel geen primaire kering is, beïnvloeden hogere Maasafvoeren direct het kerend vermogen en de operationele belasting. | G10: Deltares2023
B11: Toename frequentie hoogwater Maas & Rijn | C11: Toename van kans hoogwater op rivieren | D11: Met name in de winter wordt verwacht dat er gemiddeld meer afvoer gaat stromen door de rivieren in Nederland. Voor de Maas is dit tot 10% meer in 2050 en 30% in 2100 en minder voor de overige. Voor de Rijn is dit tot 15% in 2050 en 35% in 2100. Dit is voor het meest extreme KNMI scenario Hoognat. Het is niet geheel duidelijk hoe dit doorvertaald tot toename in frequentie hoogwater bij de HIJK | E11: Mogelijk groot | F11: Hoewel Panheel geen primaire kering is, beïnvloeden hogere Maasafvoeren direct het kerend vermogen en de operationele belasting. | G11: Deltares2023
B12: Afname rivierafvoer (voornamelijk in de zomer) | C12: Afname van jaarlijks 7-daags minimum piekwaarden | D12: 2050 -5 tot -17%; 2100 -7 tot -32% voor 7-daags minimum op de Maas. | E12: Mogelijk groot | F12: Vergroot het belang van Panheel in waterverdeling richting Brabantse kanalen, inclusief inzet van pompen, waterbesparende maatregelen en mogelijke inzet van een aangepast schutregime. | G12: Deltares2023
B13: Toename frequentie laagwater Maas & Rijn | C13: Toename kans op laagwater op rivieren | D13: Geen exacte kwantificering van beschikbaar. Wel is de verwachting dat de gemiddelde zomer afvoer van de Maas afneemt: In 2050: 0 tot -13%, 2100: -5% tot -25% | E13: Mogelijk groot | F13: Vergroot het belang van Panheel in waterverdeling richting Brabantse kanalen, inclusief inzet van pompen, waterbesparende maatregelen en mogelijke inzet van een aangepast schutregime. | G13: Deltares2023
B14: Verandering neerslagpatronen | C14: Toename van de hoeveelheid (lokale) neerslag in het achterland leidt tot meer malen uit polders (bijv. hoosbuien) | D14: Winter 10 daags maximum per 10 jaar: 2050 verandering -2% tot +2%; 2100 verandering -2% tot +15%; Totale neerslag winter: 4-24% toename in 2100. Totale neerslag zomer: 2050 afname -2% tot -13%; 2100 afname -2% tot -29% | E14: Klein | F14: Effect indirect via waterbeheer; beperkt effect op constructieve belasting van de sluis. | G14: KNMI2023
B15: Toename luchttemperatuur | C15: Stijging van gemiddelde (en gem. dagminimum/maximum) | D15: Verschilt per scenario en per seizoen; 2050 +0,7 C tot +2,2 C; 2100 +0,7 C tot +5,4 C | E15: Mogelijk klein | F15: Een stijgende luchttemperatuur heeft geen directe invloed op de hydraulische of constructieve belastingen van Sluizencomplex Panheel. | G15: KNMI2023
B16: Verandering watertemperatuur | C16: Verandering van de gemiddelde temperatuur van het water rondom het complex | D16: Door opwarming van de aarde kan de watertemperatuur veranderen (in eerste instantie toenemen, als de golfstromen stoppen juist afnemen). | E16: Mogelijk klein | F16: Een hogere watertemperatuur kan invloed hebben op ecologie en waterkwaliteit, maar heeft geen maatgevende invloed op het functioneren of de veiligheid van Sluizencomplex Panheel. Eventuele effecten op materialen of installaties zijn beperkt en secundair. | G16: Expert kennis Deltares
B17: CO2-toename in de lucht | C17: Verandering CO2 concentratie in de lucht in parts per million (ppm) | D17: Alleen wereldwijde concentratie beschikbaar, huidig ~420 ppm; 2050 tot 600 ppm; 2100 tot 1100 ppm | E17: Mogelijk klein | F17: Een hogere CO₂‑concentratie kan op lange termijn bijdragen aan snellere carbonatatie van beton, maar voor Sluizencomplex Panheel wordt dit niet als zelfstandig maatgevend proces beschouwd. Het effect is beperkt en onderdeel van bredere klimaatgedreven degradatieprocessen. | G17: KNMI2023 TNO-rapport R10699
B18: Bodemdaling | C18: Het inklinken van de bodem en daarmee het zakken van het maaiveld | D18: Bodemdaling door inklinking van slappe ondergronden kan lokaal optreden, afhankelijk van bodemopbouw en grondwaterbeheer. | E18: Klein | F18: In de omgeving van Sluizencomplex Panheel is bodemdaling beperkt en relatief uniform, waardoor geen significante extra belasting of functieverlies van het complex wordt verwacht. Monitoring blijft wenselijk, maar bodemdaling is geen dominant aandachtspunt. | G18: Expert kennis RWS
B19: Verzilting | C19: Zoutindringing in zowel grondwater als oppervlaktewateren (door open estuarium of door sluizen) | D19: Verzilting treedt vooral op in open estuaria en kustgebieden. Sluizencomplex Panheel ligt landinwaarts en heeft geen directe zoutwaterinvloed. | E19: Klein | F19: Structurele zoutindringing speelt geen rol bij Sluizencomplex Panheel. Eventuele tijdelijke of lokale effecten hebben geen betekenis voor ontwerp, veiligheid of degradatie van het complex. | G19: Expert kennis Deltares
... B23: Verandering in biodiversiteit en ecosysteem | C23: Bijv. afname biodiversiteit en achteruitgang ecosysteem door veranderingen in waterkwaliteit of connectiviteit van gebieden | D23: Geen specifieke documentatie | E23: Mogelijk klein | F23: Veranderingen in waterkwaliteit en ecologie kunnen lokaal optreden, maar hebben geen directe invloed op het primaire functioneren van de sluis. Effecten zijn vooral relevant vanuit ecologisch beleid, niet vanuit objectveiligheid of beschikbaarheid. | G23: Expert kennis RWS
A24: Socio-economische ontwikkelingen | B24: Verandering scheepvaartverkeer | C24: Een toename, in zowel intensiteit als scheepsgrootte, maar ook veranderingen in transportstrategie en type vracht | D24: Veranderingen in intensiteit, scheepsgrootte, type lading en transportstrategie binnen de binnenvaart. Scheepvaartprognoses voor gebruik sluizencomplex Panheel zijn: 2040: -7% tot +33%, 2050: +13% tot +36%. | E24: Mogelijk groot | F24: Scheepvaart bepaalt direct de gebruiksbelasting van de sluis (schutfrequentie, mechanische belasting, slijtage). Dit is één van de belangrijkste drivers voor veroudering en beschikbaarheid van Sluizencomplex Panheel. | G24: Konings2026
B25: Verandering bebouwing en/of verhoging waarde bebouwd achterland | C25: Toename in aantal woningen in het binnendijks achterland en/of toename van de waarde van dit achterland. | D25: Toename van bebouwing en economische waarde van het binnendijks achterland. | E25: Klein | F25: Sluizencomplex Panheel is geen primaire waterkering. Een toename van de waarde van het achterland leidt niet automatisch tot strengere waterveiligheidseisen voor het object. | G25: Expert kennis RWS
B26: Verandering in benodigd beveiligingsniveau | C26: Cyber security threats en fysieke beveiliging | D26: Toename van cyberdreigingen en eisen aan fysieke beveiliging, mede door bediening op afstand. | E26: Groot | F26: De afhankelijkheid van digitale systemen maakt beveiliging cruciaal voor de continuïteit van de bediening en waterverdeling. Dit is een strategisch relevante driver. | G26: Expert kennis RWS
B27: Technische ontwikkelingen (software, materiaal) | C27: - | D27: Ontwikkelingen in automatisering, sensoren, materialen en datagedreven beheer. | E27: Middel | F27: Technische innovaties bieden kansen voor betere monitoring en levensduurverlenging, maar vraagt ook om aanpassing van beheer, kennis en organisatie. | G27: Expert kennis RWS
B28: Verandering situatie leverancier | C28: Onbeschikbaarheid noodzakelijk materiaal/materieel | D28: Afname beschikbaarheid van specifieke leveranciers, onderdelen of expertise. | E28: Middel | F28: Afhankelijkheid van unieke of verouderde componenten kan risico’s opleveren voor onderhoud en storingsherstel, vooral bij oudere installaties. | G28: Expert kennis RWS
B29: Vertrek/pensionering kennisdragers | C29: Kennis van personeel moet tijdig overgedragen kunnen worden om object specifieke kennis te borgen. Bij een groot verloop van personeel kan kennisoverdracht in het geding raken. | D29: Uitstroom van ervaren personeel met objectspecifieke kennis. | E29: Middel | F29: Gebrek aan overdracht van praktische en historische kennis kan leiden tot verhoogde faalrisico’s en minder effectief beheer. | G29: Expert kennis RWS
A30: Beleidskeuze | B30: Energietransitie | C30: Aanleg van winturbines en kabels | D30: Aanleg van windturbines, kabels en leidingen; verandering in energievoorziening van het object. | E30: Middel | F30: Geen directe invloed op veiligheid, maar wel relevant voor ruimtelijke inpassing, exploitatie en mogelijke aanpassing van energievoorziening. | G30: Expert kennis RWS
B31: Ecologische waarde watersysteem | C31: Aan weerszijden van het complex als ook de connectiviteit | D31: Toenemende aandacht voor ecologische kwaliteit en connectiviteit van watersystemen. | E31: Mogelijk klein | F31: Kan leiden tot aanvullende eisen of maatregelen (bijv. vismigratie), maar raakt het primaire functioneren van de sluis beperkt | G31: Expert kennis Deltares
B32: Verandering onderhoudsbudget | C32: Mogelijke verandering economisch beleid o.b.v. regeringsbesluiten betreffend RWS | D32: Wijzigingen in beschikbare middelen door economisch of politiek beleid. | E32: Middel | F32: Budgetveranderingen beïnvloeden onderhoudsfrequentie, risicohouding en keuzes rond levensduurverlenging. | G32: Rijksoverheid2024
B33: Stikstofbeleid | C33: Stikstofuitstoot bij het opereren en onderhouden van het complex | D33: Strengere regels voor stikstofemissies bij onderhoud en uitvoering. | E33: Klein | F33: Heeft vooral invloed op uitvoering en planning van werkzaamheden, niet op functioneren of veiligheid van de sluis. | G33: Deltares 2024a, expert judgement
B34: Verbod op gebruik materialen | C34: Mogelijk wordt de wetgeving aangescherpt voor het gebruik van bepaalde materialen, dat enkele materialen zal gaan verbieden (vanwege milieu en/of Arbo veiligheid) | D34: Aanscherping van wetgeving die bepaalde materialen verbiedt (milieu/Arbo). | E34: Klein | F34: Leidt tot alternatieve materiaalkeuzes, maar geen fundamentele aanpassing van het systeem. | G34: Expert kennis RWS
B35: Aanscherping arbo veiligheidsnormen | C35: Beperkingen voor de uitvoering van het onderhoud door aanscherpingen in de Arbo veiligheidseisen | D35: Strengere eisen aan arbeidsveiligheid bij inspectie en onderhoud. | E35: Middel | F35: Kan onderhoud complexer of duurder maken en planning beïnvloeden, maar raakt de objectfunctie niet direct. | G35: Expert kennis RWS
B36: Zoutindringing | C36: Mogelijke inzet van het complex bij tegengaan zoutindringing | D36: In gebieden waar verzilting van oppervlaktewateren optreedt of een risico is, kan een schutsluis worden ingezet om zoutindringing tegen te gaan. Gedacht kan worden aan een stremming waardoor verzilt water niet meer een bepaald waterlichaam kan binnendringen. | E36: Klein | F36: Sluizencomplex Panheel heeft geen structurele rol in zoutindringingsbeheer; zoutbelasting is geen maatgevende factor. | G36: Expert kennis Deltares, oa. KPZSS2023
B37: Aanpassing streef- en sluitpeilen | C37: Aanpassing peilen aan weerszijden van kunstwerk met name richting 2100. | D37: Door verandering van wateraanvoer of waterbeschikbaarheid kan worden gekozen om aangepaste peilgrenzen te hanteren in de toekomst. | E37: Klein | F37: Peilaanpassingen zijn denkbaar, maar leiden niet tot wezenlijk nieuwe belastingen of ontwerpvragen voor Panheel. | G37: Expert kennis RWS
B38: Vervanging complex | C38: Complex wordt vervangen door een andere waterkering en is niet meer nodig om de waterveiligheid te borgen | D38: Scenario waarin Sluizencomplex Panheel wordt vervangen of zijn functie verliest. | E38: Mogelijk groot | F38: Dit heeft grote consequenties voor investeringen, kennisontwikkeling en lange‑termijn beheerstrategie. | G38: Expert kennis RWS
B39: Heroverweging aantal kolken/ functiereductie sluis | C39: Ingegeven door energietransitie en besparingen, beperkt gebruik door scheepvaart, hoge onderhoudskosten, waterbeschikbaarheid of andere redenen, kan worden overwogen om een aantal onderdelen (waaronder kolken) terug te schalen. | D39: Binnen het operationeel team leven zorgen over de noodzaak van het aanhouden van twee schutkolken bij Sluizencomplex Panheel. | E39: Mogelijk groot | F39: Brede afweging van belangen en factoren kan leiden tot een andere keuze van de inrichting en inzet van verschillende onderdelen van het sluiscomplex | G39: Expert kennis RWS, Deltares
B40: Nieuwe systeemeisen en/of -inrichting | C40: Een herinrichting van het systeem en daarmee ook nieuwe eisen aan de sluis | D40: Herinrichting van vaarweg- of watersysteem met nieuwe functionele eisen. | E40: Middel | F40: Kan aanpassingen aan het complex vereisen, maar is sterk afhankelijk van beleidskeuzes en systeemontwikkeling. | G40: Expert kennis RWS
B41: Verlenging levensduur | C41: Verlengen van de levensduur (langer inzetten complex) | D41: Bewuste keuze om het complex langer te gebruiken dan oorspronkelijk voorzien. | E41: Middel | F41: Vraagt om betere kennis van degradatie, restlevensduur en adaptieve maatregelen — kernonderwerp voor de kennisagenda. | G41: Expert kennis TNO, RWS, Deltares
B42: Strengere waterveiligheidseis | C42: Strengere veiligheidseisen ivm bevolkingsgroei/vestiging van bedrijven in gebied of wensen vanuit achterliggende waterschap | D42: Mogelijke toename van eisen aan betrouwbaarheid (faalkans, niet‑sluiten). | E42: Middel | F42: Er geldt geen wettelijke faalkansnorm, maar maatschappelijke of bestuurlijke druk kan leiden tot hogere functionele eisen. | G42: RINK-analyse Panheel
... B44: Algemene beleidskeuzen op (inter)nationaal niveau | C44: Onder andere aandacht voor vismigratie evenals bijvoorbeeld druk op aangepast beleid na forse investering in ecologie | D44: Beleidswijzigingen rond ecologie, klimaatadaptatie, bereikbaarheid en waterbeheer. | E44: Middel | F44: Effecten op Sluizencomplex Panheel zijn onzeker, maar kunnen signficant effect hebben op het functioneren van (onderdelen van) Sluizencomplex Panheel. | G44: Expert kennis RWS

Sheet ETL_componentsniveau
J1: Klimatologische en natuurlijke ontwikkelingen | AB1: Socio-economische ontwikkelingen | AJ1: Beleidsmatige ontwikkelingen
B2: Autonome situatie | C2: Huidige eisen | D2: Huidige (en ontwerp) staat en constructieve beoordeling | E2: Vermoeiing | F2: Slijtage | G2: Schade (aanvaar, temperatuursinvloeden) | H2: Degradatie | I2: Drivers | J2: Zeespiegelstijging | K2: Verandering windklimaat | L2: Verandering golfklimaat | M2: Verandering in grondwaterstanden | N2: Toename piekafvoer Maas & Rijn (voornamellijk in winter) | O2: Toename frequentie hoogwater Maas & Rijn (voornamelijk in winter) | P2: Afname rivierafvoer Maas & Rijn (voornamelijk in zomer) | Q2: Toename frequentie laagwater Maas & Rijn (voornamelijk in zomer) | R2: Verandering Neerslagpatroon | S2: Verandering luchttemperatuur | T2: Verandering van watertemperatuur | U2: Toename CO2-gehalte in de lucht | V2: Bodemdaling | W2: Verzilting | X2: Verandering sedimenttransport en bodemerosie | Y2: Verandering afvoer verdeling rijn-maas monding | Z2: Verandering in bodemligging | AA2: Verandering biodiversiteit in ecosysteem | AB2: Verandering scheepvaartverkeer | AC2: Verandering bebouwing en/of verhoging waarde bebouwd achterland | AD2: Verandering in benodigd beveiligingsniveau | AE2: Technische ontwikkelingen (software, materiaal) | AF2: Verandering situatie leverancier | AG2: Verlies van kennisdragers (pensioenering/vertrek), zowel bij RWS, als aannemers, Deltares. | AH2: Energietransitie | AI2: Toename ecologische waarde sluis Panheel | AJ2: Verandering onderhoudsbudget Sluis Panheel | AK2: Stikstofbeleid | AL2: Verbod op gebruik materialen | AM2: Aanscherpen (arbo) veiligheidsnorm | AN2: Nieuwe normen constructieve veiligheid | AO2: Aanpassing schutpeil | AP2: Zoutindringing | AQ2: Vervanging Sluis Panheel | AR2: Heroverweging aantal kolken/ functiereductie sluis | AS2: Nieuwe systeemeisen en/of -inrichting | AT2: Verlenging levensduur Sluis Panheel | AU2: Strengere waterveiligheidseis Sluis Panheel | AV2: Algemene beleidskeuzes op (inter)nationaal niveau
A3: Algemeen | K3: Effect van veranderend windklimaat op Brabantse kanalen nog nader te bepalen, verwachting is dat dit geen significante invloed heeft. | P3: EF9: Veranderingen in het gestuwde Maaspeil en het stuwprogramma beïnvloeden waterstanden en hydraulische belastingen. Er is onzekerheid over de bandbreedte van deze waterstanden en de mogelijke effecten op voorhavens, bodem en oeverbescherming. | S3: A5: Mogelijke toename van strengere wintercondities kan leiden tot hogere ijsbelastingen op constructies en sluisdeuren. Het is onduidelijk in hoeverre hiermee rekening moet worden gehouden in ontwerp en beoordeling, of dat dit via beheermaatregelen kan worden opgevangen. | AE3: ET5, C13, C14, C23, C24, A16: Risico's voor veiligheid en beschikbaarheid bij spanningsuitval. Daarnaast is de beschikbaarheid en kwaliteit van ontwerp- en beheersdata vanuit RWS onvoldoende, wat leidt tot inefficiëntie en hogere kosten bij opdrachtnemers. | AF3: A12: Leveranciers en aannemers hebben moeite met wisselingen, maar dit vormt hier geen direct probleem. Wel is er behoefte aan betere borging en overdracht van kennis bij veranderingen van leverancier. | AH3: C15: vragen rond energiegebruik, noodstroom en spanningsuitval. | AL3: A7, C12: Ontwikkelingen richting biologisch afbreekbare smeermiddelen en duurzamere toepassingen in hydraulische systemen vragen om aandacht en monitoring. | AM3: In hoeverre leiden ruimtelijke beperkingen op het complex tot arbo- en veiligheidsrisico’s, en is de veiligheid voldoende geborgd? ( wordt meegenomen in het onderhoud (tb3)). | AN3: ET1, ET2, C11: Hoe kan de constructieve veiligheid van bestaande sluizen worden beoordeeld, gegeven veranderende normen, en welke eisen en toetsingskaders zijn daarbij passend? | AO3: Het waterpeil in de kanalen is momenteel vast, maar er is onzekerheid over toekomstige ontwikkelingen in waterpeilen en of deze van invloed zullen zijn op het functioneren van sluis Panheel. | AR3: Het sluizencomplex heeft als enige in het kanaal twee kolken. Er is de vraag in hoeverre exploitatie met één kolk mogelijk is en welke gevolgen dit heeft, terwijl er vanuit de scheepvaart momenteel geen knelpunten worden ervaren. | AS3: Het sluizencomplex heeft als enige in het kanaal twee kolken. Er is de vraag in hoeverre exploitatie met één kolk mogelijk is en welke gevolgen dit heeft, terwijl er vanuit de scheepvaart momenteel geen knelpunten worden ervaren. | AV3: EF9, C20, C21: Er is onzekerheid over een mogelijke toekomstige rol van het kanaal als route voor defensie of als wateraanvoerroute richting België. Hoewel huidige afspraken geen veranderingen voorzien, is onduidelijk wat de gevolgen zouden zijn voor sluis Panheel als dit wel wijzigt.
A4: Sluisonderdelen/-componenten
A5: Oude (noord) sluis | F5: Driver heeft geen invloed | G5: driver heeft geen invloed | H5: driver heeft geen invloed | J5: driver heeft geen invloed | K5: driver heeft geen invloed. Checkvraag: is er hier een verandering in windklimaat? | L5: driver heeft geen invloed | P5: EF9: Veranderingen in het gestuwde Maaspeil en het stuwprogramma beïnvloeden waterstanden en hydraulische belastingen. Er is onzekerheid over de bandbreedte van deze waterstanden en de mogelijke effecten op voorhavens, bodem en oeverbescherming. | S5: A5: Mogelijke toename van strengere wintercondities kan leiden tot hogere ijsbelastingen op constructies en sluisdeuren. Het is onduidelijk in hoeverre hiermee rekening moet worden gehouden in ontwerp en beoordeling, of dat dit via beheermaatregelen kan worden opgevangen. | U5: driver heeft geen invloed | W5: driver heeft geen invloed | X5: Aanwezig sediment in het kanaal vormt geen probleem. | Y5: driver heeft geen invloed | Z5: driver heeft geen invloed | AA5: Bevers zijn aanwezig en vormen met name een aandachtspunt voor het kanaal. Voor de sluis (incl. spaarbekkens) levert dit geen problemen op zolang deze in gebruik zijn; er is eerder een bever waargenomen aan de noordzijde. | AC5: driver heeft geen invloed | AI5: driver heeft geen invloed | AJ5: A8: Hoe beïnvloeden budgettekorten de risico’s, het kennisbehoud (bij RWS en aannemers) en de instandhouding van de sluis, en hoe bepaalt dit de prioriteit van het object binnen de totale vloot? | AK5: Stikstofbeleid heeft geen directe invloed op het onderhoud van de sluis. | AP5: driver heeft geen invloed | AQ5: ET6: De betonconstructie van de oude sluis vertoont scheurvorming en nadert het einde van de ontwerplevensduur (circa 9 jaar). Het is onzeker in hoeverre de sluis nog voldoet aan de gestelde eisen. | AT5: ET6: In hoeverre is verlenging van de levensduur van het sluizencomplex mogelijk en welke factoren zijn daarbij bepalend? | AU5: driver heeft geen invloed
A6: Beton constructies: fundering, sluishoofd & sluiskolk | D6: C1, C2, C3, ET1, ET3, C6, X14: Onzekerheid over staat van beton en moeilijk inspecteerbare onderdelen (o.a. schermen) door gebrek aan data → risico op afkeuring; behoefte aan proportioneel beoordelingskader (oude vs. nieuwe normen), met benutting van kennis van vergelijkbare kunstwerken. Onzekerheid bodemgesteldheid en betonconstructies: Misschien kans om topologie (bodemgesteldheid) te vergelijken met andere locaties waar meer kennis is? | M6: Grondwaterstanden vormen een onzekerheid: het effect van verhoogde of verlaagde grondwaterstanden is nog onvoldoende inzichtelijk. Dit wordt momenteel niet als zorg gezien, maar is wel relevant voor het functioneren van onderloopbaarheidsschermen. | N6: Een toename van wateraanvoer vanuit het achterland wordt niet als invloedrijk beschouwd voor het functioneren van het sluizencomplex: De verwachting is dat er geen extra scheepvaart bij stremming op de Maas komt en dat voldoende afvoercapaciteit blijft. | V6: Onzekerheid over toegankelijkheid van kabelkokers in de sluishoofden (onder de sluis) en risico op verzakking van kabels en leidingen. | X6: driver heeft geen invloed | AE6: C16, C17: Hoe kunnen reparatietechnieken en boorkernonderzoek worden geoptimaliseerd om het beheer en onderhoud van betonconstructies efficiënter uit te voeren? Behoefte aan inzicht in inspectie- en monitoringsmethoden en borging van veiligheid en beschikbaarheid. | AG6: Inspecties leveren waardevolle informatie op voor de beoordeling en het beheer van de constructie. | AK6: driver heeft geen invloed
A7: Spaarbekkens, riolen & nivelleermiddel | D7: EF21: Spaarbekkens functioneren niet maar zijn belangrijk voor waterbesparing (droogte) - functie vraag | M7: Driver heeft geen invloed | N7: Spaarbekkens verminderen het schutverlies met ca. 6.000 m³ per schutting. | R7: Inzet van de oude sluis in combinatie met spaarbekkens biedt de meest optimale waterbesparing bij droogte.
A8: Sluisdeuren | E8: C5, C6, ET4: Vermoeiing niet meegenomen in ontwerp; beheer via inspectie en reparatie, maar weinig inzicht in resterende levensduur en scheurgroei (ook afhankelijk van gebruik). Geldt ook voor bewegingswerken; geen reservedeuren nieuwe sluis. Bij de stalen sluisdeuren van met name de nieuwe sluis is sprake van vermoeiingsscheuren. Deze zijn recent hersteld, maar er is onvoldoende inzicht in de snelheid van sterkteafname over de tijd. | AB8: Variaties in het aantal bewegingen (te veel of te weinig) beïnvloeden de belasting; meer bewegingen verhogen het risico op vermoeiing, maar hangen niet direct samen met veranderingen in scheepvaartverkeer.
A9: Remmings en geleidewerken
A10: Aanvaarbeveiliging | D10: Er is ruime kennis en data beschikbaar over bodem, taluds en oeverbescherming, waaronder inspecties van de sluisbodem en multibeam-inmetingen. De levensduur van de bodembescherming blijft een aandachtspunt, maar vormt geen directe kennisvraag en is met aanvullend onderzoek te bepalen.
A11: Bodem- en oeverbescherming, talud | D11: Kennis is wel veel aanwezig. Bodem van de sluis is geinspecteerd (beton). Levensduur van bodembescherming? Multibeam inmetingen zijn er, beeld komt/is er dus. Niet persé kennisvragen hier, met onderzoek is hier uit te komen.
A12: Aandrijving en bewegingswerken | D12: Geen vragen. | AB12: Variaties in het aantal bewegingen (te veel of te weinig) beïnvloeden de belasting; meer bewegingen verhogen het risico op vermoeiing, maar hangen niet direct samen met veranderingen in scheepvaartverkeer. | AG12: De tandwielkast kon niet worden geïnspecteerd vanwege markttechnische beperkingen.
A13: Voorhavens
A14: Nieuwe (zuid) sluis: | P14: EF9 | S14: A5: Mogelijke toename van strengere wintercondities kan leiden tot hogere ijsbelastingen op constructies en sluisdeuren. Het is onduidelijk in hoeverre hiermee rekening moet worden gehouden in ontwerp en beoordeling, of dat dit via beheermaatregelen kan worden opgevangen.
A15: Beton constructies: fundering, sluishoofd & sluiskolk | D15: C1, C2, C3, ET2, C4 | AB15: Door grotere schepen wordt vaker gebruik gemaakt van de nieuwe sluis, wat leidt tot een toename in waterverbruik. | AE15: C16, C17: Hoe kunnen reparatietechnieken en boorkernonderzoek worden geoptimaliseerd om het beheer en onderhoud van betonconstructies efficiënter uit te voeren? Behoefte aan inzicht in inspectie- en monitoringsmethoden en borging van veiligheid en beschikbaarheid.
A16: Sluisdeuren | E16: C5, C6, ETL4: Vermoeiing niet meegenomen in ontwerp; beheer via inspectie en reparatie, maar weinig inzicht in resterende levensduur en scheurgroei (ook afhankelijk van gebruik). Geldt ook voor bewegingswerken; geen reservedeuren nieuwe sluis. Bij de stalen sluisdeuren van met name de nieuwe sluis is sprake van vermoeiingsscheuren. Deze zijn recent hersteld, maar er is onvoldoende inzicht in de snelheid van sterkteafname over de tijd. | AB16: De nieuwe sluis is ontworpen voor scheepstypen die hier niet meer voorkomen. Dit roept de vraag op of beide sluizen in de huidige vorm in stand moeten worden gehouden.
A17: Remmings en geleidewerken
A18: Aanvaarbeveiliging
A19: Bodem- en oeverbescherming, talud
A20: Aandrijving en bewegingswerken | D20: De mechanische aandrijving en hydraulische systemen functioneren betrouwbaar en zijn goed vervangbaar. De beoordeling van restlevensduur, met name van tandwielen, is echter onzeker: berekeningen zijn vaak conservatief en leiden tot onderschatting van de werkelijke levensduur, terwijl praktijkobservaties (zoals staat van tandvlakken) en veranderende belastingen een genuanceerder beeld geven.
A21: Voorhavens
A22: Gemaal: | D22: Er is eerder nagedacht over uitbreiding met een derde pomp om droogte op te vangen en redundantie te vergroten; dit zou de beschikbaarheid verbeteren, maar is momenteel niet gebudgetteerd. Restlevensduur pompen onbekend. | P22: EF9: Veranderingen in het gestuwde Maaspeil en het stuwprogramma beïnvloeden waterstanden en hydraulische belastingen. Er is onzekerheid over de bandbreedte van deze waterstanden en de mogelijke effecten op voorhavens, bodem en oeverbescherming. | S22: A5: Mogelijke toename van strengere wintercondities kan leiden tot hogere ijsbelastingen op constructies en sluisdeuren. Het is onduidelijk in hoeverre hiermee rekening moet worden gehouden in ontwerp en beoordeling, of dat dit via beheermaatregelen kan worden opgevangen. | AB22: Het niet functioneren van pompen kan leiden tot langdurige onbeschikbaarheid en wordt als calamiteit beschouwd, gezien eerdere situaties waarin met spoed een gemaal moest worden geplaatst toen de 2 pompen uitvielen. | AD22: Het gemaal is niet voorzien van beveiliging; bediening vindt op afstand plaats. Cybersecurity is hierbij meegenomen, maar toepassing daarvan op dit sluizencomplex is niet voorzien. | AE22: C10: Welke inspectietechnieken kunnen worden ingezet om de staat van moeilijk toegankelijke onderdelen van het gemaal betrouwbaar in beeld te brengen?
A23: Opstal (gemaal) + Pompkelder (beton) | D23: C7, EF24: Zorgen over betrouwbaarheid en levensduur pompen bij mogelijk intensiever gebruik; wens voor visvriendelijker gemaal. | AA23: EF24: Het gemaal is sterk visontvriendelijk en wordt regelmatig gebruikt, wat leidt tot vissterfte. Er is onduidelijkheid over de eisen vanuit natuur en KRW en de mogelijkheden om het gemaal visvriendelijker te maken. | AH23: C18: Toepassing van pompen als turbine (energieopwekking) is eerder verkend, maar blijkt in de huidige situatie niet haalbaar door trillingen en schade aan installaties. Tegelijk is er een generieke vraag naar de potentie van turbineren en de benodigde aanpassingen aan het systeem.
A24: Doorlaatkoker (gemaal) | D24: C9, C10: Wat is de actuele staat van de leidingen (kokers) van het gemaal naar de uitstroom en hoe kan deze betrouwbaar worden vastgesteld? | F24: Geen zorgen
A25: Terrein / objectoverstijgende voorzieningen: | D25: Toegankelijkheid bij calamiteiten is over het algemeen voldoende (weg en parkeerterrein aanwezig), maar het middengebied is lastiger bereikbaar door de spaarbekkens; dit vormt naar verwachting geen groot knelpunt.
A26: Bediening en besturing | AE26: A9: Bediening en besturing (o.a. camera’s, noodstop en lokale/mobiele bediening) worden steeds complexer en vragen om regelmatige vernieuwing. Er is een wens tot verdere standaardisatie, maar in de praktijk leidt dit tot knelpunten en blijft behoefte bestaan aan object-specifieke oplossingen. | AM26: A6
A27: Kerende constructies (specifiek voorhavens Maaszijde) | D27: Damwanden vallen onder de kerende constructies; er is geen kennisvraag. Inspectievraag: wat is de levensduur van de damwanden. Dit onderzoek loopt.
A28: Energievoorziening | D28: P: Aandachtspunt voor elektrische veiligheid; spanning en installaties van het gemaal dienen te worden geactualiseerd. -> Wat is de actuele elektrische veiligheid van het gemaal en welke maatregelen zijn nodig om te voldoen aan de huidige normen? | V28: Er is geen sprake van bodemdaling in het gebied; lokale verzakkingen kunnen wel optreden. Kabels en leidingen, evenals de laagspanningsinstallatie van het gemaal, worden naar verwachting meegenomen in het V&R-proces.
A29: Overige aspecten: | D29: P: Besturing inrichten: spuien als gemaal, richtlijnen machine veiligheid & RTC
A30: Operatie en B&O | D30: De technische complexiteit is hoog, maar B&O wordt voornamelijk belemmerd door contractuele, budgettaire en organisatorische factoren (beslismacht buiten RWS), waardoor terugkerend groot onderhoud stagneert en sterk afhankelijk is van politieke keuzes. Er is een wens tot verdere standaardisatie binnen B&O.
A31: Riolen (spui / omloop) | D31: Staat riolen (spui/omloop) afhankelijk van betonkwaliteit, scheuren en afdichting; onderwaterinspecties nodig, uitvoering grotendeels binnen eigen organisatie. | AE31: Drone-inspecties ontwikkelen zich snel; inzet van duikers wordt waar mogelijk vermeden.
A33: Algemeen / WVTTK | N33: A1: Klimaatscenario's vertalen naar hydraulische randvoorwaarden | AB33: A2: Klimaatscenario's vertalen naar lokale scenario's
E36: Legenda | G36: Driver niet aanwezig | I36: Invloed driver beperkt of | N36: Invloed driver is | R36: Heeft invloed, kennisvraag
G37: of heeft geen invloed | I37: op te lossen binnen BenO | N37: een kennisvraag | R37: wanneer en oplossingsrichtingen

Sheet EFL sluizen
K1: Klimatologische en natuurlijke ontwikkelingen | AB1: Socio-economische ontwikkelingen | AJ1: Beleidsmatige ontwikkelingen
A2: Categorie | B2: Functies | C2: Autonome situatie | D2: Huidige eisen | E2: Huidige (en ontwerp) staat en constructieve beoordeling | F2: Vermoeiing | G2: Slijtage | H2: Schade (aanvaar, temperatuursinvloeden) | I2: Degradatie | J2: Drivers | K2: Zeespiegelstijging | L2: Verandering windklimaat | M2: Verandering golfklimaat | N2: Toename piekafvoer Maas & Rijn | O2: Toename frequentie hoogwater Maas & Rijn | P2: Afname rivierafvoer Maas & Rijn (voornamelijk in zomer) | Q2: Toename frequentie laagwater Maas & Rijn (voornamelijk in zomer) | R2: Verandering Neerslagpatroon | S2: Verandering van luchttemperatuur | T2: Verandering van watertemperatuur | U2: Toename CO2-gehalte in de lucht | V2: Bodemdaling | W2: Verzilting | X2: Verandering sedimenttransport en bodemerosie | Y2: Verandering afvoer verdeling rijn-maas monding | Z2: Verandering in bodemligging | AA2: Verandering (eisen aan) biodiversiteit in ecosysteem | AB2: Verandering scheepvaartverkeer | AC2: Verandering bebouwing en/of verhoging waarde bebouwd achterland | AD2: Verandering in benodigd veiligheidsniveau | AE2: Technische ontwikkelingen (software, materiaal) | AF2: Verandering situatie leverancier | AG2: Verlies van kennisdragers (pensioenering/vertrek), zowel bij RWS, als aannemers, Deltares. | AH2: Energietransitie | AI2: Toename ecologische waarde sluis Panheel | AJ2: Verandering onderhoudsbudget Sluis Panheel | AK2: Stikstofbeleid | AL2: Verbod op gebruik materialen | AM2: Aanscherping arbo veiligheidsnorm | AN2: Aanpassing sluitpeil | AO2: Zoutindringing | AP2: Vervanging sluis Panheel | AQ2: Heroverweging aantal kolken/ functiereductie sluis | AR2: Nieuwe systeemeisen en/of -inrichting | AS2: Verlenging levensduur sluis Panheel | AT2: Strengere waterveiligheidseis sluis Panheel | AU2: Algemene beleidskeuzes op (inter)nationaal niveau | AV2: duurzaamheid, beschikbaarheid materialen
A4: Algemeen / integraal | G4: driver heeft geen invloed | H4: driver heeft geen invloed | I4: driver heeft geen invloed | J4: EF1, EF2, EF22: integraal plan voor de lange termijn, meer dan 30 jaar vooruit, ontbreekt. Hoe kunnen we keuzemomenten en adaptatiepaden identificeren en rekening houden met de langere termijn bij keuzes op de kortere termijn? Inclusief budgetverminderingen, kennisbehoud. | K4: driver heeft geen invloed | L4: driver heeft geen invloed | M4: driver heeft geen invloed | O4: driver heeft geen invloed | R4: driver heeft geen invloed | S4: driver heeft geen invloed | T4: driver heeft geen invloed | U4: driver heeft geen invloed | V4: driver heeft geen invloed | W4: driver heeft geen invloed | X4: driver heeft geen invloed | Y4: driver heeft geen invloed | Z4: driver heeft geen invloed | AA4: Bij verbouwing en grootscheepse aanpassingen: Inventarisatie omliggende natuur nodig. | AC4: driver heeft geen invloed | AD4: driver heeft geen invloed | AE4: Hoe kun je AI inzetten op een betrouwbare manier? Hoe zet je de experts in om de AI uitkomsten te checken/valideren? Ook AI-ontwikkeling kan een gevaar zijn, want nieuwe medewerkers/nieuwe generatie vertrouwen daar veel op. Andere kant ook een kans natuurlijk qua data. | AF4: A10: Hoe zorg je voor kennisniveau op de markt op niveau en kenniscontinuiteit bij marktpartijen? | AG4: A11, A12. A13, A14, A15: Hoe behoud je de benodige kennis voor B&O en vervanging/renovatie/vernieuwing binnen de organisatie (RWS)? RWS collega's met echt inhoudelijke kennis van zaken worden minder, echt een ding voor toetsing van stukken opdrachtnemers of aannemers. KV: Kennisbehoud bij overige partners (bijvoorbeeld Wallonie): Samenwerking in de toekomst onzeker: Maas afvoerverdrag treedt in werking bij laag water, geen verdrag met Wallonië. Naleving gaat wel goed nu, als er nieuwe mensen zijn is er wel een risico misschien. Voor oude sluizen neemt de beschikbaarheid van materialen en specifieke kennis af, waardoor vervanging niet altijd één-op-één mogelijk is en risico’s voor de beschikbaarheid ontstaan. Kennis is bovendien geconcentreerd bij een beperkt aantal personen. De externe capaciteit in de aannemerij is een aandachtspunt; er zijn weinig onderhoudscontracten, terwijl de vraag naar uitvoering en onderhoud naar verwachting zal toenemen. | AJ4: EF1, C19: Visie welke functies op welk niveau behouden / loslaten bij afnemend onderhoudsbudget? | AL4: driver heeft geen invloed | AM4: driver heeft geen invloed | AN4: driver heeft geen invloed | AO4: driver heeft geen invloed | AP4: driver heeft geen invloed | AQ4: driver heeft geen invloed | AR4: EF9: Veranderingen in het gestuwde Maaspeil en het stuwprogramma beïnvloeden waterstanden en hydraulische belastingen. Er is onzekerheid over de bandbreedte van deze waterstanden en de mogelijke effecten op voorhavens, bodem en oeverbescherming.
A5: Peilbeheer en waterveiligheid | B5: Water vasthouden (peilbeheer) | E5: Oude spaarkommen bij de Oude Sluis doen het niet | P5: EF7; EF8: Wat wordt de toekomstige waterbalans watersysteem bij droogte (relatie met nationaal waterplan & ook toekomstige watervraag brabantse kanalen): Uitgewerkt naar verliezen (lek en schut), inzet spaarbekkens, inzet pompen, waterbeschikbaarheid in stuwpand Linne (voor oppompen). Wat wordt de toekomstige waterverdeling over het grotere geheel (Maastricht -> Linne). Hoe ga je dat doen door de seizoenen heen. Nu op onderbuikgevoel. Ik stuur nu meer door de grensmaas omdat de natuur daar kwetsbaar is. Samenwerking met Belgie moet worden versterkt: Hun beleidskeuzes en die in NL afstemmen en sturing beter coordineren. KV: Wat zijn de eisen aan het lekverlies en schutverlies? Kun je dan beoordelen of je de spaarbekkens hier iets in kunnen doen en of dat ook nuttig is voor het systeem? Als je veel te weinig water hebt, wat is dan acceptabel qua schutverlies maar ook lekverlies want dat is 24/7 een ding? Altijd pompen is niet wenselijk qua duurzaamheid maar je hebt bij laag water ook maar beperkte beschikbaarheid. Een deel van het water wordt ook verder gebruikt in het systeem namelijk. In het volgende NWP pleiten we voor een redeneerlijn waterverdeling voor de Grensmaas, het Julianakanaal en de MLNBK. Daar komen dezelfde kennisvragen ook naar voren. | AU5: A3: Toekomstige afweging tussen duurzaamheid vs. verdringingsreeks, maar ook energieverbruik en circulariteit van aanleveren van componenten. Door te pompen blijf je zo lang mogelijk weg uit je verdringingsreeks, eerst doe je pompen tbv scheepvaart (lekverlies werkt hier op door), dit heb je tot de verdringingsreeks ingaat. Peilbeheer moet je altijd doen, want dat is categorie 1 (waarbij natuurbehoud Peel prio boven scheepvaart). Je wilt onnatuurlijke maatregelen zo lang mogelijk uitstellen. Pompen zijn ook niet altijd beschikbaar, dan gaat eerst de scheepvaart eruit, daarna het peilbeheer eruit. Lekverlies beperken gaat dit niet voorkomen, maar je stelt het wel uit. Dus hoeveel kun je het uitstellen is kennisvraag. | AV5: Zijn er bijv. materialenpaspoorten aanwezig om circulair gebruik te faciliteren? Wordt aan gewerkt, veel informatie is, maar moet her en der nog aangevuld worden. IAC?-inspecties een klein beetje uitbreiden om bij een vervanging of renovatie dit ergens anders in te zetten. Actuele informatie nodig. KV: hoe kunnen we met circulariteit omgaan (overkoepelend over de sluizen)?
B6: Keren water (waterveiligheid, kanaalzijde oevers tot aan de sluis, niet de sluis zelf) | D6: Wat is de versterkingsopgave Panheel? Afgekeurde keringen moeten misschien aangepakt worden, maar keringen hoeven waarschijnlijk niet hoger, want peil hangt ook samen met hoogte van de bruggen. | AJ6: Ook kering die aangepakt moet worden wordt lastig als budgetten minder worden. | AV6: driver heeft geen invloed
B7: Spuien water/ Afvoeren van overtollig water (peilbeheer). Spuien is door de sluizen (spuiwerkje (buis) tussen de nieuwe en de oude sluis wordt al jaren niet meer gebruikt). | N7: EF7: Waterafvoerfunctie voldoende in de toekomst? Je kan ook naar het noorden water afvoeren | AB7: EF10;EF2: Hoe in toekomst water afvoeren: Alleen via spuien door de kolk of via andere route mogelijk maken? Als uitfaseren 1 sluis. Risico voor robuustheid beheer watersysteem (specifiek spui-functie). | AT7: EF2, EF10, EF25: onbekend of eisen veranderen
A8: Leefbaarheid | B8: Schutverlies beperken dmv spaarbekkens (peilbeheer) | D8: EF20; EF21: Hoe kunnen de spaarbekkens, riolen en het nivelleermiddel van de oude (noordelijke) sluis technisch en functioneel weer in gebruik worden genomen? Spaarbekkens functioneren niet maar zijn belangrijk voor waterbesparing (droogte) - functie vraag | P8: P: minder Maaswater beschikbaar in droge perioden, in de toekomst nog zuiniger omgaan met water | AF8: (onderdeel A10) Verandering van leverancier heeft ervoor gezorgd dat materiaalkeuze verkeerd is geweest waardoor spaarbekkens niet meer werken. Materiaalkeuze en levering van kwaliteit gaat achteruit. Vanuit aannemers wordt aangegeven dat de boel vervangen moet worden, maar wordt er door experts van RWS dan wel bijgestuurd. Heeft ook te maken met kennisverlies binnen RWS. Specialistische kennis gaat achteruit en is minder aanwezig binnen organisatie. | AR8: Zie kolom Q/R | AU8: Wat als Vlaanderen (verdrag) of Wallonie (geen verdrag) meer water wil vasthouden? Dan moeten nog zuiniger omgegaan worden met het water.
B9: Water pompen (peilbeheer) | D9: Onbekend wat (hoe vaak, hoe veel) huidige inzet pompen is voor peilhandhaving. | E9: EF24: hoe kan zoveel mogelijk voorkomen worden dat vissen vermalen worden in het gemaal? | F9: C7: Robuustheid pompen onzeker door groter gebruik dan eerder ingeschat | P9: EF7: Wat is toekomstige waterverdeling en waterbeschikbaarheid in combinatie met andere beleidskeuzes en daarmee inzet pompen? Seizoensafhankelijkheid niet onderzocht nog (binnen Klimaatbestendige netwerken). Hoe ver kan je uitstellen dat je peil niet kunt handhaven door lekverlies te beperken. Eer zijn nu 2 pompen, moeten we gaan denken aan een 3e pomp? | AA9: EF23: Welke eisen stelt de KRW en natuurwetgeving aan het functioneren van een gemaal met betrekking tot visvriendelijkheid en vispasseerbaarheid? | AH9: P: Toekomstige pomp met turbine-functie? | AI9: EF23 | AR9: Zie kolom Q/R | AU9: Wat als Vlaanderen (verdrag) of Wallonie (geen verdrag) meer water wil vasthouden? Dan moeten nog zuiniger omgegaan worden met het water.
B10: Waterkwaliteit | AA10: EF13, EF23: Mogelijke aanpassing eisen waterkwaliteit en ecologie watersysteem: vissterfte gemaal, blauwlagen, etc. Waterkwaliteit en ecologie: voedingsvijver van het pompgemaal, bijv. blauwalg die je dan het kanaal binnen haalt. Vissterfte door aanzetten gemaal. Maatregelen dat vissen er niet gaan nestelen. KRW opgave in het kanaal is heel laag. Liever voorkomen dat vissen in de pompen komen, maar moet geen aantrekkende kracht hebben. Laagdrempelige oplossing is opzich welkom. Chemische waterkwaliteit: blauwalg en wel punten voor waterkwaliteit maar heeft niet persé met het complex te maken. Wel een ding welke kan het op stroomt. Als je niets meer doet bij Panheel dan is er geen afvoer, maar zolang we daar blijven varen is er beweging. Niet echt een probleem nu. P: Groeiende urgentie van natuurwaarden en waterkwaliteit raakt hier misschien ook aan. Dus zou ook mee kunnen tellen. Een plek waar reeën het water uit kunnen is ook een ding (fauna-uittredeplaatsen), zou meer zijn bij grote schepen. Maar hier minder relevant want ook vrijwel geen natuurvriendelijke oevers. | AI10: EF23 | AK10: EF13: In hoeverre gaat Natura2000 richtlijnen voor stikstof in de toekomst de scheepvaart beinvloeden (alternatief via A2 (naast sluis) is minder wenselijk). | AR10: EF13: invloed KRW (nieuwe wetgeving) op bestaande objecten; Wat is natuuropgave voor kanaal in toekomst? Mogelijkheid voor kanaal natuurvriendelijker maken: Natuurlijke oevers en uittreedtplaatsen voor Reeen
B11: Ecologie | D11: Welke eisen worden gesteld aan de sluis irt vissen? | AK11: Quickscans ecologie worden gedaan bij werkzaamheden.
B12: Cultuurhistorische waarde | AS12: EF14: Als oude sluis monumentstatus krijgt, wat betekent dit voor het B&O en Verniewing? Cultuurhistorie: het oude complex is heel slim ingericht, dus moeten we behouden! En door vrouw (Elsa van der Ban) ontworpen! Informatiebord vervangen.
A13: Bereikbaarheid | B13: Faciliteren scheepvaart | D13: EF15, EF26: Wat zijn de beschikbaarheidseisen van schutsluizen – harde eisen ten opzichte van wensen (schuttijden / passagetijden en stremmingen). | E13: EF16; A5: Voldoet sluis aan richtlijn vaarwegen? (waterbouw en bodembescherming voorhavens, drempels en beschadigingen: trillingen deuren, troskrachten, passages schepen, nivelleren). Hoe vertaal je de eis op netwerkniveau naar een realistische eis op complex/objecten niveau? | AB13: EF15, EF17, EF27: Vraag of toekomst 2 sluiskolken noodzakelijk is. En wat implicaties zijn van uitffaseren 1 kolk. Blijven de klasse 5 schepen komen of moet je focussen op de kleinere scheepsmaat? Wat zijn en worden de vlootontwikkelingen? Rob Konings check? Gaat het er echt naartoe dat de kleine schepen eruit gaan of dat er specifieke scheepsmaten blijven en overslag daarbij. Nieuwe kolk is geschikt voor klasse 5, remmingswerken en de rest van het kanaal is er niet klaar voor. Je sluiskolk is geschikt, maar er is maar 1 bedrijf die deze capaciteit nodig heeft. Op de rest van het kanalenstelsel is er wel vraag naar klasse 5 (ri. Veghel en Tilburg, Beatrixkanaal, Helmond), maar voor Panheel is de roep heel klein. Zien we nog ontwikkelingen die wel 5 nodig hebben? Er is nog nooit eerder afgeschaald (als RWS?). Misschien wordt in de toekomst wel de afweging gemaakt voor kosten vs. het gebruik van de nieuwe sluis? Is 1 kolk voldoende als aantal schuttingen beperkt blijft (incl consequenties qua interrupties voor onderhoud)? | AH13: EF18: Er is niet duidelijk wat de richtllijnen zijn rondom walstroom (stroomvoorziening (electrische) schepen) bij sluizen. Wat zijn de kaders voor walstroom bij de rijksaanlegplaatsen, is dit nog actueel en wat geldt er voor een sluis zoals bij Panheel? | AJ13: EF19: Waar kun je bezuinigen op scheepvaartveiligheid zonder dat de veiligheid in het geding komt? Deze komt als eerst in de knel wanneer het onderhoudsbudget minder wordt ivm pompen. Gemaal en scheepvaartsfunctie staan beide onder druk.
A14: Overige functies | B14: Faciliteren van bediening
B15: Calamiteiten | D15: P: Gemaal kan ingezet worden bij ontreinigingsongelukken in zuid-willemsvaart. Geen kennisvraag. Niet besproken wat toekomstige risico's en kansen zouden betekenen. | AR15: x
J20: Legenda | L20: Driver niet aanwezig | O20: Invloed driver beperkt of | T20: Invloed driver is | W20: Heeft invloed, kennisvraag
L21: of heeft geen invloed | O21: op te lossen binnen BenO | T21: een kennisvraag

Sheet Opzet kennisagenda
B1: Tussenstap opzet kennisagenda - vragen geclusterd op componentvragen, ETL-vragen, EFL-vragen en A-vragen
B2: C-vragen (Component)
A3: {=_xlfn.SORTBY(_xlfn._xlws.FILTER('Kennisagenda onderzoekslijnen'!C20:C200,LEFT('Kennisagenda onderzoekslijnen'!C20:C200,1)="C"),_xlfn._xlws.FILTER('Kennisagenda onderzoekslijnen'!I20:I200,LEFT('Kennisagenda onderzoekslijnen'!C20:C200,1)="C"),1)} -> C1 | B3: {=_xlfn.SORTBY(_xlfn._xlws.FILTER(""&'Kennisagenda onderzoekslijnen'!F20:F200,LEFT('Kennisagenda onderzoekslijnen'!C20:C200,1)="C"),_xlfn._xlws.FILTER('Kennisagenda onderzoekslijnen'!I20:I200,LEFT('Kennisagenda onderzoekslijnen'!C20:C200,1)="C"),1)} -> Hoe bepaal je de kwaliteit en variabiliteit van het historische (ongewapende) beton van de oude sluis?
A4: C2 | B4: Hoe kan de huidige staat van moeilijk inspecteerbare onderdelen (zoals onderloopsheidschermen) betrouwbaar worden bepaald, gegeven het ontbreken van directe inspectie en meetgegevens?
A5: C3 | B5: Welke lessen uit vergelijkbare sluizen (zelfde bouwjaar, typologie, ondergrond, constructiemethode) zijn bruikbaar voor de beoordeling en instandhouding van de betonconstructies van sluis Panheel, en hoe kan met deze kennis de onzekerheid in bodemgesteldheid en betonconstructies worden verkleind?
A6: C4 | B6: In hoeverre is de RBK (richtlijn bestaande kunstwerken) met de bijbehorende aanpak constructieve veiligheid sluizen geschikt om tot een goed oordeel te komen voor de betonconstructies van sluis Panheel? En welke gegevens hebben we daarvoor nodig?
A7: C5 | B7: Hoe ontwikkelt vermoeiingsschade in stalen sluisdeuren zich over de tijd en wat betekent dit voor de resterende sterkte en levensduur?
A8: C6 | B8: In hoeverre is een beheerstrategie op basis van inspectie en reparatie voldoende om vermoeiingsschade tijdig te signaleren en falen te voorkomen?
A9: C7 | B9: Wat is de resterende levensduur en betrouwbaarheid van de pompen (bij toenemend watergebruik en mogelijk langere droge periodes), en in hoeverre zijn deze geschikt voor mogelijk intensiever gebruik?
A10: C9 | B10: Wat is de actuele staat van de leidingen (kokers) van het gemaal?
A11: C10 | B11: Welke inspectietechnieken kunnen worden ingezet om de staat van moeilijk toegankelijke onderdelen van het gemaal betrouwbaar in beeld te brengen?
A12: C11 | B12: Zouden nieuwe onderdelen aan de ROK – constructieve veiligheidseis - moeten voldoen als de rest van het complex daar niet aan voldoet (Is dat dan niet een te hoge eis?)? Afwegingskader: moet je de hoogste kaders / normen gebruiken of is een lagere eis soms voldoende?
A13: C12 | B13: Wat is de potentie voor hergebruik van materialen/elementen?
A14: C13 | B14: Hoe kan de beschikbaarheid van systemen in oude sluizen worden geborgd, gegeven de beperkte beschikbaarheid van specifieke materialen en kennis?
A15: C14 | B15: Hoe kan de beschikbaarheid en kwaliteit van ontwerp-, beheer- en inspectiedata worden verbeterd om uitvoering en onderhoud efficiënter en beter voorspelbaar te maken?
... A25: C24 | B25: Welke standaard oplossing is te bedenken voor redundantie voor stroom of glasvezel?
B28: ETL-componentsniveau vragen (Einde levensduur)
A29: {=_xlfn.SORTBY(_xlfn._xlws.FILTER('Kennisagenda onderzoekslijnen'!C20:C200,LEFT('Kennisagenda onderzoekslijnen'!C20:C200,2)="ET"),_xlfn._xlws.FILTER('Kennisagenda onderzoekslijnen'!I20:I200,LEFT('Kennisagenda onderzoekslijnen'!C20:C200,2)="ET"),1)} -> ET1 | B29: {=_xlfn.SORTBY(_xlfn._xlws.FILTER(""&'Kennisagenda onderzoekslijnen'!F20:F200,LEFT('Kennisagenda onderzoekslijnen'!C20:C200,2)="ET"),_xlfn._xlws.FILTER('Kennisagenda onderzoekslijnen'!I20:I200,LEFT('Kennisagenda onderzoekslijnen'!C20:C200,2)="ET"),1)} -> Wat is de actuele constructieve veiligheid van de betonconstructies van de oude sluis Panheel, gegeven dat de ontwerplevensduur is bereikt, en welke onzekerheden beïnvloeden deze beoordeling?
A30: ET2 | B30: Wat is de actuele constructieve veiligheid van de betonconstructies van de nieuwe sluis Panheel, gegeven dat de ontwerplevensduur nog niet is bereikt, en welke onzekerheden beïnvloeden deze beoordeling?
A31: ET3 | B31: Welke functionele eisen worden aan sluizencomplex Panheel gesteld en in hoeverre moeten constructieve componenten van de oude sluis hierop worden aangepast volgens den huidige normen?
A32: ET4 | B32: Welke mate van redundantie (bijv. reservedeuren of alternatieven) is nodig om de beschikbaarheid en robuustheid van het sluizencomplex te borgen?
A33: ET5 | B33: Welke risico’s voor veiligheid en beschikbaarheid ontstaan bij langdurige spanningsuitval voor welke functies, hoe erg is dit, en waar zijn noodstroomvoorzieningen (zoals aggregaten) noodzakelijk binnen het sluizencomplex? Hoe ziet een draaiboek bij stroomuitvalling eruit?
A34: ET6 | B34: In hoeverre is verlenging van de levensduur van het sluizencomplex (oude sluis) mogelijk en welke factoren zijn daarbij bepalend?
B37: EFL-vragen (Einde Functioneel)
A38: {=_xlfn.SORTBY(_xlfn._xlws.FILTER('Kennisagenda onderzoekslijnen'!C20:C200,LEFT('Kennisagenda onderzoekslijnen'!C20:C200,2)="EF"),_xlfn._xlws.FILTER('Kennisagenda onderzoekslijnen'!I20:I200,LEFT('Kennisagenda onderzoekslijnen'!C20:C200,2)="EF"),1)} -> EF1 | B38: {=_xlfn.SORTBY(_xlfn._xlws.FILTER(""&'Kennisagenda onderzoekslijnen'!F20:F200,LEFT('Kennisagenda onderzoekslijnen'!C20:C200,2)="EF"),_xlfn._xlws.FILTER('Kennisagenda onderzoekslijnen'!I20:I200,LEFT('Kennisagenda onderzoekslijnen'!C20:C200,2)="EF"),1)} -> Wat is de lange termijn visie/plan voor de toekomst van sluizencomplex Panheel, rekeninghoudend met veranderende wensen/gebruik (functies), budgetverminderingen, kennisbehoud, etc. (incl. keuzemomenten en adaptatiepaden)?
A39: EF2 | B39: Wat zijn de effecten van exploitatie met één kolk op beschikbaarheid, scheepvaart (inclusief voorhavens) en beheer, en welke sluis is daarbij het meest geschikt om te behouden?
A40: EF7 | B40: Wat wordt de toekomstige waterbalans van het watersysteem waarvan Panheel een onderdeel uitmaakt (inclusief traject Maastricht - Linne & samenwerking met Belgie) voor de verschillende seizoenen (inclusief wateroverlast en droogte)?
A41: EF8 | B41: Welke eisen worden gesteld aan de verschillende functies (water bergen en water afvoeren) en componenten (lekverlies, schutverlies, spaarbekkens) van sluis Panheel?
A42: EF9 | B42: Wat zijn de (toekomstige) beleidskeuzes rondom Maaspeilen en het stuwprogramma, en wat is de invloed hiervan op waterstanden, hydraulische belastingen en het functioneren van het sluizencomplex (incl. bevaarbaarheid, voorhavens, bodem en oeverbescherming)?
A43: EF10 | B43: Is het in de toekomst, bij een grotere afvoerbehoefte, nodig om andere routes te gebruiken dan spuien via de kolk?
A44: EF13 | B44: Wat zijn de toekomstige eisen aan sluizencomplex en kanaal voor waterkwaliteit, ecologie en natuuropgaven (zoals vissterfte bij gemalen, blauwalgen, Natura 2000-stikstofeisen i.r.t. scheepvaart en passeerbaarheid, zoals natuurvriendelijke oevers)?
A45: EF14 | B45: Als de oude sluis een monumentstatus krijgt, wat betekent dit voor B&O en Vernieuwing?
A46: EF15 | B46: Wat zijn de beschikbaarheidseisen van schutsluizen – harde eisen ten opzichte van wensen (schuttijden / passagetijden en stremmingen) nu en in de toekomst?
A47: EF16 | B47: Voldoet sluizencomplex Panheel aan richtlijn vaarwegen?
A48: EF17 | B48: Wat is de verwachte ontwikkeling van de binnenvaart en gebruik van Sluizencomplex Panheel (incl. voorhavens) en welke voorzieningen zijn hiervoor nodig?
A49: EF18 | B49: Wat zijn de richtllijnen rondom walstroom (stroomvoorziening (electrische) schepen) bij sluizen? Wat zijn de kaders voor walstroom bij de rijksaanlegplaatsen? Voldoet de walstroomvoorziening van sluizencomplex Panheel aan de eisen?
A50: EF19 | B50: Waar kun je bezuinigen bij sluis Panheel zonder dat de veiligheid en functies in geding komen?
... A58: EF27 | B58: Wat is de invloed van de ontwikkelingen in de scheepvaart op de staat van de componenten en wat je van de componenten vraagt?
B61: Algemene kennisvragen over de sluizen heen
A62: {=_xlfn.SORTBY(_xlfn._xlws.FILTER('Kennisagenda onderzoekslijnen'!C20:C200,LEFT('Kennisagenda onderzoekslijnen'!C20:C200,1)="A"),_xlfn._xlws.FILTER('Kennisagenda onderzoekslijnen'!I20:I200,LEFT('Kennisagenda onderzoekslijnen'!C20:C200,1)="A"),1)} -> A1 | B62: {=_xlfn.SORTBY(_xlfn._xlws.FILTER(""&'Kennisagenda onderzoekslijnen'!F20:F200,LEFT('Kennisagenda onderzoekslijnen'!C20:C200,1)="A"),_xlfn._xlws.FILTER('Kennisagenda onderzoekslijnen'!I20:I200,LEFT('Kennisagenda onderzoekslijnen'!C20:C200,1)="A"),1)} -> Hoe kunnen klimaatscenario’s worden vertaald naar hydraulische randvoorwaarden voor het functioneren en de beoordeling van het sluizencomplex?
A63: A2 | B63: Hoe kunnen klimaatscenario’s worden vertaald naar lokale omstandigheden en randvoorwaarden voor het functioneren van het sluizencomplex?
A64: A3 | B64: Wat wordt de toekomstige afweging tussen duurzaamheid vs. verdringingsreeks, maar ook energieverbruik en circulariteit van aanleveren van componenten bij sluizen?
A65: A4 | B65: Hoe vertaal je de eis op netwerkniveau naar een realistische eis op complex/objecten niveau?
A66: A5 | B66: Wat is de invloed van mogelijke strengere winters op ijsbelasting van sluizen, en in hoeverre moet dit worden meegenomen in beoordeling, ontwerp of beheermaatregelen?
A67: A6 | B67: Welke eisen stellen de Machinerichtlijn en andere veiligheidskaders aan de besturing van spuien en gemalen, en wat betekent dit voor het ontwerp en beheer?
A68: A7 | B68: Welke duurzame alternatieven voor smeermiddelen en hydraulische systemen zijn toepasbaar en wat zijn de effecten op functioneren en betrouwbaarheid van het object?
A69: A8 | B69: Hoe om te gaan met de effecten van budgettekorten en het kennisbehoud (bij RWS en aannemers) op de risico's en de instandhouding van sluizen, en wat betekent dit voor de prioritering van objecten binnen het areaal?
A70: A9 | B70: Hoe kan een balans worden gevonden tussen standaardisatie en object-specifieke keuzes in bediening en besturing van sluizen?
A71: A10 | B71: Hoe zorg je voor kennisniveau en kenniscontinuïteit bij marktpartijen, inclusief borging bij leverancierwisselingen en personeelsverloop?
A72: A11 | B72: Hoe ontwikkelt de externe uitvoeringscapaciteit (bijvoorbeeld bij aannemers) voor het beheer en onderhoud van sluizen zich, en in hoeverre is deze toereikend voor de toekomstige opgave?
A73: A12 | B73: Hoe behoud je de benodige kennis voor B&O en vervanging/renovatie/vernieuwing binnen de organisatie (RWS)?
A74: A13 | B74: Hoe behoud je de benodige kennis voor operationele sturing (extreme condities), maar ook B&O en vervanging/renovatie/vernieuwing bij overige partners?
... A77: A16 | B77: Hoe kun je zorgen dat kennis uit onderzoeken voor één sluis ook gebruikt wordt bij andere sluizen?

Sheet Kennisagenda onderzoekslijnen
A1: Onderwerp hoofdnummer | B1: Onderwerp detailnummer | D1: Onderwerp vraag | E1: Overlap met andere vraag | F1: Dit tabblad is een tussenstap, waarbij de vragen geclusterd zijn per onderzoekslijn | G1: Onderwerp onderzoekslijn | H1: Toelichting | I1: Hulpkolom nummering (NIET VERWIJDEREN!)
F2: Algemene vragen
A3: 1 | B3: 1 | D3: Technische levensduur - civiele delen | F3: Hoe ontwikkelen schade, vermoeiing en degradatie zich in de civiele constructies en de bewegende delen van het sluizencomplex en wat betekent dit voor de constructieve veiligheid en resterende levensduur?
A4: 2 | B4: 2 | D4: Technische levensduur - installaties | F4: Hoe ontwikkelen slijtage, veroudering en storingen zich in de machines en installaties van het sluizencomplex en wat betekent dit voor de betrouwbaarheid, veiligheid en resterende levensduur?
A5: 3 | B5: 3 | D5: Inspecties, monitoring en data | F5: Hoe kunnen inspecties, monitoring en data de kwaliteit en betrouwbaarheid van technische beoordelingen vergroten?
A6: 4 | B6: 4 | D6: Hoogwaterveiligheid | F6: In hoeverre vervult het sluizencomplex nu en in de toekomst zijn functie als onderdeel van het systeem van primaire waterkeringen, en welke eisen stelt dit aan constructies, installaties en beheer?
A7: 5 | B7: 5 | D7: Watersysteem en waterbeschikbaarheid | F7: Welke ontwikkelingen in het huidige en toekomstige watersysteem zijn bepalend voor het functioneren van sluis Panheel en welke eisen stellen deze aan het sluizencomplex?
A8: 6 | B8: 6 | D8: Ecologie en waterkwaliteit watersysteem | F8: Hoe kan het sluizencomplex bijdragen aan het voldoen aan waterkwaliteits- en ecologische eisen voor het watersysteem, nu en in de toekomst?
A9: 7 | B9: 7 | D9: Functies van het complex in het netwerk (scheepvaart, weg en water) | F9: Welke functies vervult sluizencomplex Panheel binnen het vaarweg- en watersysteem, nu en in de toekomst en welke eisen stelt dit aan het sluizencomplex?
A10: 8 | B10: 8 | D10: Operatie: bediening en besturing | F10: Hoe kan het sluizencomplex onder reguliere en uitzonderlijke omstandigheden veilig, efficiënt en robuust worden bediend voor de functies die het vervult?
A11: 9 | B11: 9 | D11: Beschikbaarheid en robuustheid | F11: Hoe kunnen beschikbaarheid en robuustheid van het sluizencomplex worden geborgd?
A12: 10 | B12: 10 | D12: Stategie, afweging en keuzes | F12: Hoe kunnen integrale afwegingen worden gemaakt tussen prestaties, kosten en risico's? En welke ontwikkelingen zijn daarbij van belang?
A13: 11 | B13: 11 | D13: Milieu-impact | F13: Hoe kunnen we de milieu-impact van schutsluizen gedurende de gehele levenscyclus verminderen, door slimmer om te gaan met materialen, energieverbruik en CO₂-uitstoot?
A14: 12 | B14: 12 | D14: Organisatorische aspecten | F14: Hoe organiseren we governance, samenwerking en kennisborging zodat beheer, onderhoud en vernieuwing van het sluizencomplex toekomstbestendig en beheersbaar blijven?
A19: 1 | D19: Technische levensduur - civiele delen | F19: Hoe ontwikkelen schade, vermoeiing en degradatie zich in de civiele constructies en de bewegende delen van het sluizencomplex en wat betekent dit voor de constructieve veiligheid en resterende levensduur?
A20: 1 | B20: a | C20: C1 | E20: C22 | F20: Hoe bepaal je de kwaliteit en variabiliteit van het historische (ongewapende) beton van de oude sluis? | G20: Technische levensduur - civiele delen | I20: =VALUE(SUBSTITUTE(SUBSTITUTE(SUBSTITUTE(SUBSTITUTE(C20,"EF",""),"ET",""),"C",""),"A","")) -> 1
A21: 1 | B21: b | C21: C3 | F21: Welke lessen uit vergelijkbare sluizen (zelfde bouwjaar, typologie, ondergrond, constructiemethode) zijn bruikbaar voor de beoordeling en instandhouding van de betonconstructies van sluis Panheel, en hoe kan met deze kennis de onzekerheid in bodemgesteldheid en betonconstructies worden verkleind? | G21: Technische levensduur - civiele delen | H21: Loopt een onderzoek bij TNO (greta zoekt dit uit) | I21: =VALUE(SUBSTITUTE(SUBSTITUTE(SUBSTITUTE(SUBSTITUTE(C21,"EF",""),"ET",""),"C",""),"A","")) -> 3
A22: 1 | B22: c | C22: C4 | E22: ET1 | F22: In hoeverre is de RBK (richtlijn bestaande kunstwerken) met de bijbehorende aanpak constructieve veiligheid sluizen geschikt om tot een goed oordeel te komen voor de betonconstructies van sluis Panheel? En welke gegevens hebben we daarvoor nodig? | G22: Technische levensduur - civiele delen | I22: =VALUE(SUBSTITUTE(SUBSTITUTE(SUBSTITUTE(SUBSTITUTE(C22,"EF",""),"ET",""),"C",""),"A","")) -> 4
A23: 1 | B23: d | C23: ET1 | E23: C4 | F23: Wat is de actuele constructieve veiligheid van de betonconstructies van de oude sluis Panheel, gegeven dat de ontwerplevensduur is bereikt, en welke onzekerheden beïnvloeden deze beoordeling? | G23: Technische levensduur - civiele delen | I23: =VALUE(SUBSTITUTE(SUBSTITUTE(SUBSTITUTE(SUBSTITUTE(C23,"EF",""),"ET",""),"C",""),"A","")) -> 1
A24: 1 | B24: e | C24: C22 | E24: C1 | F24: Kan met behulp van de bewezen historische sterkte of een proefbelasting de resterende levensduur van de betonconstructie van de oude sluis worden bepaald? | G24: Technische levensduur - civiele delen | I24: =VALUE(SUBSTITUTE(SUBSTITUTE(SUBSTITUTE(SUBSTITUTE(C24,"EF",""),"ET",""),"C",""),"A","")) -> 22
A25: 1 | B25: f | C25: ET6 | F25: In hoeverre is verlenging van de levensduur van het sluizencomplex (oude sluis) mogelijk en welke factoren zijn daarbij bepalend? | G25: Technische levensduur - civiele delen | I25: =VALUE(SUBSTITUTE(SUBSTITUTE(SUBSTITUTE(SUBSTITUTE(C25,"EF",""),"ET",""),"C",""),"A","")) -> 6
A26: 1 | B26: g | C26: ET2 | F26: Wat is de actuele constructieve veiligheid van de betonconstructies van de nieuwe sluis Panheel, gegeven dat de ontwerplevensduur nog niet is bereikt, en welke onzekerheden beïnvloeden deze beoordeling? | G26: Technische levensduur - civiele delen | I26: =VALUE(SUBSTITUTE(SUBSTITUTE(SUBSTITUTE(SUBSTITUTE(C26,"EF",""),"ET",""),"C",""),"A","")) -> 2
A27: 1 | B27: h | C27: ET3 | F27: Welke functionele eisen worden aan sluizencomplex Panheel gesteld en in hoeverre moeten constructieve componenten van de oude sluis hierop worden aangepast volgens den huidige normen? | G27: Technische levensduur - civiele delen | I27: =VALUE(SUBSTITUTE(SUBSTITUTE(SUBSTITUTE(SUBSTITUTE(C27,"EF",""),"ET",""),"C",""),"A","")) -> 3
A28: 1 | B28: i | C28: C11 | F28: Zouden nieuwe onderdelen aan de ROK – constructieve veiligheidseis - moeten voldoen als de rest van het complex daar niet aan voldoet (Is dat dan niet een te hoge eis?)? Afwegingskader: moet je de hoogste kaders / normen gebruiken of is een lagere eis soms voldoende? | G28: Technische levensduur - civiele delen | I28: =VALUE(SUBSTITUTE(SUBSTITUTE(SUBSTITUTE(SUBSTITUTE(C28,"EF",""),"ET",""),"C",""),"A","")) -> 11
A29: 1 | B29: j | C29: A5 | F29: Wat is de invloed van mogelijke strengere winters op ijsbelasting van sluizen, en in hoeverre moet dit worden meegenomen in beoordeling, ontwerp of beheermaatregelen? | G29: Technische levensduur - civiele delen | I29: =VALUE(SUBSTITUTE(SUBSTITUTE(SUBSTITUTE(SUBSTITUTE(C29,"EF",""),"ET",""),"C",""),"A","")) -> 5
A30: 1 | B30: k | C30: C5 | F30: Hoe ontwikkelt vermoeiingsschade in stalen sluisdeuren zich over de tijd en wat betekent dit voor de resterende sterkte en levensduur? | G30: Technische levensduur - civiele delen | I30: =VALUE(SUBSTITUTE(SUBSTITUTE(SUBSTITUTE(SUBSTITUTE(C30,"EF",""),"ET",""),"C",""),"A","")) -> 5
A31: 1 | B31: l | C31: C6 | F31: In hoeverre is een beheerstrategie op basis van inspectie en reparatie voldoende om vermoeiingsschade tijdig te signaleren en falen te voorkomen? | G31: Technische levensduur - civiele delen | I31: =VALUE(SUBSTITUTE(SUBSTITUTE(SUBSTITUTE(SUBSTITUTE(C31,"EF",""),"ET",""),"C",""),"A","")) -> 6
A32: 1 | B32: m | C32: A6 | F32: Welke eisen stellen de Machinerichtlijn en andere veiligheidskaders aan de besturing van spuien en gemalen, en wat betekent dit voor het ontwerp en beheer? | G32: Technische levensduur - civiele delen | I32: =VALUE(SUBSTITUTE(SUBSTITUTE(SUBSTITUTE(SUBSTITUTE(C32,"EF",""),"ET",""),"C",""),"A","")) -> 6
A33: 1 | B33: n | C33: A7 | F33: Welke duurzame alternatieven voor smeermiddelen en hydraulische systemen zijn toepasbaar en wat zijn de effecten op functioneren en betrouwbaarheid van het object? | G33: Technische levensduur - civiele delen | I33: =VALUE(SUBSTITUTE(SUBSTITUTE(SUBSTITUTE(SUBSTITUTE(C33,"EF",""),"ET",""),"C",""),"A","")) -> 7
A34: 1 | B34: o | C34: A9 | F34: Hoe kan een balans worden gevonden tussen standaardisatie en object-specifieke keuzes in bediening en besturing van sluizen? | G34: Technische levensduur - civiele delen | I34: =VALUE(SUBSTITUTE(SUBSTITUTE(SUBSTITUTE(SUBSTITUTE(C34,"EF",""),"ET",""),"C",""),"A","")) -> 9
I35: =VALUE(SUBSTITUTE(SUBSTITUTE(SUBSTITUTE(SUBSTITUTE(C35,"EF",""),"ET",""),"C",""),"A","")) -> #VALUE!
A36: 2 | D36: Technische levensduur - installaties | F36: Hoe ontwikkelen slijtage, veroudering en storingen zich in de machines en installaties van het sluizencomplex en wat betekent dit voor de betrouwbaarheid, veiligheid en resterende levensduur? | I36: =VALUE(SUBSTITUTE(SUBSTITUTE(SUBSTITUTE(SUBSTITUTE(C36,"EF",""),"ET",""),"C",""),"A","")) -> #VALUE!
A37: 2 | B37: a | C37: C7 | F37: Wat is de resterende levensduur en betrouwbaarheid van de pompen (bij toenemend watergebruik en mogelijk langere droge periodes), en in hoeverre zijn deze geschikt voor mogelijk intensiever gebruik? | G37: Technische levensduur - installaties | I37: =VALUE(SUBSTITUTE(SUBSTITUTE(SUBSTITUTE(SUBSTITUTE(C37,"EF",""),"ET",""),"C",""),"A","")) -> 7
A38: 2 | B38: b | C38: C9 | F38: Wat is de actuele staat van de leidingen (kokers) van het gemaal? | G38: Technische levensduur - installaties | I38: =VALUE(SUBSTITUTE(SUBSTITUTE(SUBSTITUTE(SUBSTITUTE(C38,"EF",""),"ET",""),"C",""),"A","")) -> 9
I39: =VALUE(SUBSTITUTE(SUBSTITUTE(SUBSTITUTE(SUBSTITUTE(C39,"EF",""),"ET",""),"C",""),"A","")) -> #VALUE!
I40: =VALUE(SUBSTITUTE(SUBSTITUTE(SUBSTITUTE(SUBSTITUTE(C40,"EF",""),"ET",""),"C",""),"A","")) -> #VALUE!
A41: 3 | D41: Inspecties, monitoring en data | F41: Hoe kunnen inspecties, monitoring en data de kwaliteit en betrouwbaarheid van technische beoordelingen vergroten? | I41: =VALUE(SUBSTITUTE(SUBSTITUTE(SUBSTITUTE(SUBSTITUTE(C41,"EF",""),"ET",""),"C",""),"A","")) -> #VALUE!
A42: 3 | B42: a | C42: C2 | F42: Hoe kan de huidige staat van moeilijk inspecteerbare onderdelen (zoals onderloopsheidschermen) betrouwbaar worden bepaald, gegeven het ontbreken van directe inspectie en meetgegevens? | G42: Inspecties, monitoring en data | I42: =VALUE(SUBSTITUTE(SUBSTITUTE(SUBSTITUTE(SUBSTITUTE(C42,"EF",""),"ET",""),"C",""),"A","")) -> 2
A43: 3 | B43: b | C43: C10 | F43: Welke inspectietechnieken kunnen worden ingezet om de staat van moeilijk toegankelijke onderdelen van het gemaal betrouwbaar in beeld te brengen? | G43: Inspecties, monitoring en data | I43: =VALUE(SUBSTITUTE(SUBSTITUTE(SUBSTITUTE(SUBSTITUTE(C43,"EF",""),"ET",""),"C",""),"A","")) -> 10
A44: 3 | B44: c | C44: C16 | F44: Welke inspectie-, monitoring- en datagedreven technieken (incl. AI) zijn geschikt om de staat van betonconstructies en installaties betrouwbaar te beoordelen en intern inzichtelijk te maken? | G44: Inspecties, monitoring en data | I44: =VALUE(SUBSTITUTE(SUBSTITUTE(SUBSTITUTE(SUBSTITUTE(C44,"EF",""),"ET",""),"C",""),"A","")) -> 16
A45: 3 | B45: d | C45: C14 | F45: Hoe kan de beschikbaarheid en kwaliteit van ontwerp-, beheer- en inspectiedata worden verbeterd om uitvoering en onderhoud efficiënter en beter voorspelbaar te maken? | G45: Inspecties, monitoring en data | I45: =VALUE(SUBSTITUTE(SUBSTITUTE(SUBSTITUTE(SUBSTITUTE(C45,"EF",""),"ET",""),"C",""),"A","")) -> 14
A46: 3 | B46: e | C46: C17 | F46: Hoe kunnen reparatietechnieken en boorkernonderzoek worden geoptimaliseerd om het beheer en onderhoud van betonconstructies efficiënter uit te voeren? | G46: Inspecties, monitoring en data | I46: =VALUE(SUBSTITUTE(SUBSTITUTE(SUBSTITUTE(SUBSTITUTE(C46,"EF",""),"ET",""),"C",""),"A","")) -> 17
A47: 3 | B47: f | C47: C23 | E47: A16 | F47: Hoe kunnen inzichten uit inspecties worden vertaald naar andere sluizen en sluizenfamilies? | G47: Inspecties, monitoring en data | I47: =VALUE(SUBSTITUTE(SUBSTITUTE(SUBSTITUTE(SUBSTITUTE(C47,"EF",""),"ET",""),"C",""),"A","")) -> 23
A48: 3 | B48: g | C48: A16 | E48: C23 | F48: Hoe kun je zorgen dat kennis uit onderzoeken voor één sluis ook gebruikt wordt bij andere sluizen? | G48: Inspecties, monitoring en data | H48: Gaat om beschikbaarheid en vindbaarheid van data, maar ook de volgende stap hoe je daar informatie en inzichten uit kan halen voor een volgende vraag van de volgende sluis. Bv mbv digital twin / AI en gekoppeld aan de sluizenfamilies. | I48: =VALUE(SUBSTITUTE(SUBSTITUTE(SUBSTITUTE(SUBSTITUTE(C48,"EF",""),"ET",""),"C",""),"A","")) -> 16
I49: =VALUE(SUBSTITUTE(SUBSTITUTE(SUBSTITUTE(SUBSTITUTE(C49,"EF",""),"ET",""),"C",""),"A","")) -> #VALUE!
I50: =VALUE(SUBSTITUTE(SUBSTITUTE(SUBSTITUTE(SUBSTITUTE(C50,"EF",""),"ET",""),"C",""),"A","")) -> #VALUE!
A51: 4 | D51: Hoogwaterveiligheid | F51: In hoeverre vervult het sluizencomplex nu en in de toekomst zijn functie als onderdeel van het systeem van primaire waterkeringen, en welke eisen stelt dit aan constructies, installaties en beheer? | I51: =VALUE(SUBSTITUTE(SUBSTITUTE(SUBSTITUTE(SUBSTITUTE(C51,"EF",""),"ET",""),"C",""),"A","")) -> #VALUE!
I52: =VALUE(SUBSTITUTE(SUBSTITUTE(SUBSTITUTE(SUBSTITUTE(C52,"EF",""),"ET",""),"C",""),"A","")) -> #VALUE!
A53: 5 | D53: Watersysteem en waterbeschikbaarheid | F53: Welke ontwikkelingen in het huidige en toekomstige watersysteem zijn bepalend voor het functioneren van sluis Panheel en welke eisen stellen deze aan het sluizencomplex? | I53: =VALUE(SUBSTITUTE(SUBSTITUTE(SUBSTITUTE(SUBSTITUTE(C53,"EF",""),"ET",""),"C",""),"A","")) -> #VALUE!
A54: 5 | B54: a | C54: EF7 | F54: Wat wordt de toekomstige waterbalans van het watersysteem waarvan Panheel een onderdeel uitmaakt (inclusief traject Maastricht - Linne & samenwerking met Belgie) voor de verschillende seizoenen (inclusief wateroverlast en droogte)? | G54: Watersysteem en waterbeschikbaarheid | I54: =VALUE(SUBSTITUTE(SUBSTITUTE(SUBSTITUTE(SUBSTITUTE(C54,"EF",""),"ET",""),"C",""),"A","")) -> 7
A55: 5 | B55: b | C55: C21 | F55: In hoeverre kunnen veranderingen in wateraanvoerafspraken met België optreden en wat betekent dit voor de hydraulische belasting en het functioneren van sluis Panheel? | G55: Watersysteem en waterbeschikbaarheid | I55: =VALUE(SUBSTITUTE(SUBSTITUTE(SUBSTITUTE(SUBSTITUTE(C55,"EF",""),"ET",""),"C",""),"A","")) -> 21
A56: 5 | B56: c | C56: EF8 | F56: Welke eisen worden gesteld aan de verschillende functies (water bergen en water afvoeren) en componenten (lekverlies, schutverlies, spaarbekkens) van sluis Panheel? | G56: Watersysteem en waterbeschikbaarheid | I56: =VALUE(SUBSTITUTE(SUBSTITUTE(SUBSTITUTE(SUBSTITUTE(C56,"EF",""),"ET",""),"C",""),"A","")) -> 8
A57: 5 | B57: d | C57: A1 | F57: Hoe kunnen klimaatscenario’s worden vertaald naar hydraulische randvoorwaarden voor het functioneren en de beoordeling van het sluizencomplex? | G57: Watersysteem en waterbeschikbaarheid | I57: =VALUE(SUBSTITUTE(SUBSTITUTE(SUBSTITUTE(SUBSTITUTE(C57,"EF",""),"ET",""),"C",""),"A","")) -> 1
A58: 5 | B58: e | C58: A2 | F58: Hoe kunnen klimaatscenario’s worden vertaald naar lokale omstandigheden en randvoorwaarden voor het functioneren van het sluizencomplex? | G58: Watersysteem en waterbeschikbaarheid | I58: =VALUE(SUBSTITUTE(SUBSTITUTE(SUBSTITUTE(SUBSTITUTE(C58,"EF",""),"ET",""),"C",""),"A","")) -> 2
I59: =VALUE(SUBSTITUTE(SUBSTITUTE(SUBSTITUTE(SUBSTITUTE(C59,"EF",""),"ET",""),"C",""),"A","")) -> #VALUE!
I60: =VALUE(SUBSTITUTE(SUBSTITUTE(SUBSTITUTE(SUBSTITUTE(C60,"EF",""),"ET",""),"C",""),"A","")) -> #VALUE!
A61: 6 | D61: Ecologie en waterkwaliteit watersysteem | F61: Hoe kan het sluizencomplex bijdragen aan het voldoen aan waterkwaliteits- en ecologische eisen voor het watersysteem, nu en in de toekomst? | I61: =VALUE(SUBSTITUTE(SUBSTITUTE(SUBSTITUTE(SUBSTITUTE(C61,"EF",""),"ET",""),"C",""),"A","")) -> #VALUE!
B62: a | C62: EF23 | F62: Welke eisen stelt de KRW en natuurwetgeving aan het functioneren van een gemaal met betrekking tot visvriendelijkheid en vispasseerbaarheid? | G62: Ecologie en waterkwaliteit watersysteem | I62: =VALUE(SUBSTITUTE(SUBSTITUTE(SUBSTITUTE(SUBSTITUTE(C62,"EF",""),"ET",""),"C",""),"A","")) -> 23
B63: b | C63: EF13 | F63: Wat zijn de toekomstige eisen aan sluizencomplex en kanaal voor waterkwaliteit, ecologie en natuuropgaven (zoals vissterfte bij gemalen, blauwalgen, Natura 2000-stikstofeisen i.r.t. scheepvaart en passeerbaarheid, zoals natuurvriendelijke oevers)? | G63: Ecologie en waterkwaliteit watersysteem | I63: =VALUE(SUBSTITUTE(SUBSTITUTE(SUBSTITUTE(SUBSTITUTE(C63,"EF",""),"ET",""),"C",""),"A","")) -> 13
B64: c | C64: EF24 | F64: Welke maatregelen zijn mogelijk om het gemaal visvriendelijker (voorkomen vermaling) te maken en wat is het effect daarvan op functioneren en prestaties? | G64: Ecologie en waterkwaliteit watersysteem | I64: =VALUE(SUBSTITUTE(SUBSTITUTE(SUBSTITUTE(SUBSTITUTE(C64,"EF",""),"ET",""),"C",""),"A","")) -> 24
I65: =VALUE(SUBSTITUTE(SUBSTITUTE(SUBSTITUTE(SUBSTITUTE(C65,"EF",""),"ET",""),"C",""),"A","")) -> #VALUE!
A66: 7 | D66: Functies van het complex in het netwerk (scheepvaart, weg en water) | F66: Welke functies vervult sluizencomplex Panheel binnen het vaarweg- en watersysteem, nu en in de toekomst en welke eisen stelt dit aan het sluizencomplex? | I66: =VALUE(SUBSTITUTE(SUBSTITUTE(SUBSTITUTE(SUBSTITUTE(C66,"EF",""),"ET",""),"C",""),"A","")) -> #VALUE!
B67: a | C67: EF26 | E67: EF17, EF15 | F67: Wat is de functie van sluis Panheel in de scheepvaart corridors vanuit de netwerkbenadering? | G67: Functies van het complex in het netwerk (scheepvaart, weg en water) | I67: =VALUE(SUBSTITUTE(SUBSTITUTE(SUBSTITUTE(SUBSTITUTE(C67,"EF",""),"ET",""),"C",""),"A","")) -> 26
B68: b | C68: EF16 | F68: Voldoet sluizencomplex Panheel aan richtlijn vaarwegen? | G68: Functies van het complex in het netwerk (scheepvaart, weg en water) | I68: =VALUE(SUBSTITUTE(SUBSTITUTE(SUBSTITUTE(SUBSTITUTE(C68,"EF",""),"ET",""),"C",""),"A","")) -> 16
B69: c | C69: EF17 | E69: EF2, EF26 | F69: Wat is de verwachte ontwikkeling van de binnenvaart en gebruik van Sluizencomplex Panheel (incl. voorhavens) en welke voorzieningen zijn hiervoor nodig? | G69: Functies van het complex in het netwerk (scheepvaart, weg en water) | I69: =VALUE(SUBSTITUTE(SUBSTITUTE(SUBSTITUTE(SUBSTITUTE(C69,"EF",""),"ET",""),"C",""),"A","")) -> 17
B70: d | C70: EF27 | E70: EF17, EF15 | F70: Wat is de invloed van de ontwikkelingen in de scheepvaart op de staat van de componenten en wat je van de componenten vraagt? | G70: Functies van het complex in het netwerk (scheepvaart, weg en water) | I70: =VALUE(SUBSTITUTE(SUBSTITUTE(SUBSTITUTE(SUBSTITUTE(C70,"EF",""),"ET",""),"C",""),"A","")) -> 27
B71: e | C71: C20 | F71: In hoeverre kan het kanaal in de toekomst een rol spelen als route voor defensie? Wat betekent dit voor het functioneren van de scheepvaartroute? Wat betekent dit voor het functioneren en de eisen aan sluis Panheel? | G71: Functies van het complex in het netwerk (scheepvaart, weg en water) | H71: Wat moet vanuit defensie door de sluis kunnen? Wat als defensie voorrang krijgt bij scheepvaart als transportroute? | I71: =VALUE(SUBSTITUTE(SUBSTITUTE(SUBSTITUTE(SUBSTITUTE(C71,"EF",""),"ET",""),"C",""),"A","")) -> 20
B72: f | C72: EF18 | F72: Wat zijn de richtllijnen rondom walstroom (stroomvoorziening (electrische) schepen) bij sluizen? Wat zijn de kaders voor walstroom bij de rijksaanlegplaatsen? Voldoet de walstroomvoorziening van sluizencomplex Panheel aan de eisen? | G72: Functies van het complex in het netwerk (scheepvaart, weg en water) | I72: =VALUE(SUBSTITUTE(SUBSTITUTE(SUBSTITUTE(SUBSTITUTE(C72,"EF",""),"ET",""),"C",""),"A","")) -> 18
I73: =VALUE(SUBSTITUTE(SUBSTITUTE(SUBSTITUTE(SUBSTITUTE(C73,"EF",""),"ET",""),"C",""),"A","")) -> #VALUE!
A74: 8 | D74: Operatie: bediening en besturing | F74: Hoe kan het sluizencomplex onder reguliere en uitzonderlijke omstandigheden veilig, efficiënt en robuust worden bediend voor de functies die het vervult? | I74: =VALUE(SUBSTITUTE(SUBSTITUTE(SUBSTITUTE(SUBSTITUTE(C74,"EF",""),"ET",""),"C",""),"A","")) -> #VALUE!
A75: 8 | B75: a | C75: EF25 | E75: EF10 | F75: Welke van de spuimiddelen kunnen we nu en in de toekomst het beste inzetten bij teveel water (bijv. spuien door kolken, spuiriool of spuien via gemaal)? | G75: Operatie: bediening en besturing | I75: =VALUE(SUBSTITUTE(SUBSTITUTE(SUBSTITUTE(SUBSTITUTE(C75,"EF",""),"ET",""),"C",""),"A","")) -> 25
A76: 8 | B76: b | C76: EF10 | E76: EF25, EF2 | F76: Is het in de toekomst, bij een grotere afvoerbehoefte, nodig om andere routes te gebruiken dan spuien via de kolk? | G76: Operatie: bediening en besturing | I76: =VALUE(SUBSTITUTE(SUBSTITUTE(SUBSTITUTE(SUBSTITUTE(C76,"EF",""),"ET",""),"C",""),"A","")) -> 10
A77: 8 | B77: c | C77: C18 | F77: In hoeverre kan turbineren met bestaande gemalen worden toegepast, gegeven beperkingen zoals trillingen en schade, en welke ontwerpaanpassingen zijn nodig? | G77: Operatie: bediening en besturing | I77: =VALUE(SUBSTITUTE(SUBSTITUTE(SUBSTITUTE(SUBSTITUTE(C77,"EF",""),"ET",""),"C",""),"A","")) -> 18
I78: =VALUE(SUBSTITUTE(SUBSTITUTE(SUBSTITUTE(SUBSTITUTE(C78,"EF",""),"ET",""),"C",""),"A","")) -> #VALUE!
A79: 9 | D79: Beschikbaarheid en robuustheid | F79: Hoe kunnen beschikbaarheid en robuustheid van het sluizencomplex worden geborgd? | I79: =VALUE(SUBSTITUTE(SUBSTITUTE(SUBSTITUTE(SUBSTITUTE(C79,"EF",""),"ET",""),"C",""),"A","")) -> #VALUE!
A80: 9 | B80: a | C80: EF15 | E80: EF26, EF17 | F80: Wat zijn de beschikbaarheidseisen van schutsluizen – harde eisen ten opzichte van wensen (schuttijden / passagetijden en stremmingen) nu en in de toekomst? | G80: Beschikbaarheid en robuustheid | I80: =VALUE(SUBSTITUTE(SUBSTITUTE(SUBSTITUTE(SUBSTITUTE(C80,"EF",""),"ET",""),"C",""),"A","")) -> 15
A81: 9 | B81: b | C81: C13 | F81: Hoe kan de beschikbaarheid van systemen in oude sluizen worden geborgd, gegeven de beperkte beschikbaarheid van specifieke materialen en kennis? | G81: Beschikbaarheid en robuustheid | I81: =VALUE(SUBSTITUTE(SUBSTITUTE(SUBSTITUTE(SUBSTITUTE(C81,"EF",""),"ET",""),"C",""),"A","")) -> 13
A82: 9 | B82: c | C82: ET4 | F82: Welke mate van redundantie (bijv. reservedeuren of alternatieven) is nodig om de beschikbaarheid en robuustheid van het sluizencomplex te borgen? | G82: Beschikbaarheid en robuustheid | I82: =VALUE(SUBSTITUTE(SUBSTITUTE(SUBSTITUTE(SUBSTITUTE(C82,"EF",""),"ET",""),"C",""),"A","")) -> 4
A83: 9 | B83: d | C83: C24 | F83: Welke standaard oplossing is te bedenken voor redundantie voor stroom of glasvezel? | G83: Beschikbaarheid en robuustheid | I83: =VALUE(SUBSTITUTE(SUBSTITUTE(SUBSTITUTE(SUBSTITUTE(C83,"EF",""),"ET",""),"C",""),"A","")) -> 24
A84: 9 | B84: e | C84: ET5 | F84: Welke risico’s voor veiligheid en beschikbaarheid ontstaan bij langdurige spanningsuitval voor welke functies, hoe erg is dit, en waar zijn noodstroomvoorzieningen (zoals aggregaten) noodzakelijk binnen het sluizencomplex? Hoe ziet een draaiboek bij stroomuitvalling eruit? | G84: Beschikbaarheid en robuustheid | I84: =VALUE(SUBSTITUTE(SUBSTITUTE(SUBSTITUTE(SUBSTITUTE(C84,"EF",""),"ET",""),"C",""),"A","")) -> 5
I85: =VALUE(SUBSTITUTE(SUBSTITUTE(SUBSTITUTE(SUBSTITUTE(C85,"EF",""),"ET",""),"C",""),"A","")) -> #VALUE!
A86: 10 | D86: Stategie, afweging en keuzes | F86: Hoe kunnen integrale afwegingen worden gemaakt tussen prestaties, kosten en risico's? En welke ontwikkelingen zijn daarbij van belang? | I86: =VALUE(SUBSTITUTE(SUBSTITUTE(SUBSTITUTE(SUBSTITUTE(C86,"EF",""),"ET",""),"C",""),"A","")) -> #VALUE!
A87: 10 | B87: a | C87: EF1 | F87: Wat is de lange termijn visie/plan voor de toekomst van sluizencomplex Panheel, rekeninghoudend met veranderende wensen/gebruik (functies), budgetverminderingen, kennisbehoud, etc. (incl. keuzemomenten en adaptatiepaden)? | G87: Stategie, afweging en keuzes | I87: =VALUE(SUBSTITUTE(SUBSTITUTE(SUBSTITUTE(SUBSTITUTE(C87,"EF",""),"ET",""),"C",""),"A","")) -> 1
A88: 10 | B88: b | C88: EF2 | E88: EF10 | F88: Wat zijn de effecten van exploitatie met één kolk op beschikbaarheid, scheepvaart (inclusief voorhavens) en beheer, en welke sluis is daarbij het meest geschikt om te behouden? | G88: Stategie, afweging en keuzes | I88: =VALUE(SUBSTITUTE(SUBSTITUTE(SUBSTITUTE(SUBSTITUTE(C88,"EF",""),"ET",""),"C",""),"A","")) -> 2
A89: 10 | B89: c | C89: EF9 | F89: Wat zijn de (toekomstige) beleidskeuzes rondom Maaspeilen en het stuwprogramma, en wat is de invloed hiervan op waterstanden, hydraulische belastingen en het functioneren van het sluizencomplex (incl. bevaarbaarheid, voorhavens, bodem en oeverbescherming)? | G89: Stategie, afweging en keuzes | I89: =VALUE(SUBSTITUTE(SUBSTITUTE(SUBSTITUTE(SUBSTITUTE(C89,"EF",""),"ET",""),"C",""),"A","")) -> 9
A90: 10 | B90: d | C90: EF14 | F90: Als de oude sluis een monumentstatus krijgt, wat betekent dit voor B&O en Vernieuwing? | G90: Stategie, afweging en keuzes | I90: =VALUE(SUBSTITUTE(SUBSTITUTE(SUBSTITUTE(SUBSTITUTE(C90,"EF",""),"ET",""),"C",""),"A","")) -> 14
A91: 10 | B91: e | C91: EF20 | F91: Hoe kunnen de spaarbekkens, riolen en het nivelleermiddel van de oude (noordelijke) sluis technisch en functioneel weer in gebruik worden genomen? | G91: Stategie, afweging en keuzes | I91: =VALUE(SUBSTITUTE(SUBSTITUTE(SUBSTITUTE(SUBSTITUTE(C91,"EF",""),"ET",""),"C",""),"A","")) -> 20
A92: 10 | B92: f | C92: EF21 | F92: Welke rol kan de oude sluis (inclusief werkende spaarbekkens) spelen in het minimaliseren van watergebruik binnen het sluizencomplex Panheel, en welke maatregelen (zoals herstel of aanpassing van de nieuwe sluis) zijn daarvoor het meest effectief? | G92: Stategie, afweging en keuzes | I92: =VALUE(SUBSTITUTE(SUBSTITUTE(SUBSTITUTE(SUBSTITUTE(C92,"EF",""),"ET",""),"C",""),"A","")) -> 21
A93: 10 | B93: g | C93: EF22 | F93: Welke integrale en ‘sober en doelmatige’ afweging is mogelijk voor ingrepen aan het sluizencomplex Panheel, rekening houdend met watergebruik, duurzaamheid, kosten en beschikbaarheid, en welke methoden (zoals LCC, LCA en de bedrijfswaardenmatrix) zijn daarbij geschikt? | G93: Stategie, afweging en keuzes | I93: =VALUE(SUBSTITUTE(SUBSTITUTE(SUBSTITUTE(SUBSTITUTE(C93,"EF",""),"ET",""),"C",""),"A","")) -> 22
A94: 10 | B94: h | C94: C15 | F94: Hoe kan het energiegebruik van het gemaal en de sluis worden geoptimaliseerd (bijv. energiezuinig pompen en afstemming op energieaanbod) zonder afbreuk te doen aan beschikbaarheid en functioneren? | G94: Stategie, afweging en keuzes | I94: =VALUE(SUBSTITUTE(SUBSTITUTE(SUBSTITUTE(SUBSTITUTE(C94,"EF",""),"ET",""),"C",""),"A","")) -> 15
A95: 10 | B95: i | C95: A8 | E95: A10 | F95: Hoe om te gaan met de effecten van budgettekorten en het kennisbehoud (bij RWS en aannemers) op de risico's en de instandhouding van sluizen, en wat betekent dit voor de prioritering van objecten binnen het areaal? | G95: Stategie, afweging en keuzes | I95: =VALUE(SUBSTITUTE(SUBSTITUTE(SUBSTITUTE(SUBSTITUTE(C95,"EF",""),"ET",""),"C",""),"A","")) -> 8
A96: 10 | B96: j | C96: EF19 | F96: Waar kun je bezuinigen bij sluis Panheel zonder dat de veiligheid en functies in geding komen? | G96: Stategie, afweging en keuzes | I96: =VALUE(SUBSTITUTE(SUBSTITUTE(SUBSTITUTE(SUBSTITUTE(C96,"EF",""),"ET",""),"C",""),"A","")) -> 19
A97: 10 | B97: k | C97: A3 | F97: Wat wordt de toekomstige afweging tussen duurzaamheid vs. verdringingsreeks, maar ook energieverbruik en circulariteit van aanleveren van componenten bij sluizen? | G97: Stategie, afweging en keuzes | I97: =VALUE(SUBSTITUTE(SUBSTITUTE(SUBSTITUTE(SUBSTITUTE(C97,"EF",""),"ET",""),"C",""),"A","")) -> 3
A98: 10 | B98: l | C98: A4 | F98: Hoe vertaal je de eis op netwerkniveau naar een realistische eis op complex/objecten niveau? | G98: Stategie, afweging en keuzes | I98: =VALUE(SUBSTITUTE(SUBSTITUTE(SUBSTITUTE(SUBSTITUTE(C98,"EF",""),"ET",""),"C",""),"A","")) -> 4
A99: 10 | B99: m | C99: C19 | F99: Waar gaat tijd, geld, milieu impact inzitten in dagelijks B&O sluis Panheel en waar is winst te behalen? | G99: Stategie, afweging en keuzes | I99: =VALUE(SUBSTITUTE(SUBSTITUTE(SUBSTITUTE(SUBSTITUTE(C99,"EF",""),"ET",""),"C",""),"A","")) -> 19
I100: =VALUE(SUBSTITUTE(SUBSTITUTE(SUBSTITUTE(SUBSTITUTE(C100,"EF",""),"ET",""),"C",""),"A","")) -> #VALUE!
A101: 11 | D101: Milieu-impact | F101: Hoe kunnen we de milieu-impact van schutsluizen gedurende de gehele levenscyclus verminderen, door slimmer om te gaan met materialen, energieverbruik en CO₂-uitstoot? | I101: =VALUE(SUBSTITUTE(SUBSTITUTE(SUBSTITUTE(SUBSTITUTE(C101,"EF",""),"ET",""),"C",""),"A","")) -> #VALUE!
A102: 11 | B102: a | C102: C12 | F102: Wat is de potentie voor hergebruik van materialen/elementen? | G102: Milieu-impact | I102: =VALUE(SUBSTITUTE(SUBSTITUTE(SUBSTITUTE(SUBSTITUTE(C102,"EF",""),"ET",""),"C",""),"A","")) -> 12
I103: =VALUE(SUBSTITUTE(SUBSTITUTE(SUBSTITUTE(SUBSTITUTE(C103,"EF",""),"ET",""),"C",""),"A","")) -> #VALUE!
A104: 12 | D104: Organisatorische aspecten | F104: Hoe organiseren we governance, samenwerking en kennisborging zodat beheer, onderhoud en vernieuwing van het sluizencomplex toekomstbestendig en beheersbaar blijven? | I104: =VALUE(SUBSTITUTE(SUBSTITUTE(SUBSTITUTE(SUBSTITUTE(C104,"EF",""),"ET",""),"C",""),"A","")) -> #VALUE!
...

Sheet Database
A1: Sluis | B1: Code | C1: link met andere code (indien relevent) | D1: keywords kennisvraag | E1: Kennisvraag | F1: Toelichting kennisvraag (waarom belangrijk) (Aantekeningen Meinard tijdens sessie) | G1: Prioriteit: Functie waterveiligheid | H1: Prioriteit: Functie waterbeschikbaarheid | I1: Prioriteit: Functie Scheepvaart | J1: Prioriteit: Functies (anders dan waterveiligheid, waterbeschikbaarheid, scheepvaart) | K1: Prioriteit: BenO (budget, planning en uitvoering) | L1: Prioriteit: Operatie (OT) | M1: Prioriteit totaal | N1: Tijd | O1: Onderwerp onderzoekslijn | P1: Raakt aan (onderzoeks)programma | Q1: Belegd in (onderzoeks)programma | R1: Status | Y1: Draagt bij aan strandaardisatie (kennis toepasbaar voor andere sluizen) | AG1: Assetmanagement Lemniscaat
S2: Onderzoekslijn eerste keus | T2: Onderzoekslijn tweede keus (indien nodig) | U2: toelichting tijd / wanneer antwoord nodig | V2: toelichting onderzoekslijn | W2: status | X2: Waar belegd | Z2: kosten [euro] | AA2: doorlooptijd [jaren] | AB2: Toelichting status onderzoek (niet voor de database) | AC2: Toelichting waar moet het belged worden | AD2: Toelichting kosten en doorlooptijd studie (niet voor de database) | AE2: relevante documenten | AG2: Kerntak I&W | AH2: Roadmap Sluizen | AI2: Netwerk | AJ2: 1. Beleidskaders & stategie | AK2: 2. Plannen | AL2: 3. Uitvoeringsplan(nen) | AM2: 4. Netwerkschakelanalyse | AN2: 5. Netwerkanalyse | AO2: 6. Netwerkprogrammering | AP2: 7. Offerte-opdracht | AQ2: 8. Interne opdracht | AR2: 9. Voorbereidingen contractering | AS2: 10. uitvoering en voortgangsrapportage | AT2: 11. Monitoring Netwerkschakel (P-R-K) | AU2: 12. Monitoring netwerk (P-R-K) | AV2: 13. Evalueren en bijsturen | AW2: Discipline | AX2: Tijdshorizon | AY2: Doelen KenI Instandhoudingprogramma
A3: Is dit een kennisvraag voor een specifieke sluis of voor alle sluizen? Hier: SP (sluis Panheel) of Xsluizen (overkoepelende vraag voor de sluizen) | B3: Code van de kennisvraag bv SP_ET1 | G3: Impact van het niet weten / beantwoorden van de vraag op de functie waterveiligheid. 1=laag; 2=middel; 3=hoog | H3: Impact van het niet weten / beantwoorden van de vraag op de functie waterbeschikbaarheid. 1=laag; 2=middel; 3=hoog | I3: Impact van het niet weten / beantwoorden van de vraag op de functie scheepvaart. 1=laag; 2=middel; 3=hoog | J3: Impact van het niet weten / beantwoorden van de vraag op overige functies (Waterkwaliteit, ecologie, sedimenttransport etc.). (0 - 3, 0 geen invloed, 3 is zeer grote invloed) | K3: Impact van het niet weten / beantwoorden van de vraag op budget, planning en uitvoering van BenO. (0 - 3, 0 geen invloed, 3 is zeer grote invloed) | L3: impact van het niet weten/beantwoorden van de vraag op de operatie van sluiten en openen van de sluis door het operationeel team. 1=laag; 2=middel; 3=hoog | N3: Wanneer is het antwoord op de kennisvraag nodig? Hierbij zijn 4 categorieen gekozen: 0=antwoord levert te weinig op, kennisvraag niet oppakken 1= nu; 2=2033-2040; 3=>2040 | Y3: Is de kennis toepasbaar op andere sluizen? Zo ja, waarom en welke?
A4: SP | B4: ="SP_"&'Kennisagenda onderzoekslijnen'!C20 -> SP_C1 | C4: SP_C2 | E4: ='Kennisagenda onderzoekslijnen'!F20 -> Hoe bepaal je de kwaliteit en variabiliteit van het historische (ongewapende) beton van de oude sluis? | F4: Esther: Status levensduur beton oude sluis als 1 kennisvraag, met daaronder subvragen. C1, C2, C4, C16, C17. Breed gedragen: Erg belangrijk. Maar lastig te scoren: Is geen waterveiligheidsrisico, beperkt risico scheepvaart, groot risico B&O. Maar scheepvaart mogelijk geen groot probleem, want Nieuwe Sluis. Waterbeschikbaarheid: Mogelijk wel belangrijk want geen nieuwe sluis: Meer watervraag, dus probleem waterbeschikbaarheid. Wilco: Algemeen voor sluizen: Waterveiligheid heeft prioriteit, bijvoorbeeld bij betonveroudering. Deze sluis heeft geen waterkerende functie. Echter, wegvallen sluiskolk betekent ook wegvallen keringsfunctie. Waterveiligheid is bij Panheel geen discussie: Deuren weg, water in Maas, geen risico. Staat van beton geen direct waterveiligheidsrisico. | G4: 1 | H4: 2 | I4: 2 | J4: 1 | K4: 3 | L4: 1 | M4: =SUM(G4:L4) -> 10 | N4: 1 | O4: ='Kennisagenda onderzoekslijnen'!G20 -> Technische levensduur - civiele delen | P4: Dit is een test programma waar het onderzoek mee te maken heeft. | Q4: In dit programma wordt het onderzoek belegd | Y4: ja
A5: SP | B5: ="SP_"&'Kennisagenda onderzoekslijnen'!C42 -> SP_C2 | C5: SP_C1 | E5: ='Kennisagenda onderzoekslijnen'!F42 -> Hoe kan de huidige staat van moeilijk inspecteerbare onderdelen (zoals onderloopsheidschermen) betrouwbaar worden bepaald, gegeven het ontbreken van directe inspectie en meetgegevens? | F5: Inspectie en beoordeling status en resterende levensduur moeilijk toegankelijke plekken samenvatten tot 1 kennisvragen met daaronder subvragen. | G5: 1 | H5: 2 | I5: 1 | J5: 0 | K5: 2 | L5: 1 | M5: =SUM(G5:L5) -> 7 | N5: 1 | O5: ='Kennisagenda onderzoekslijnen'!G42 -> Inspecties, monitoring en data | Q5: Ook hier wordt een onderzoek belegd in een programma. Dit programma heeft een zeer lange naam en omschrijving, dus verwacht ik dat het over meerdere regels wordt weergegeven. | Y5: ja
A6: SP | B6: ="SP_"&'Kennisagenda onderzoekslijnen'!C21 -> SP_C3 | E6: ='Kennisagenda onderzoekslijnen'!F21 -> Welke lessen uit vergelijkbare sluizen (zelfde bouwjaar, typologie, ondergrond, constructiemethode) zijn bruikbaar voor de beoordeling en instandhouding van de betonconstructies van sluis Panheel, en hoe kan met deze kennis de onzekerheid in bodemgesteldheid en betonconstructies worden verkleind? | G6: 1 | H6: 1 | I6: 1 | J6: 1 | K6: 2 | L6: 1 | M6: =SUM(G6:L6) -> 7 | N6: 2 | O6: ='Kennisagenda onderzoekslijnen'!G21 -> Technische levensduur - civiele delen | Y6: ja
A7: SP | B7: ="SP_"&'Kennisagenda onderzoekslijnen'!C22 -> SP_C4 | E7: ='Kennisagenda onderzoekslijnen'!F22 -> In hoeverre is de RBK (richtlijn bestaande kunstwerken) met de bijbehorende aanpak constructieve veiligheid sluizen geschikt om tot een goed oordeel te komen voor de betonconstructies van sluis Panheel? En welke gegevens hebben we daarvoor nodig? | G7: 1 | H7: 2 | I7: 1 | J7: 1 | K7: 3 | L7: 1 | M7: =SUM(G7:L7) -> 9 | N7: 1 | O7: ='Kennisagenda onderzoekslijnen'!G22 -> Technische levensduur - civiele delen | Y7: ja
A8: SP | B8: ="SP_"&'Kennisagenda onderzoekslijnen'!C30 -> SP_C5 | E8: ='Kennisagenda onderzoekslijnen'!F30 -> Hoe ontwikkelt vermoeiingsschade in stalen sluisdeuren zich over de tijd en wat betekent dit voor de resterende sterkte en levensduur? | G8: 0 | H8: 2 | I8: 2 | J8: 1 | K8: 2 | L8: 1 | M8: =SUM(G8:L8) -> 8 | N8: 1 | O8: ='Kennisagenda onderzoekslijnen'!G30 -> Technische levensduur - civiele delen | Y8: ja
A9: SP | B9: ="SP_"&'Kennisagenda onderzoekslijnen'!C31 -> SP_C6 | E9: ='Kennisagenda onderzoekslijnen'!F31 -> In hoeverre is een beheerstrategie op basis van inspectie en reparatie voldoende om vermoeiingsschade tijdig te signaleren en falen te voorkomen? | G9: 0 | H9: 2 | I9: 2 | J9: 1 | K9: 2 | L9: 1 | M9: =SUM(G9:L9) -> 8 | N9: 1 | O9: ='Kennisagenda onderzoekslijnen'!G31 -> Technische levensduur - civiele delen | Y9: ja
A10: SP | B10: ="SP_"&'Kennisagenda onderzoekslijnen'!C37 -> SP_C7 | E10: ='Kennisagenda onderzoekslijnen'!F37 -> Wat is de resterende levensduur en betrouwbaarheid van de pompen (bij toenemend watergebruik en mogelijk langere droge periodes), en in hoeverre zijn deze geschikt voor mogelijk intensiever gebruik? | F10: Voorkeur Carla (alle vragen over gemaal, C15, C7, C8, C9): Gemaal van belang voor waterbeschikbaarheid, scheepvaart (niet kunnen schutten, inclusief Empel schuttingen alleen mogelijk genoeg water kanaalpand), ecologie (vissen), B&O, duurzaamheid, etc. | G10: 0 | H10: 3 | I10: 2 | J10: 1 | K10: 2 | L10: 2 | M10: =SUM(G10:L10) -> 10 | N10: 1 | O10: ='Kennisagenda onderzoekslijnen'!G37 -> Technische levensduur - installaties | Y10: nee
A11: SP | B11: ="SP_"&'Kennisagenda onderzoekslijnen'!C38 -> SP_C9 | E11: ='Kennisagenda onderzoekslijnen'!F38 -> Wat is de actuele staat van de leidingen (kokers) van het gemaal? | F11: Gemaal van belang voor waterbeschikbaarheid, scheepvaart (niet kunnen schutten, inclusief Empel schuttingen alleen mogelijk genoeg water kanaalpand), ecologie (vissen), B&O, duurzaamheid, etc. Hangt ook samen met het gehele systeem, niet alleen Panheel. | G11: 2 | H11: 2 | I11: 2 | J11: 1 | K11: 2 | L11: 1 | M11: =SUM(G11:L11) -> 10 | N11: 1 | O11: ='Kennisagenda onderzoekslijnen'!G38 -> Technische levensduur - installaties | Y11: nee
A12: SP | B12: ="SP_"&'Kennisagenda onderzoekslijnen'!C43 -> SP_C10 | E12: ='Kennisagenda onderzoekslijnen'!F43 -> Welke inspectietechnieken kunnen worden ingezet om de staat van moeilijk toegankelijke onderdelen van het gemaal betrouwbaar in beeld te brengen? | F12: C10, C16, C17: Clusteren inspectietechnieken. Belangrijk voor B&O. Ook overlap met betonkwaliteit C1. | G12: 0 | H12: 1 | I12: 1 | J12: 1 | K12: 2 | L12: 1 | M12: =SUM(G12:L12) -> 6 | N12: 1 | O12: ='Kennisagenda onderzoekslijnen'!G43 -> Inspecties, monitoring en data | Y12: ja
A13: SP | B13: ="SP_"&'Kennisagenda onderzoekslijnen'!C29 -> SP_A5 | E13: ='Kennisagenda onderzoekslijnen'!F29 -> Wat is de invloed van mogelijke strengere winters op ijsbelasting van sluizen, en in hoeverre moet dit worden meegenomen in beoordeling, ontwerp of beheermaatregelen? | G13: 1 | H13: 2 | I13: 1 | J13: 0 | K13: 1 | L13: 1 | M13: =SUM(G13:L13) -> 6 | N13: 2 | O13: ='Kennisagenda onderzoekslijnen'!G29 -> Technische levensduur - civiele delen | Y13: ja
A14: SP | B14: ="SP_"&'Kennisagenda onderzoekslijnen'!C32 -> SP_A6 | E14: ='Kennisagenda onderzoekslijnen'!F32 -> Welke eisen stellen de Machinerichtlijn en andere veiligheidskaders aan de besturing van spuien en gemalen, en wat betekent dit voor het ontwerp en beheer? | G14: 0 | H14: 1 | I14: 1 | J14: 1 | K14: 2 | L14: 2 | M14: =SUM(G14:L14) -> 7 | N14: 1 | O14: ='Kennisagenda onderzoekslijnen'!G32 -> Technische levensduur - civiele delen | Y14: ja
A15: SP | B15: ="SP_"&'Kennisagenda onderzoekslijnen'!C81 -> SP_C13 | E15: ='Kennisagenda onderzoekslijnen'!F81 -> Hoe kan de beschikbaarheid van systemen in oude sluizen worden geborgd, gegeven de beperkte beschikbaarheid van specifieke materialen en kennis? | G15: 0 | H15: 1 | I15: 2 | J15: 1 | K15: 2 | L15: 2 | M15: =SUM(G15:L15) -> 8 | N15: 2 | O15: ='Kennisagenda onderzoekslijnen'!G81 -> Beschikbaarheid en robuustheid | Y15: ja
A16: SP | B16: ="SP_"&'Kennisagenda onderzoekslijnen'!C45 -> SP_C14 | E16: ='Kennisagenda onderzoekslijnen'!F45 -> Hoe kan de beschikbaarheid en kwaliteit van ontwerp-, beheer- en inspectiedata worden verbeterd om uitvoering en onderhoud efficiënter en beter voorspelbaar te maken? | G16: 1 | H16: 0 | I16: 0 | J16: 1 | K16: 2 | L16: 2 | M16: =SUM(G16:L16) -> 6 | N16: 2 | O16: ='Kennisagenda onderzoekslijnen'!G45 -> Inspecties, monitoring en data | Y16: ja
A17: SP | B17: ="SP_"&'Kennisagenda onderzoekslijnen'!C94 -> SP_C15 | E17: ='Kennisagenda onderzoekslijnen'!F94 -> Hoe kan het energiegebruik van het gemaal en de sluis worden geoptimaliseerd (bijv. energiezuinig pompen en afstemming op energieaanbod) zonder afbreuk te doen aan beschikbaarheid en functioneren? | G17: 0 | H17: 1 | I17: 1 | J17: 3 | K17: 1 | L17: 2 | M17: =SUM(G17:L17) -> 8 | N17: 2 | O17: ='Kennisagenda onderzoekslijnen'!G94 -> Stategie, afweging en keuzes | Y17: ja
A18: SP | B18: ="SP_"&'Kennisagenda onderzoekslijnen'!C44 -> SP_C16 | E18: ='Kennisagenda onderzoekslijnen'!F44 -> Welke inspectie-, monitoring- en datagedreven technieken (incl. AI) zijn geschikt om de staat van betonconstructies en installaties betrouwbaar te beoordelen en intern inzichtelijk te maken? | F18: Van belang voor beheer en onderhoud | G18: 1 | H18: 1 | I18: 1 | J18: 1 | K18: 3 | L18: 1 | M18: =SUM(G18:L18) -> 8 | N18: 1 | O18: ='Kennisagenda onderzoekslijnen'!G44 -> Inspecties, monitoring en data | Y18: ja
A19: SP | B19: ="SP_"&'Kennisagenda onderzoekslijnen'!C46 -> SP_C17 | E19: ='Kennisagenda onderzoekslijnen'!F46 -> Hoe kunnen reparatietechnieken en boorkernonderzoek worden geoptimaliseerd om het beheer en onderhoud van betonconstructies efficiënter uit te voeren? | F19: Van belang voor beheer en onderhoud | G19: 1 | H19: 1 | I19: 0 | J19: 1 | K19: 3 | L19: 1 | M19: =SUM(G19:L19) -> 7 | N19: 1 | O19: ='Kennisagenda onderzoekslijnen'!G46 -> Inspecties, monitoring en data | Y19: ja
A20: SP | B20: ="SP_"&'Kennisagenda onderzoekslijnen'!C77 -> SP_C18 | E20: ='Kennisagenda onderzoekslijnen'!F77 -> In hoeverre kan turbineren met bestaande gemalen worden toegepast, gegeven beperkingen zoals trillingen en schade, en welke ontwerpaanpassingen zijn nodig? | G20: 1 | H20: 2 | I20: 0 | J20: 2 | K20: 1 | L20: 2 | M20: =SUM(G20:L20) -> 8 | N20: 2 | O20: ='Kennisagenda onderzoekslijnen'!G77 -> Operatie: bediening en besturing
A21: SP | B21: ="SP_"&'Kennisagenda onderzoekslijnen'!C33 -> SP_A7 | E21: ='Kennisagenda onderzoekslijnen'!F33 -> Welke duurzame alternatieven voor smeermiddelen en hydraulische systemen zijn toepasbaar en wat zijn de effecten op functioneren en betrouwbaarheid van het object? | F21: Foutekeuze: Niet functioneren sluis. Geen of positieve invloed op functioneren. | G21: 1 | H21: 1 | I21: 1 | J21: 2 | K21: 2 | L21: 1 | M21: =SUM(G21:L21) -> 8 | N21: 2 | O21: ='Kennisagenda onderzoekslijnen'!G33 -> Technische levensduur - civiele delen | Y21: ja
A22: SP | B22: ="SP_"&'Kennisagenda onderzoekslijnen'!C71 -> SP_C20 | E22: ='Kennisagenda onderzoekslijnen'!F71 -> In hoeverre kan het kanaal in de toekomst een rol spelen als route voor defensie? Wat betekent dit voor het functioneren van de scheepvaartroute? Wat betekent dit voor het functioneren en de eisen aan sluis Panheel? | F22: Esra: Mogelijk erg bepalend voor toekomstige beschikbaarheid andere functies en ook van belang met betrekking tot eisen voor functioneren. Ook voor wat-als situaties: Calamiteiten en dan vereisten voor defensie? Jos: Onwaarschijnlijk dat transportroutes defensie voor Panheel route zouden kiezen. Carrina mee eens. Andere routes voor de hand liggender, al was het maar over de weg. Programma Weerbaarheid gaat dit afpellen. Dus dat afwachten (al is het misschien vertrouwelijk?) | G22: 0 | H22: 1 | I22: 2 | J22: 1 | K22: 1 | L22: 1 | M22: =SUM(G22:L22) -> 6 | N22: 3 | O22: ='Kennisagenda onderzoekslijnen'!G71 -> Functies van het complex in het netwerk (scheepvaart, weg en water) | Y22: ja
A23: SP | B23: ="SP_"&'Kennisagenda onderzoekslijnen'!C55 -> SP_C21 | E23: ='Kennisagenda onderzoekslijnen'!F55 -> In hoeverre kunnen veranderingen in wateraanvoerafspraken met België optreden en wat betekent dit voor de hydraulische belasting en het functioneren van sluis Panheel? | G23: 1 | H23: 2 | I23: 1 | J23: 1 | K23: 1 | L23: 2 | M23: =SUM(G23:L23) -> 8 | N23: 3 | O23: ='Kennisagenda onderzoekslijnen'!G55 -> Watersysteem en waterbeschikbaarheid | Y23: nee
A24: SP | B24: ="SP_"&'Kennisagenda onderzoekslijnen'!C95 -> SP_A8 | E24: ='Kennisagenda onderzoekslijnen'!F95 -> Hoe om te gaan met de effecten van budgettekorten en het kennisbehoud (bij RWS en aannemers) op de risico's en de instandhouding van sluizen, en wat betekent dit voor de prioritering van objecten binnen het areaal? | F24: Kennisbehoud hier er uit (zit in EF3,4,5). Tom (maar breed gedragen): Erg belangrijk voor B&O: Dingen die niet werken nu al. Ook voor hoofdfuncties. Esther: Dat er geen budget is heeft veel invloed, maar niet kennisvraag. Uitgaande van een budget tekort: Hoe kun je het beste afwegingen en keuzes maken? Werkt door op alle functies. Speelt al jaren, is alleen nu extreem. Onderbouwen van risico's (incl worst case: kleine kans groot gevolg) van geen geld. Hoe onderbouw je keuzes die gemaakt moeten worden door beperkt budget (moet ook in grotere beeld). | G24: 1 | H24: 2 | I24: 2 | J24: 2 | K24: 3 | L24: 2 | M24: =SUM(G24:L24) -> 12 | N24: 2 | O24: ='Kennisagenda onderzoekslijnen'!G95 -> Stategie, afweging en keuzes | Y24: ja
A25: SP | B25: ="SP_"&'Kennisagenda onderzoekslijnen'!C34 -> SP_A9 | E25: ='Kennisagenda onderzoekslijnen'!F34 -> Hoe kan een balans worden gevonden tussen standaardisatie en object-specifieke keuzes in bediening en besturing van sluizen? | G25: 0 | H25: 1 | I25: 2 | J25: 1 | K25: 2 | L25: 2 | M25: =SUM(G25:L25) -> 8 | N25: 2 | O25: ='Kennisagenda onderzoekslijnen'!G34 -> Technische levensduur - civiele delen | Y25: ja
A26: SP | B26: ="SP_"&'Kennisagenda onderzoekslijnen'!C23 -> SP_ET1 | E26: ='Kennisagenda onderzoekslijnen'!F23 -> Wat is de actuele constructieve veiligheid van de betonconstructies van de oude sluis Panheel, gegeven dat de ontwerplevensduur is bereikt, en welke onzekerheden beïnvloeden deze beoordeling? | F26: Wilco: belangrijk (breder gedragen). Urgentie voor oude sluis is hoger dan voor nieuwe sluis. | G26: 1 | H26: 2 | I26: 2 | J26: 2 | K26: 3 | L26: 1 | M26: =SUM(G26:L26) -> 11 | N26: 1 | O26: ='Kennisagenda onderzoekslijnen'!G23 -> Technische levensduur - civiele delen | Y26: ja
A27: SP | B27: ="SP_"&'Kennisagenda onderzoekslijnen'!C26 -> SP_ET2 | E27: ='Kennisagenda onderzoekslijnen'!F26 -> Wat is de actuele constructieve veiligheid van de betonconstructies van de nieuwe sluis Panheel, gegeven dat de ontwerplevensduur nog niet is bereikt, en welke onzekerheden beïnvloeden deze beoordeling? | F27: Wilco: belangrijk (breder gedragen) | G27: 1 | H27: 1 | I27: 2 | J27: 2 | K27: 2 | L27: 1 | M27: =SUM(G27:L27) -> 9 | N27: 2 | O27: ='Kennisagenda onderzoekslijnen'!G26 -> Technische levensduur - civiele delen | Y27: ja
A28: SP | B28: ="SP_"&'Kennisagenda onderzoekslijnen'!C27 -> SP_ET3 | E28: ='Kennisagenda onderzoekslijnen'!F27 -> Welke functionele eisen worden aan sluizencomplex Panheel gesteld en in hoeverre moeten constructieve componenten van de oude sluis hierop worden aangepast volgens den huidige normen? | F28: Wilco: Dit is een EF-vraag. | G28: 1 | H28: 2 | I28: 2 | J28: 2 | K28: 2 | L28: 1 | M28: =SUM(G28:L28) -> 10 | N28: 2 | O28: ='Kennisagenda onderzoekslijnen'!G27 -> Technische levensduur - civiele delen
A29: SP | B29: ="SP_"&'Kennisagenda onderzoekslijnen'!C82 -> SP_ET4 | E29: ='Kennisagenda onderzoekslijnen'!F82 -> Welke mate van redundantie (bijv. reservedeuren of alternatieven) is nodig om de beschikbaarheid en robuustheid van het sluizencomplex te borgen? | G29: 0 | H29: 2 | I29: 2 | J29: 1 | K29: 2 | L29: 2 | M29: =SUM(G29:L29) -> 9 | N29: 2 | O29: ='Kennisagenda onderzoekslijnen'!G82 -> Beschikbaarheid en robuustheid | Y29: ja
A30: SP | B30: ="SP_"&'Kennisagenda onderzoekslijnen'!C84 -> SP_ET5 | E30: ='Kennisagenda onderzoekslijnen'!F84 -> Welke risico’s voor veiligheid en beschikbaarheid ontstaan bij langdurige spanningsuitval voor welke functies, hoe erg is dit, en waar zijn noodstroomvoorzieningen (zoals aggregaten) noodzakelijk binnen het sluizencomplex? Hoe ziet een draaiboek bij stroomuitvalling eruit? | G30: 1 | H30: 2 | I30: 2 | J30: 1 | K30: 1 | L30: 2 | M30: =SUM(G30:L30) -> 9 | N30: 1 | O30: ='Kennisagenda onderzoekslijnen'!G84 -> Beschikbaarheid en robuustheid | Y30: ja
A31: SP | B31: ="SP_"&'Kennisagenda onderzoekslijnen'!C25 -> SP_ET6 | E31: ='Kennisagenda onderzoekslijnen'!F25 -> In hoeverre is verlenging van de levensduur van het sluizencomplex (oude sluis) mogelijk en welke factoren zijn daarbij bepalend? | F31: Wilco: belangrijk (breder gedragen) | G31: 1 | H31: 2 | I31: 2 | J31: 1 | K31: 3 | L31: 1 | M31: =SUM(G31:L31) -> 10 | N31: 2 | O31: ='Kennisagenda onderzoekslijnen'!G25 -> Technische levensduur - civiele delen | Y31: ja
A32: SP | B32: ="SP_"&'Kennisagenda onderzoekslijnen'!C87 -> SP_EF1 | E32: ='Kennisagenda onderzoekslijnen'!F87 -> Wat is de lange termijn visie/plan voor de toekomst van sluizencomplex Panheel, rekeninghoudend met veranderende wensen/gebruik (functies), budgetverminderingen, kennisbehoud, etc. (incl. keuzemomenten en adaptatiepaden)? | F32: Greta: Hier komen veel factoren samen (oa 1-2 sluizen) in combi met resterende levensduur. Komt meerdere keren terug, brengt samen budgetten etc. | G32: 2 | H32: 2 | I32: 2 | J32: 2 | K32: 2 | L32: 1 | M32: =SUM(G32:L32) -> 11 | N32: 2 | O32: ='Kennisagenda onderzoekslijnen'!G87 -> Stategie, afweging en keuzes | Y32: nee
A33: SP | B33: ="SP_"&'Kennisagenda onderzoekslijnen'!C88 -> SP_EF2 | E33: ='Kennisagenda onderzoekslijnen'!F88 -> Wat zijn de effecten van exploitatie met één kolk op beschikbaarheid, scheepvaart (inclusief voorhavens) en beheer, en welke sluis is daarbij het meest geschikt om te behouden? | G33: 1 | H33: 2 | I33: 2 | J33: 1 | K33: 2 | L33: 2 | M33: =SUM(G33:L33) -> 10 | N33: 2 | O33: ='Kennisagenda onderzoekslijnen'!G88 -> Stategie, afweging en keuzes | Y33: nee
A34: SP | B34: ="SP_"&'Kennisagenda onderzoekslijnen'!C108 -> SP_A10 | E34: ='Kennisagenda onderzoekslijnen'!F108 -> Hoe zorg je voor kennisniveau en kenniscontinuïteit bij marktpartijen, inclusief borging bij leverancierwisselingen en personeelsverloop? | G34: 1 | H34: 1 | I34: 1 | J34: 2 | K34: 2 | L34: 1 | M34: =SUM(G34:L34) -> 8 | N34: 2 | O34: ='Kennisagenda onderzoekslijnen'!G108 -> Organisatorische aspecten | Y34: ja
A35: SP | B35: ="SP_"&'Kennisagenda onderzoekslijnen'!C109 -> SP_A11 | E35: ='Kennisagenda onderzoekslijnen'!F109 -> Hoe ontwikkelt de externe uitvoeringscapaciteit (bijvoorbeeld bij aannemers) voor het beheer en onderhoud van sluizen zich, en in hoeverre is deze toereikend voor de toekomstige opgave? | G35: 0 | H35: 1 | I35: 1 | J35: 2 | K35: 2 | L35: 1 | M35: =SUM(G35:L35) -> 7 | N35: 2 | O35: ='Kennisagenda onderzoekslijnen'!G109 -> Organisatorische aspecten | Y35: ja
A36: SP | B36: ="SP_"&'Kennisagenda onderzoekslijnen'!C106 -> SP_A12 | E36: ='Kennisagenda onderzoekslijnen'!F106 -> Hoe behoud je de benodige kennis voor B&O en vervanging/renovatie/vernieuwing binnen de organisatie (RWS)? | G36: 1 | H36: 2 | I36: 1 | J36: 2 | K36: 2 | L36: 1 | M36: =SUM(G36:L36) -> 9 | N36: 2 | O36: ='Kennisagenda onderzoekslijnen'!G106 -> Organisatorische aspecten | Y36: ja
B37: ="SP_"&'Kennisagenda onderzoekslijnen'!C107 -> SP_A13 | E37: ='Kennisagenda onderzoekslijnen'!F107 -> Hoe behoud je de benodige kennis voor operationele sturing (extreme condities), maar ook B&O en vervanging/renovatie/vernieuwing bij overige partners? | F37: Erg lage prioritering (Kees, Carla) | G37: 0 | H37: 2 | I37: 1 | J37: 1 | K37: 1 | L37: 2 | M37: =SUM(G37:L37) -> 7 | N37: 2 | O37: ='Kennisagenda onderzoekslijnen'!G107 -> Organisatorische aspecten | Y37: ja
A38: SP | B38: ="SP_"&'Kennisagenda onderzoekslijnen'!C54 -> SP_EF7 | E38: ='Kennisagenda onderzoekslijnen'!F54 -> Wat wordt de toekomstige waterbalans van het watersysteem waarvan Panheel een onderdeel uitmaakt (inclusief traject Maastricht - Linne & samenwerking met Belgie) voor de verschillende seizoenen (inclusief wateroverlast en droogte)? | F38: Tom: Uitwerken waterbesxchikbaarheid Maas kanalen gewenst (op netwerk niveau juiste prioriteiten uitwerken: waar pompen inzetten?). Wordt nu nog niet goed uitgewerkt (incl opstellen redeneerlijn). Veel uitgewerkt door Deltares over toekomst Maas-watersysteem (Carina: oude stress testen geen Panheel, nieuwe stress test (scheepvaart + waterbeheer inclusief inzet pompen (altijd inzetten)), maar altijd met uitzondering van Panheel (niet uitgewerkt). Op panheel maatregel pomp beschikbaar (voor watervoorziening naar kanaal), dus relevant om te beschouwen. Tom: Kijk naar laatste toegevoegde vraag over scheepvaart corridor, wat zijn implicaties in wateraanbod, peilgevolgen, etc? (misschien geen probleem, aldus Carla, want belegd onder EF7) | G38: 1 | H38: 2 | I38: 2 | J38: 1 | K38: 1 | L38: 1 | M38: =SUM(G38:L38) -> 8 | N38: 2 | O38: ='Kennisagenda onderzoekslijnen'!G54 -> Watersysteem en waterbeschikbaarheid | Y38: nee
A39: SP | B39: ="SP_"&'Kennisagenda onderzoekslijnen'!C56 -> SP_EF8 | E39: ='Kennisagenda onderzoekslijnen'!F56 -> Welke eisen worden gesteld aan de verschillende functies (water bergen en water afvoeren) en componenten (lekverlies, schutverlies, spaarbekkens) van sluis Panheel? | G39: 1 | H39: 2 | I39: 2 | J39: 1 | K39: 2 | L39: 1 | M39: =SUM(G39:L39) -> 9 | N39: 3 | O39: ='Kennisagenda onderzoekslijnen'!G56 -> Watersysteem en waterbeschikbaarheid | Y39: nee
A40: SP | B40: ="SP_"&'Kennisagenda onderzoekslijnen'!C89 -> SP_EF9 | E40: ='Kennisagenda onderzoekslijnen'!F89 -> Wat zijn de (toekomstige) beleidskeuzes rondom Maaspeilen en het stuwprogramma, en wat is de invloed hiervan op waterstanden, hydraulische belastingen en het functioneren van het sluizencomplex (incl. bevaarbaarheid, voorhavens, bodem en oeverbescherming)? | G40: 1 | H40: 1 | I40: 2 | J40: 1 | K40: 1 | L40: 1 | M40: =SUM(G40:L40) -> 7 | N40: 3 | O40: ='Kennisagenda onderzoekslijnen'!G89 -> Stategie, afweging en keuzes | Y40: ja
A41: SP | B41: ="SP_"&'Kennisagenda onderzoekslijnen'!C76 -> SP_EF10 | E41: ='Kennisagenda onderzoekslijnen'!F76 -> Is het in de toekomst, bij een grotere afvoerbehoefte, nodig om andere routes te gebruiken dan spuien via de kolk? | G41: 1 | H41: 2 | I41: 1 | J41: 1 | K41: 1 | L41: 2 | M41: =SUM(G41:L41) -> 8 | N41: 3 | O41: ='Kennisagenda onderzoekslijnen'!G76 -> Operatie: bediening en besturing | Y41: nee
A42: SP | B42: ="SP_"&'Kennisagenda onderzoekslijnen'!C63 -> SP_EF13 | E42: ='Kennisagenda onderzoekslijnen'!F63 -> Wat zijn de toekomstige eisen aan sluizencomplex en kanaal voor waterkwaliteit, ecologie en natuuropgaven (zoals vissterfte bij gemalen, blauwalgen, Natura 2000-stikstofeisen i.r.t. scheepvaart en passeerbaarheid, zoals natuurvriendelijke oevers)? | G42: 0 | H42: 1 | I42: 1 | J42: 2 | K42: 2 | L42: 1 | M42: =SUM(G42:L42) -> 7 | N42: 2 | O42: ='Kennisagenda onderzoekslijnen'!G63 -> Ecologie en waterkwaliteit watersysteem | Y42: ja
A43: SP | B43: ="SP_"&'Kennisagenda onderzoekslijnen'!C90 -> SP_EF14 | E43: ='Kennisagenda onderzoekslijnen'!F90 -> Als de oude sluis een monumentstatus krijgt, wat betekent dit voor B&O en Vernieuwing? | G43: 2 | H43: 1 | I43: 1 | J43: 1 | K43: 2 | L43: 2 | M43: =SUM(G43:L43) -> 9 | N43: 2 | O43: ='Kennisagenda onderzoekslijnen'!G90 -> Stategie, afweging en keuzes | Y43: ja
A44: SP | B44: ="SP_"&'Kennisagenda onderzoekslijnen'!C80 -> SP_EF15 | E44: ='Kennisagenda onderzoekslijnen'!F80 -> Wat zijn de beschikbaarheidseisen van schutsluizen – harde eisen ten opzichte van wensen (schuttijden / passagetijden en stremmingen) nu en in de toekomst? | F44: Jos: 47min voor scheepspassage. | G44: 1 | H44: 1 | I44: 2 | J44: 1 | K44: 2 | L44: 2 | M44: =SUM(G44:L44) -> 9 | N44: 2 | O44: ='Kennisagenda onderzoekslijnen'!G80 -> Beschikbaarheid en robuustheid | Y44: ja
A45: SP | B45: ="SP_"&'Kennisagenda onderzoekslijnen'!C68 -> SP_EF16 | E45: ='Kennisagenda onderzoekslijnen'!F68 -> Voldoet sluizencomplex Panheel aan richtlijn vaarwegen? | G45: 1 | H45: 1 | I45: 2 | J45: 1 | K45: 1 | L45: 1 | M45: =SUM(G45:L45) -> 7 | N45: 1 | O45: ='Kennisagenda onderzoekslijnen'!G68 -> Functies van het complex in het netwerk (scheepvaart, weg en water) | Y45: nee
A46: SP | B46: ="SP_"&'Kennisagenda onderzoekslijnen'!C69 -> SP_EF17 | E46: ='Kennisagenda onderzoekslijnen'!F69 -> Wat is de verwachte ontwikkeling van de binnenvaart en gebruik van Sluizencomplex Panheel (incl. voorhavens) en welke voorzieningen zijn hiervoor nodig? | G46: 0 | H46: 1 | I46: 2 | J46: 1 | K46: 1 | L46: 1 | M46: =SUM(G46:L46) -> 6 | N46: 2 | O46: ='Kennisagenda onderzoekslijnen'!G69 -> Functies van het complex in het netwerk (scheepvaart, weg en water) | Y46: nee
A47: SP | B47: ="SP_"&'Kennisagenda onderzoekslijnen'!C72 -> SP_EF18 | E47: ='Kennisagenda onderzoekslijnen'!F72 -> Wat zijn de richtllijnen rondom walstroom (stroomvoorziening (electrische) schepen) bij sluizen? Wat zijn de kaders voor walstroom bij de rijksaanlegplaatsen? Voldoet de walstroomvoorziening van sluizencomplex Panheel aan de eisen? | G47: 0 | H47: 0 | I47: 2 | J47: 1 | K47: 1 | L47: 0 | M47: =SUM(G47:L47) -> 4 | N47: 3 | O47: ='Kennisagenda onderzoekslijnen'!G72 -> Functies van het complex in het netwerk (scheepvaart, weg en water) | Y47: ja
A48: SP | B48: ="SP_"&'Kennisagenda onderzoekslijnen'!C96 -> SP_EF19 | E48: ='Kennisagenda onderzoekslijnen'!F96 -> Waar kun je bezuinigen bij sluis Panheel zonder dat de veiligheid en functies in geding komen? | G48: 1 | H48: 1 | I48: 2 | J48: 1 | K48: 2 | L48: 1 | M48: =SUM(G48:L48) -> 8 | N48: 2 | O48: ='Kennisagenda onderzoekslijnen'!G96 -> Stategie, afweging en keuzes | Y48: nee
A49: SP | B49: ="SP_"&'Kennisagenda onderzoekslijnen'!C91 -> SP_EF20 | E49: ='Kennisagenda onderzoekslijnen'!F91 -> Hoe kunnen de spaarbekkens, riolen en het nivelleermiddel van de oude (noordelijke) sluis technisch en functioneel weer in gebruik worden genomen? | G49: 1 | H49: 3 | I49: 1 | J49: 1 | K49: 2 | L49: 1 | M49: =SUM(G49:L49) -> 9 | N49: 2 | O49: ='Kennisagenda onderzoekslijnen'!G91 -> Stategie, afweging en keuzes | Y49: nee
A50: SP | B50: ="SP_"&'Kennisagenda onderzoekslijnen'!C92 -> SP_EF21 | E50: ='Kennisagenda onderzoekslijnen'!F92 -> Welke rol kan de oude sluis (inclusief werkende spaarbekkens) spelen in het minimaliseren van watergebruik binnen het sluizencomplex Panheel, en welke maatregelen (zoals herstel of aanpassing van de nieuwe sluis) zijn daarvoor het meest effectief? | F50: Greta: Laaghangend fruit en erg wenselijk. Moet prioriteit hebben. Kleine studie die noodzaak spaarbekkens legt, daarmee minder druk pompen en meer mogelijkheden voor toekomstig beheer. Kwantitatief maken waterbesparing, wsaterbalans, en efficiency spaarbekkens. Daarmee geen aantasting beton spaarbekkens. Besparing: water, k(E), energie! | G50: 0 | H50: 2 | I50: 1 | J50: 0 | K50: 2 | L50: 2 | M50: =SUM(G50:L50) -> 7 | N50: 2 | O50: ='Kennisagenda onderzoekslijnen'!G92 -> Stategie, afweging en keuzes | Y50: nee
A51: SP | B51: ="SP_"&'Kennisagenda onderzoekslijnen'!C93 -> SP_EF22 | E51: ='Kennisagenda onderzoekslijnen'!F93 -> Welke integrale en ‘sober en doelmatige’ afweging is mogelijk voor ingrepen aan het sluizencomplex Panheel, rekening houdend met watergebruik, duurzaamheid, kosten en beschikbaarheid, en welke methoden (zoals LCC, LCA en de bedrijfswaardenmatrix) zijn daarbij geschikt? | G51: 0 | H51: 1 | I51: 1 | J51: 1 | K51: 3 | L51: 1 | M51: =SUM(G51:L51) -> 7 | N51: 2 | O51: ='Kennisagenda onderzoekslijnen'!G93 -> Stategie, afweging en keuzes | Y51: ja
A52: SP | B52: ="SP_"&'Kennisagenda onderzoekslijnen'!C62 -> SP_EF23 | E52: ='Kennisagenda onderzoekslijnen'!F62 -> Welke eisen stelt de KRW en natuurwetgeving aan het functioneren van een gemaal met betrekking tot visvriendelijkheid en vispasseerbaarheid? | G52: 0 | H52: 1 | I52: 1 | J52: 2 | K52: 1 | L52: 1 | M52: =SUM(G52:L52) -> 6 | N52: 2 | O52: ='Kennisagenda onderzoekslijnen'!G62 -> Ecologie en waterkwaliteit watersysteem | Y52: ja
A53: SP | B53: ="SP_"&'Kennisagenda onderzoekslijnen'!C64 -> SP_EF24 | E53: ='Kennisagenda onderzoekslijnen'!F64 -> Welke maatregelen zijn mogelijk om het gemaal visvriendelijker (voorkomen vermaling) te maken en wat is het effect daarvan op functioneren en prestaties? | G53: 0 | H53: 1 | I53: 0 | J53: 2 | K53: 2 | L53: 2 | M53: =SUM(G53:L53) -> 7 | N53: 2 | O53: ='Kennisagenda onderzoekslijnen'!G64 -> Ecologie en waterkwaliteit watersysteem | Y53: ja
A54: SP | B54: ="SP_"&'Kennisagenda onderzoekslijnen'!C57 -> SP_A1 | E54: ='Kennisagenda onderzoekslijnen'!F57 -> Hoe kunnen klimaatscenario’s worden vertaald naar hydraulische randvoorwaarden voor het functioneren en de beoordeling van het sluizencomplex? | F54: Voor Panheel wat minder van belang, maar voor bijv. stuwprogramma en RWS breed wel relevant. | G54: 2 | H54: 2 | I54: 1 | J54: 1 | K54: 1 | L54: 1 | M54: =SUM(G54:L54) -> 8 | N54: 2 | O54: ='Kennisagenda onderzoekslijnen'!G57 -> Watersysteem en waterbeschikbaarheid | Y54: ja
A55: SP | B55: ="SP_"&'Kennisagenda onderzoekslijnen'!C58 -> SP_A2 | E55: ='Kennisagenda onderzoekslijnen'!F58 -> Hoe kunnen klimaatscenario’s worden vertaald naar lokale omstandigheden en randvoorwaarden voor het functioneren van het sluizencomplex? | F55: Voor Panheel wat minder van belang, maar voor bijv. stuwprogramma en RWS breed wel relevant. | G55: 2 | H55: 2 | I55: 1 | J55: 1 | K55: 2 | L55: 1 | M55: =SUM(G55:L55) -> 9 | N55: 2 | O55: ='Kennisagenda onderzoekslijnen'!G58 -> Watersysteem en waterbeschikbaarheid | Y55: ja
A56: SP | B56: ="SP_"&'Kennisagenda onderzoekslijnen'!C97 -> SP_A3 | E56: ='Kennisagenda onderzoekslijnen'!F97 -> Wat wordt de toekomstige afweging tussen duurzaamheid vs. verdringingsreeks, maar ook energieverbruik en circulariteit van aanleveren van componenten bij sluizen? | F56: Carina: hangt samen met redeneerlijn, toekomstige waerbalans, verdringingsreeks. Duurzaamheid haakt hier op in. (Waterbalans Grensmaas speelt hierin mee (meer water bij Maastricht via Grensmaas goed voor locale ecologie en dan extra oppompen via Panheel (ipv in Maastricht meer water richting Panheel voeren), is geen kennisvraag.) | G56: 1 | H56: 2 | I56: 2 | J56: 1 | K56: 1 | L56: 2 | M56: =SUM(G56:L56) -> 9 | N56: 2 | O56: ='Kennisagenda onderzoekslijnen'!G97 -> Stategie, afweging en keuzes | Y56: ja
A57: SP | B57: ="SP_"&'Kennisagenda onderzoekslijnen'!C98 -> SP_A4 | E57: ='Kennisagenda onderzoekslijnen'!F98 -> Hoe vertaal je de eis op netwerkniveau naar een realistische eis op complex/objecten niveau? | F57: Martine (breder beaamd): Door RWS nog te kraken, met veel samenhang met andere vragen (uit dit lijstje). Erg belangrijk. Urgentie: Naast Ecologie, ook prioriteit voor Waterbeheer, Scheepvaart, en snel antwoord nodig. Daarmee ook breder toepasbaar qua methodiek en kennis. Toevoegen prioriteit voor Asset Management? | G57: 1 | H57: 2 | I57: 1 | J57: 2 | K57: 1 | L57: 0 | M57: =SUM(G57:L57) -> 7 | N57: 2 | O57: ='Kennisagenda onderzoekslijnen'!G98 -> Stategie, afweging en keuzes | Y57: ja
A58: SP | B58: ="SP_"&'Kennisagenda onderzoekslijnen'!C28 -> SP_C11 | E58: ='Kennisagenda onderzoekslijnen'!F28 -> Zouden nieuwe onderdelen aan de ROK – constructieve veiligheidseis - moeten voldoen als de rest van het complex daar niet aan voldoet (Is dat dan niet een te hoge eis?)? Afwegingskader: moet je de hoogste kaders / normen gebruiken of is een lagere eis soms voldoende? | M58: 1 | N58: 2 | O58: ='Kennisagenda onderzoekslijnen'!G28 -> Technische levensduur - civiele delen
A59: SP | B59: ="SP_"&'Kennisagenda onderzoekslijnen'!C47 -> SP_C23 | E59: ='Kennisagenda onderzoekslijnen'!F47 -> Hoe kunnen inzichten uit inspecties worden vertaald naar andere sluizen en sluizenfamilies? | M59: 1 | N59: 2 | O59: ='Kennisagenda onderzoekslijnen'!G47 -> Inspecties, monitoring en data
A60: SP | B60: ="SP_"&'Kennisagenda onderzoekslijnen'!C48 -> SP_A16 | E60: ='Kennisagenda onderzoekslijnen'!F48 -> Hoe kun je zorgen dat kennis uit onderzoeken voor één sluis ook gebruikt wordt bij andere sluizen? | M60: 1 | N60: 2 | O60: ='Kennisagenda onderzoekslijnen'!G48 -> Inspecties, monitoring en data
A61: SP | B61: ="SP_"&'Kennisagenda onderzoekslijnen'!C75 -> SP_EF25 | E61: ='Kennisagenda onderzoekslijnen'!F75 -> Welke van de spuimiddelen kunnen we nu en in de toekomst het beste inzetten bij teveel water (bijv. spuien door kolken, spuiriool of spuien via gemaal)? | M61: 9 | N61: 3 | O61: ='Kennisagenda onderzoekslijnen'!G75 -> Operatie: bediening en besturing
A62: SP | B62: ="SP_"&'Kennisagenda onderzoekslijnen'!C83 -> SP_C24 | E62: ='Kennisagenda onderzoekslijnen'!F83 -> Welke standaard oplossing is te bedenken voor redundantie voor stroom of glasvezel? | M62: 1 | N62: 2 | O62: ='Kennisagenda onderzoekslijnen'!G83 -> Beschikbaarheid en robuustheid
A63: SP | B63: ="SP_"&'Kennisagenda onderzoekslijnen'!C67 -> SP_EF26 | E63: ='Kennisagenda onderzoekslijnen'!F67 -> Wat is de functie van sluis Panheel in de scheepvaart corridors vanuit de netwerkbenadering? | M63: 1 | N63: 3 | O63: ='Kennisagenda onderzoekslijnen'!G67 -> Functies van het complex in het netwerk (scheepvaart, weg en water)
A64: SP | B64: ="SP_"&'Kennisagenda onderzoekslijnen'!C70 -> SP_EF27 | E64: ='Kennisagenda onderzoekslijnen'!F70 -> Wat is de invloed van de ontwikkelingen in de scheepvaart op de staat van de componenten en wat je van de componenten vraagt? | M64: 1 | N64: 2 | O64: ='Kennisagenda onderzoekslijnen'!G70 -> Functies van het complex in het netwerk (scheepvaart, weg en water)
A65: SP | B65: ="SP_"&'Kennisagenda onderzoekslijnen'!C102 -> SP_C12 | E65: ='Kennisagenda onderzoekslijnen'!F102 -> Wat is de potentie voor hergebruik van materialen/elementen? | M65: 1 | N65: 3 | O65: ='Kennisagenda onderzoekslijnen'!G102 -> Milieu-impact
A66: SP | B66: ="SP_"&'Kennisagenda onderzoekslijnen'!C99 -> SP_C19 | E66: ='Kennisagenda onderzoekslijnen'!F99 -> Waar gaat tijd, geld, milieu impact inzitten in dagelijks B&O sluis Panheel en waar is winst te behalen? | M66: 9 | N66: 2 | O66: ='Kennisagenda onderzoekslijnen'!G99 -> Stategie, afweging en keuzes
A67: SP | B67: ="SP_"&'Kennisagenda onderzoekslijnen'!C105 -> SP_A14 | E67: ='Kennisagenda onderzoekslijnen'!F105 -> Op welke aspecten wil je als RWS het stuur weer in handen krijgen in BenO en waar laat je het aan de markt over? Hoe zouden we de contractvorming moeten regelen? Welke methodiek werkt dan? | M67: 1 | N67: 2 | O67: ='Kennisagenda onderzoekslijnen'!G105 -> Organisatorische aspecten
A68: SP | B68: ="SP_"&'Kennisagenda onderzoekslijnen'!C110 -> SP_A15 | E68: ='Kennisagenda onderzoekslijnen'!F110 -> Waar kunnen standaardisatie en uniformering beheer en onderhoud ondersteunen? | M68: 1 | N68: 2 | O68: ='Kennisagenda onderzoekslijnen'!G110 -> Organisatorische aspecten
A69: SP | B69: ="SP_"&'Kennisagenda onderzoekslijnen'!C24 -> SP_C22 | E69: ='Kennisagenda onderzoekslijnen'!F24 -> Kan met behulp van de bewezen historische sterkte of een proefbelasting de resterende levensduur van de betonconstructie van de oude sluis worden bepaald? | M69: 9 | N69: 1 | O69: ='Kennisagenda onderzoekslijnen'!G24 -> Technische levensduur - civiele delen

Sheet Functie overzicht
A1: Complex | C1: Type functies complex | D1: Functies complex | E1: (Wettelijk) eisen / richtlijnen / wensen systeemniveau | F1: (Wettelijk) eisen / richtlijnen / wensen vertaald naar complex | G1: Object | H1: Functie object | I1: Eisen/wensen object | J1: Opmerkingen over eisen/wensen en relevantie voor functioneren van sluiscomplex | K1: Bron
A2: Sluiscomplex XX (dus incl. de andere objecten van dit complex) | C2: Waterveiligheid | D2: Beschermen tegen hoogwater vanuit XX | F2: sluis heeft geen eis/richtlijn voor kans op niet sluiten? - Pieter van Geer?
B3: indelen naar: Waterveiligheid
D4: afvoeren van overtollig water (van meer, rivier, kanaal etc.) | F4: Afvoercapaciteit complex - Moet water kunnen afvoeren (afhankelijk van complex: een of beide kanten op) | G4: spuisluis | H4: water afvoeren | I4: XX m3/tijd | J4: Zijn hier berekeningen van? Voor alle complexen of alleen voor de grote? En rekening gehouden met veranderende condities?
G5: schutsluis | H5: water afvoeren
G6: pomp | H6: water afvoeren
E7: peilbesluit | G7: vispassage | H7: water afvoeren
B8: Bereikbaarheid | C8: Waterbeheer | D8: voldoende zoetwater tegenhouden in tijden van droogte
C9: Water kwaliteit en ecologie | D9: Verzilting tegengaan
D11: Ecologie - passeerbaarheid | E11: KRW - eisen systeemniveau? - Tom | F11: XX % van de vissen passeren het complex | G11: vispassage | H11: passeerbaarheid vissen | I11: XX % van de vissen doorlaten??
G12: gemaal | H12: visvriendelijk malen | I12: XX % van de vissen laten overleven??
B13: Leefbaarheid | D13: Ecologie - splitsen: passeerbaarheid, waterkwaliteit, habitat - vestigingsklimaat, XXX
D14: Faciliteren broedseizoen voor het bevorderen van de ecologie (Natura2000) | E14: Boven water: vleermuizen, knaagdieren, vogels facileren op en rond het complex Onder water: xx | G14: kades | H14: natuurvriendelijkheid
B15: Calamiteiten??
D16: Calamiteiten
C17: Infrastructureel | D17: Wegverkeer | G17: brug | I17: Niet open tijdens de spits? Bereikbaarheid minimaal XXX? Continu beschikbaar? Afhankelijk van complex
D19: Scheepvaart | G19: schutsluis | I19: richtlijn schutsluis: max. XX uur /jaar niet bereikbaar + iets over wachttijden. Check bij stuwen Maas en Rolien
G20: stuw (indien onderdeel van complex)
D21: Nuts-voorzieningen | M21: maximale waterstand
C22: Overige functies | D22: Hoge iconische waarde van het netwerk. Er zijn spanningen tussen behoud monumentstatus en de veiligheid functie.
C23: Check bij laatste versie RP
C24: voorbeelden uitwerken

Sheet ETL
J1: Klimatologische en natuurlijke ontwikkelingen | AA1: Socio-economische ontwikkelingen | AH1: Beleidsmatige ontwikkelingen
B2: Autonome situatie | C2: Huidige (en ontwerp) staat | D2: Vermoeiing | E2: Slijtage | F2: Schade | G2: Degradatie | H2: Corrosie | I2: Drivers | J2: Zeespiegelstijging | K2: Verandering windklimaat | L2: Verandering golfklimaat | M2: Toename piekafvoer Maas & Rijn (voornamellijk in winter) | N2: Toename frequentie hoogwater Maas & Rijn (voornamelijk in winter) | O2: Afname afvoer Maas & Rijn (voornamelijk in zomer) | P2: Verandering Neerslagpatroon | Q2: Verandering luchttemperatuur | R2: Toename watertemperatuur | S2: Toename CO2-gehalte in de lucht | T2: Bodemdaling | U2: Verzilting | V2: Verandering sedimenttransport en bodemerosie | W2: Verandering afvoer verdeling rijn-maas monding | X2: Verandering in bodemligging haringvlietmonding | Y2: Verandering biodiversiteit in ecosysteem | Z2: Verandering in getijden | AA2: Verandering scheepvaartverkeer | AB2: Verandering bebouwing en/of verhoging waarde bebouwd achterland | AC2: Verandering in benodigd beveiligingsniveau | AD2: Technische ontwikkelingen (software, materiaal) | AE2: Verandering situatie leverancier | AF2: Vertrek/pensionering van kennisdragers | AG2: Energietransitie | AH2: Verandering (bv verlaging) onderhoudsbudget | AI2: Stikstofbeleid | AJ2: Verbod op gebruik materialen | AK2: Aanscherpen arbo veiligheidsnorm | AL2: Aanpassing sluitpeil | AM2: Vervanging HV | AN2: Nieuwe systeemeisen en/of -inrichting | AO2: Verlenging levensduur HV | AP2: Strengere waterveiligheidseis HV (faalkans en/of niet-sluiten kans) | AQ2: Algemene beleidskeuzes op (inter)nationaal niveau
A3: Keringonderdelen/-componenten
A4: Betonnen pijlers (incl machinekamer en oplegblokken weg) | C4: ET2 / ET3 | D4: - | E4: Door waterbeweging slijtage in de openingen. | F4: Pijler 8 zit een herstelplaat op na aanvaring met kotter. Moet dit verwerkt worden in een constructieve faalkans? Of is de constructieve staat een randvoorwaarde voor de foutenboom. Dan moeten we beoordelen of de constructie nog voldoet. | G4: Driver heeft geen invloed | H4: Corrosie van wapening waar er schade is. Carbonatatie? Hoe groot is dit effect en hoeveel maakt toename in CO2 uit?. Één pijler (14) heeft een holte met schade. Beton reparatie in een zoute omgeving is lastig, hoe kun je dit oplossen? Beton het liefst zoveel mogelijk heel houden - maak geen gatenkaas van de kering. Metingen naar chloride indringen geven ook inzicht in zwakke plekken. | J4: Je krijgt standaard meer hydrostatische kracht overal op vanaf de zeezijde. Of het functioneren daarmee in de problemen komt, denken we niet. De kering is robust ontworpen en het verleden heeft uitgewezen dat de kering de krachten makkelijk aan kan. | K4: Driver heeft geen invloed | L4: Driver heeft geen invloed | M4: Bij meer spuien komt er meer zand/sediment langs de pijlers waardoor de pijler wat sneller kan slijten. Dus monitoren maar niet een specifieke actie nodig. Daar zijn programmeringsinspecties voor. 24 uur tussen Lobith en afvoer bij HV, dat zijn drie spuiperiodes. 25miljoen m3 per seconde is de maximale spuicapaciteit. Event limburg was (maar) 8,5miljoen m3 per seconde. | N4: Driver heeft geen invloed | O4: Driver heeft geen invloed | P4: Driver heeft geen invloed | Q4: verwarming in de pijlers mogelijk toch nodig bij extreme koude events. Maar als je de zeeschuif openzet dan krijg je ook zout water bij de rivierzijde en smelt het ook. Tenzij bij echt extreme kou | R4: Driver heeft geen invloed | S4: ET11 | T4: 2 keer per jaar deformatie metingen ivm kieren - wordt omgezet naar 1 keer omdat er nooit iets naarvoren komt en dit voldoende is | U4: Driver heeft geen invloed | V4: ET12 | W4: Driver heeft geen invloed | X4: - | Y4: - | Z4: Driver heeft geen invloed | AA4: Driver heeft geen invloed | AB4: Driver heeft geen invloed | AC4: Vanaf de weg en het water kun je relatief makkelijk de pijler in. Maar nu bezig met een nieuw systeem om te controleren of iets of iemand in de kering is. Ongoing vraagstuk | AD4: - | AE4: - | AF4: - | AG4: - | AI4: Driver heeft geen invloed | AJ4: Driver heeft geen invloed | AK4: er zitten stalen hekjes op de pijlers die te laag zijn. (hekjes moeten steeds hoger) | AL4: Driver heeft geen invloed | AM4: Driver heeft geen invloed | AN4: - | AO4: Beton kan wel lang mee, wel opletten met blootliggende wapening | AP4: Gerard vragen wat zijn de faalkansgevoelige onderdelen? Kijken we naar 1 schuif of de gehele kering, veel is redunant. Er wordt gewerkt met scenario's en daar is een overzicht van wat de grootste bijdragen heeft. Het faalkans model moet opnieuw opgezet worden, elke keer als er iets aangepast moet worden dan moet er op zoveel meer plekken iets aangepast worden. Dus steeds tegen nieuwe dingen aanlopen voor een update. Hier zit een tekortkoming in. Het zal een beter model (beter de werkelijkheid vangen) worden. Relais voor 1 opening zit er 17 keer in maar zit er niet goed in voor commoncostfailures. We gebruiken 1/3 van het faalkansbudget. Gaat dus om prestatiepeilen en niet constructieve faalkanseis. Zelf een prestatiepeil voorstel aan DGWB gestuurd en beheerruimte gedefinieerd en dat wordt nu toegepast. Nu hiervoor gekeken naar de maximale faalkansen in de afgelopen 10 jaar en op basis daarvan is een beheerruimte berekend. Maar je wil het eigenlijk andersom netjes doorrekenen | AQ4: Driver heeft geen invloed
A5: Betonnen (nabla)liggers | C5: ET4 | D5: - | E5: Het enige wat zou kunnen is betonrot wat je niet kunt zien, maar onwaarschijnlijk | F5: ET4 | H5: nvt | J5: Krachtafdracht van de schuiven op de nablaligger neemt toe. Maar de kering kan de krachten makkelijk aan en bewezen sterkte. | M5: Alles is zodanig sterk ontworpen dat hier geen zorgen of vragen over zijn | Q5: - | S5: ET11 | T5: - | V5: - | X5: - | Y5: - | AC5: - | AD5: - | AE5: - | AF5: - | AG5: - | AK5: - | AN5: - | AO5: - | AP5: -
A6: Zeeschuif+arm | C6: - | D6: Dikte en haarscheurtjes worden gemonitord tijdens conserveren - elke 7 jaar. En elke 25 jaar opnieuw conserveren | E6: Kan in de rollagers zitten. Het zijn allemaal langzaambewegende lagers. Dit wordt gemonitord en nooit iets geks gezien. Lang stil staan is problematischer dan vaak langzaam bewegen | F6: Looproosters in de schuiven kunnen schade krijgen door bv zeehonden | H6: ET6 | J6: Bij grote zeespiegelstijging kan overworgen worden om de schuif te verhogen, maar dat raakt ook aan monumentale status | M6: - | Q6: ET15 Als het algemeen warmer wordt, zal er meer verkrijting van de verf zijn en dus snelleren afname kwaliteit conservering | S6: - | T6: - | V6: Meer zand is meer schuring maar niet in onderzoek en geen zorgen over | X6: ET13 | Y6: ET 16? Nog geen ijzer-etende bacterie gevonden bij HV. Marine aangroei maakt de conservering weker, meer aantasting. Heeft enige invloed op onderhoud/conserveren van 24 misschien naar 20 jaar maar dat is nog steeds maar 2 keer tot einde levensduur | AC6: - | AD6: - | AE6: - | AF6: - | AG6: - | AH6: De conservering van de schuiven loopt momenteel achter op het instandhoudingsplan. DIt is een groot aandachtspunt maar in relatie tot onderhoudsbudget is geen kennisvraag geindentificeerd. | AK6: - | AN6: - | AO6: ET6 | AP6: -
A7: Rivierschuif+arm | C7: - | D7: Dikte en haarscheurtjes worden gemonitord tijdens conserveren - elke 7 jaar. En elke 25 jaar opnieuw conserveren | E7: Kan in de rollagers zitten. Het zijn allemaal langzaambewegende lagers. Dit wordt gemonitord en nooit iets geks gezien. Lang stil staan is problematischer dan vaak langzaam bewegen | F7: Looproosters in de schuiven kunnen schade krijgen door bv zeehonden | H7: ET6 | J7: Bij grote zeespiegelstijging kan overworgen worden om de schuif te verhogen, maar dat raakt ook aan monumentale status | M7: - | Q7: De spleet tussen de balg en de schuif is gemeten bij verschillende temperaturen, er zit voldoende ruimte voor temperatuurverschillen | S7: - | T7: - | V7: Meer zand is meer schuring maar niet in onderzoek en geen zorgen over | X7: ET13 | Y7: ET16 Nog geen ijzer-etende bacterie gevonden bij HV | AC7: - | AD7: - | AE7: - | AF7: - | AG7: - | AH7: De conservering van de schuiven loopt momenteel achter op het instandhoudingsplan. DIt is een groot aandachtspunt maar in relatie tot onderhoudsbudget is geen kennisvraag geindentificeerd. | AK7: - | AN7: - | AO7: ET6 | AP7: -
A8: Bewegingswerk (cilinders, trekstang, giek) | C8: ET1/ET5 | D8: zwakste draaipunt (D) laten ze nu doorrekenen. Hydraulische pomp en kleppen in een volgend onderzoek (revisie of vervanging) . Draaipunt waar de hele schuif aan hangt is meest kritisch voor vermoeiing | E8: ET1/ET7/ET10 | F8: - | H8: Standaard binnen B&O aangepakt | J8: ET8/ET9 | M8: ET8/ET9 | Q8: kan een verhoging van lucht temperatuur zorgen voor meer slijtage aan bewigingsdelen door uitzetting van stalen onderdelen? | S8: - | T8: - | V8: - | X8: - | Y8: - | AC8: - | AD8: - | AE8: - | AF8: - | AG8: - | AK8: - | AN8: Stel dat dit zo is, heeft dit voornamelijk invloed op de bewegende delen | AO8: - | AP8: -
A9: Fundering en drempel | C9: Lastig om te bekijken, er ligt een plaat. Er is onderzoek naar gedaan want er loopt een scheur over de hele breedte van kering, daaronder zit een holte, maar deze holte is niet zandvoerend. Dit wordt gemonitord door een duiker die de scheur meet. | D9: - | E9: Woelbak aan de zeezijde om zoet met zout water te mengen voor de vissen en het functioneert als golfbreker. Status van die bak is onbekend, in het verleden naar gekeken en toen zag het er goed uit. Moeilijk te zien | F9: - | H9: - | J9: - | M9: - | Q9: - | S9: - | T9: - | V9: Woelbak? Geen zorgen geen vragen | X9: - | Y9: - | AC9: - | AD9: - | AE9: - | AF9: - | AG9: - | AK9: - | AN9: - | AO9: Niet vervangbaar, staat wordt gemonitord en kan gerepareerd/verstevigd worden | AP9: -
A10: Bodembescherming | C10: Geen vervormingen, meerdere keren per jaar gescant. Ook met kieren geen verschillen, waarschijnlijk was er in de bouw met het kieren al wel rekening mee gehouden. Bij de bouw is er veel "gekierd". Geen nabijgelegen ontgrondingskuilen (>700m) | D10: - | E10: Goed, slijt wel wat maar geen B&O nodig | F10: - | H10: - | J10: - | M10: - | Q10: - | S10: - | T10: - | V10: - | X10: - | Y10: - | AC10: - | AD10: - | AE10: - | AF10: - | AG10: - | AK10: - | AN10: - | AO10: - | AP10: -
A11: Visriool | C11: ET1 | D11: - | E11: ET1 | F11: - | H11: Schuiven in de rioleren maar geen kennisvraag - standaard onderhoud | J11: - | M11: - | Q11: - | S11: - | T11: - | V11: - | X11: - | Y11: Pijp is groot genoeg voor aangroei van bijv mosselen. | AC11: - | AD11: - | AE11: - | AF11: - | AG11: - | AK11: - | AN11: - | AO11: - | AP11: -
A12: Zoutriool | C12: ET1 | D12: - | E12: ET1 | F12: - | H12: Schuiven in de rioleren maar geen kennisvraag - standaard onderhoud | J12: - | M12: - | Q12: - | S12: - | T12: - | V12: - | X12: - | Y12: - | AC12: - | AD12: - | AE12: - | AF12: - | AG12: - | AK12: - | AN12: - | AO12: - | AP12: -
A13: Wegdek | C13: Voegovergangen zijn niet waterdicht, lekt, dus niet helemaal goed. Maar komt wel weer goed | D13: nvt; beton; met huidige asbelasting geen probleem. (Wel mogelijk bij de sluis, bewegend brugdek) | E13: Slijt door verkeer. Recent laten opruwen/schoonspuiten en witte verkeersstrepen aanbrengen. | F13: - | H13: - | J13: - | M13: - | Q13: kan een verhoging van lucht temperatuur zorgen voor een te heet wegdek? Kan dit schade veroorzaken (aan de weg of aan de kering)? | S13: ET11 | T13: - | V13: - | X13: - | Y13: - | AC13: - | AD13: - | AE13: - | AF13: - | AG13: - | AK13: - | AN13: - | AO13: - | AP13: -
A14: Landhoofden | C14: ET2 | D14: - | E14: zie pijlers | F14: - | H14: - | J14: - | M14: - | Q14: - | S14: ET11 | T14: Aansluiting landhoofden op weg, was een keer een probleem. Kan dat nog een keer gebeuren en waarom gebeurt dit? | V14: - | X14: - | Y14: - | AC14: - | AD14: - | AE14: - | AF14: - | AG14: - | AK14: - | AN14: - | AO14: - | AP14: -
A15: Bediening en Besturingssysteem | C15: Nu LVO (levensverlengdonderhoud) aan het uitvoeren tot 2032(/2037). Daarna vervangen bovenlaag (software, hardware..) en onderlaag (hardware, servers, controllers etc). In 2012 is alles vernieuwd | D15: - | E15: - | F15: - | H15: - | J15: Bedieningsgebouw ligt binnendijks en hoog genoeg | M15: - | Q15: - | S15: - | T15: - | V15: - | X15: - | Y15: Op vier plekken in de uitersten van de kering staan meetputten voor het meten van de waterstand. 14 meter diepe koker met een plaat met een gat van een peer cm. Als er veel aangroei zit op de pijp naar buiten dan kun je niet goed de waterstand meten en kan de aansturing verkeerd gaan. Het systeem kiest de beste twee meetputten. Elk jaar worden deze putten schoongemaakt. Met een drone kan dit worden gecheckt/gefilmd. | AD15: Er komt een upgrade van de software aan. Er is een groot onderzoek door ABB uitgevoerd over wat verstandig is om te doen, daaruit kwam de upgrade. En dan na 2032 nieuw te vervangen. De test en acceptatieomgeving ligt bij ABB. Operator heeft in het hoofdgebouw 2 werkplekken en er is daarnaast nog een ander gebouw bij de sluis met een werk/bedieningsplek. | AE15: Heeft hier voornamelijk invloed op. Er is 1 leverancier, ABB. In slechtste geval draai je door op de huidige software | AF15: - | AG15: - | AK15: - | AN15: - | AO15: - | AP15: Hier zijn de gevolgen het grootst
A16: Energievoorziening | C16: Goed onder controle. In 2012 is dat allemaal vernieuwd, dat gaat nog meerdere jaren mee | D16: - | E16: - | F16: - | H16: - | J16: - | M16: - | Q16: - | S16: - | T16: - | V16: - | X16: - | Y16: - | AD16: - | AE16: - | AF16: - | AG16: - | AK16: - | AN16: - | AO16: - | AP16: Hier zijn de gevolgen het grootst
A17: Terrein | C17: Beleid heeft hier veel invloed op, RQI (risk quality), bijv alleen al het onkruidbestrijden. Prima onder controle. Ondergronden en toegang nu goed. Het (kantoor)gebouw is in corporate beheer, dus daar niet volledig de controle over. Bijvoorbeeld lekkages in het pand, elders wordt daar knoop over doorgehakt. Er zijn delen van het terrein waar men de status niet van weet. (Ontgronding onder het kantoorpand). Maarten is technisch beheerder van het pand, maar er is ook een objectbeheerder. Kan het objectbeheer ook bij het AM-team komen te liggen? | D17: - | E17: - | F17: - | H17: - | J17: - | M17: - | Q17: - | S17: - | T17: Het is allemaal opgespoten zand. Maar meestal gebeurt er niks | V17: - | X17: - | Y17: - | AC17: Locatiebeveilingsplan | AD17: - | AE17: - | AF17: - | AG17: Er zijn plannen voor nieuwe windmolens rondom de kering | AK17: - | AN17: - | AO17: - | AP17: -
A18: Operatie en BenO | C18: Er is overcapaciteit in de HV qua beschikbare schuiven. Er komt een mogelijk probleem aan qua teaminzetbaarheid met nieuwe contractvorm. Opertatie, bediening is een andere afdeling (VWM) - overzienbaar | D18: - | E18: - | F18: - | H18: - | J18: - | M18: - | Q18: - | S18: - | T18: - | V18: - | X18: - | Y18: - | AC18: - | AD18: - | AE18: Heeft hier voornamelijk invloed op; kwaliteit minder of meer | AF18: Leidt vooral tot vertraging - risico in tijd | AG18: - | AK18: - | AN18: - | AO18: - | AP18: -
A19: algemene opmerking | K19: Weinig effect. Alleen lichtmasten tijdens storm Franklin kapot gegaan. Tijdens storm / hevige wind is de kering nog steeds bereikbaar. Je kunt ook vanaf de andere kant van de kering erin voor beschutting. | L19: Golven breken op de eerste buitenste plaat, er zijn meer verzandingsproblemen dan dat het open komt - check | N19: Doordat de schuiven al elk vloed dicht gaan en elke eb (deels) open, bewegen de schuiven al elke dag. Vaker piekafvoer, heeft hooguit effect op voorspuien, maar niet op ETL | O19: Nu staat de kering in de zomer soms als weken/maanden dicht. Dit zal wellicht in de toekomst langer/vaker gebeuren. Voor ETL heeft dit geen effect: Alle schuiven worden eens in de maand bewogen, omdat lang niet bewegen slecht is voor het systeem.Ook meer functioneel, kan een effect hebben op de kwaliteit van het water. Mogelijk hierdoor zouter water, maar dat heeft geen effect want de kering staat al in zout water | Q19: Hele kering ondervindt krimp en uitzetting maar geen vragen/zorgen over bij de assetmanagers. | S19: Samenstelling beton HV en OSK is hetzelfde maar OSK heeft versnellers in het beton | U19: Zout water is er altijd al geweest | V19: Meer zand is meer schuring maar niet in onderzoek en geen zorgen over | W19: alleen 1 pijler heeft schade/blootgestelde wapening. | X19: De verwachting is dat de zandplaat voor de monding in de toekomst blijft groeien. Door de zandplaat breken de golven al eerder, wat juist voor een vermindering van golfenergie bij de kering veroorzaakt. | AA19: Niet van toepassing | AB19: Er loopt een stroomkabel van andere windmolens door de kering heen die AM-team niet uit kan zetten. Draagt een risico mee maar niet direct invloed | AD19: Er worden geen nieuwe materiale e.d. voorzien dat invloed gaat hebben op onderhoud en of functioneren van de kering | AE19: Het is makkelijk als je dezelfde spullen gebruikt net als de andere keringen en of complexen, dan kun je uitwisselen | AI19: Er wordt niks nieuws gebouwd dus geen problemen mee. Het kantoorpand is net als de kering 60 jaar oud. Er is een onderzoek geweest naar hoe je het huidige pand energielabel A kan krijgen. Maar dat is lastig. Oplossing: kantoorfunctie eruit halen? | AJ19: Niet top of mind of problemen op korte termijn. in het extreme geval zou bijv bepaalde type verf verboden worden, maar komt vooralsnog niet ter sprake/oren. Er zijn al geen chloridenhoudende verf gebruikt. | AK19: Hoe ver gaat het? Maar geen direct effect op einde technische levensduur. Alleen als de bereikbaarheid van onderdelen niet meer mogelijk zou zijn | AL19: Sluit nog steeds even vaak. Maar hoogstens meer schuiven moeten bewegen dus meer energie verbruik en iets verhoging van slijtage en benodigd onderhoud | AM19: Deltacommissie onderzoek die kijkt naar toekomstige delta | AO19: Valt of staat met onderhoud of zaken echt harder gaan slijten. Alles kan in principe vervangen worden | AP19: Er loopt een stroomkabel van andere windmolens door de kering heen die AM-team niet uit kan zetten. Draagt een risico mee maar niet direct invloed | AQ19: Geen concrete aanwijzingen voor grote impact volle veranderingen
A20: Gebouw? Bediengebouw (als los onderdeel?) | AP20: Operationeel team komt alleen in actie als er een storing/probleem is. Hier is standaard de bediening via VWM. Een storm is maar een klein onderdeel van de kering
D21: Legenda | F21: Driver niet aanwezig | I21: Invloed driver beperkt of | M21: Invloed driver is | P21: Heeft invloed, kennisvraag
F22: of heeft geen invloed | I22: op te lossen binnen BenO | M22: een kennisvraag | P22: wanneer en oplossingsrichtingen
M24: uitzoekvrraag versus kennisvraag
V26: Betonnen pijlers

Sheet EFL
K1: Klimatologische en natuurlijke ontwikkelingen | AB1: Socio-economische ontwikkelingen | AJ1: Beleidsmatige ontwikkelingen
A2: Categorie | B2: Functies | C2: Autonome situatie | D2: Huidige (en ontwerp) staat | E2: Vermoeiing | F2: Slijtage | G2: Schade | H2: Degradatie | I2: Corrosie | J2: Drivers | K2: Zeespiegelstijging | L2: Verandering windklimaat | M2: Verandering golfklimaat Noordzee | N2: Toename piekafvoer Maas & Rijn | O2: Toename frequentie hoogwater Maas & Rijn | P2: Afname afvoer Maas & Rijn (voornamelijk in zomer) | Q2: Verandering Neerslagpatroon | R2: Verandering van luchttemperatuur | S2: Verandering van watertemperatuur | T2: Toename CO2-gehalte in de lucht | U2: Bodemdaling | V2: Verzilting | W2: Verandering sedimenttransport en bodemerosie | X2: Verandering afvoer verdeling rijn-maas monding | Y2: Verandering in bodemligging HV monding | Z2: Verandering in getijslag Noordzee | AA2: Verandering biodiversiteit in ecosysteem | AB2: Verandering scheepvaartverkeer | AC2: Verandering bebouwing en/of verhoging waarde bebouwd achterland | AD2: Verandering in benodigd veiligheidsniveau | AE2: Technische ontwikkelingen (software, materiaal) | AF2: Verandering situatie leverancier | AG2: Vertrek/pensionering van kennisdragers | AH2: Energietransitie | AI2: Toename ecologische waarde HV | AJ2: Verandering onderhoudsbudget HV | AK2: Stikstofbeleid | AL2: Verbod op gebruik materialen | AM2: Aanscherping arbo veiligheidsnorm | AN2: Zoutindringing | AO2: Sluitpeilverhoging EK (MLK en HK) | AP2: Vervanging HV | AQ2: Nieuwe systeemeisen en/of -inrichting | AR2: Verlenging levensduur HV | AS2: Strengere waterveiligheidseis HV (faalkans en/of niet-sluiten kans) | AT2: Verandering sluitpeil HV | AU2: Algemene beleidskeuzes op (inter)nationaal niveau
A4: Waterveiligheid | B4: Bescherming tegen hoogwater Noordzee | D4: EF1/ EF27/ EF28 | E4: EF3 | K4: EF5 | M4: Driver heeft geen invloed | Q4: Driver heeft geen invloed | R4: EF9 | S4: EF10 | T4: Driver heeft geen invloed | U4: Driver heeft geen invloed | V4: Driver heeft geen invloed | Y4: EF13 | AA4: Driver heeft geen invloed | AB4: Driver heeft geen invloed | AD4: EF17 | AE4: EF18/ EF19/ EF20 | AG4: EF21 | AH4: EF22/ EF23 | AI4: Driver heeft geen invloed | AK4: Driver heeft geen invloed | AL4: EF24 | AO4: EF25 | AP4: EF26 | AQ4: EF26 | AR4: EF26 | AS4: EF27 | AT4: EF27 | AU4: Driver heeft geen invloed
B5: Rivierafvoer | E5: EF3 | K5: EF5 | N5: EF6 | O5: EF1 | R5: EF9 | S5: EF10 | W5: EF11 | X5: EF6 | AD5: EF17 | AE5: EF18/ EF19/ EF20 | AG5: EF21 | AH5: EF22/ EF23 | AL5: EF24 | AO5: EF25 | AP5: EF26 | AQ5: EF26 | AR5: EF26 | AS5: EF27 | AT5: EF27
A6: Waterbeheer | B6: Voldoende zoetwater (droogte) | D6: EF2 | P6: EF8 | R6: EF9 | S6: EF10 | Z6: EF15 | AD6: EF17 | AE6: EF18/ EF19/ EF20 | AG6: EF21 | AH6: EF22/ EF23 | AL6: EF24 | AP6: EF26 | AQ6: EF26 | AR6: EF26
A7: Waterkwaliteit | B7: Verzilting tegengaan | D7: EF2 | E7: EF3 | S7: EF10 | Z7: EF15 | AD7: EF17 | AE7: EF18/ EF19/ EF20 | AG7: EF21 | AH7: EF22/ EF23 | AL7: EF24 | AN7: Binnen het Deltaprogramma worden beslissingen voorbereid met betrekking tot zoutindringing. | AP7: EF26 | AQ7: EF26 | AR7: EF26
B8: Natura2000 - Brak waterzone | E8: EF3 | F8: EF3 | G8: EF3 | K8: EF5 | L8: Een verandering van het windklimaat kan een effect hebben op de ecologie (zou een beleidskeuze kunnen zijn) | O8: EF7 | S8: EF10 | Z8: EF15 | AD8: EF17 | AE8: EF18/ EF19/ EF20 | AG8: EF21 | AH8: EF22/ EF23 | AL8: EF24 | AN8: Binnen het Deltaprogramma worden beslissingen voorbereid met betrekking tot zoutindringing. | AP8: EF26 | AQ8: EF26 | AR8: EF26
B9: Natura2000 - Broedseizoen | K9: EF5 | N9: EF6 | S9: EF10 | X9: EF6 | Z9: EF15 | AD9: EF17 | AE9: EF18/ EF19/ EF20 | AG9: EF21 | AH9: EF22/ EF23 | AL9: EF24 | AP9: EF26 | AQ9: EF26 | AR9: EF26
B10: Calamiteiten | D10: EF2 | S10: EF10 | AD10: EF17 | AE10: EF18/ EF19/ EF20 | AG10: EF21 | AH10: EF22/ EF23 | AL10: EF24 | AP10: EF26 | AQ10: EF26 | AR10: EF26
A11: Infrastructuur | B11: Wegverkeer | AC11: EF16 | AD11: EF17 | AE11: EF18/ EF19/ EF20 | AG11: EF21 | AH11: EF22/ EF23 | AL11: EF24 | AP11: EF26 | AQ11: EF26 | AR11: EF26
B12: Scheepvaart | H12: voor de goereesluis | W12: EF12 | Y12: EF14 | AD12: EF17 | AE12: EF18/ EF19/ EF20 | AG12: EF21 | AH12: EF22/ EF23 | AL12: EF24 | AP12: EF26 | AQ12: EF26 | AR12: EF26
B13: Nuts | AD13: EF17 | AE13: EF18/ EF19/ EF20 | AG13: EF21 | AH13: EF22/ EF23 | AL13: EF24 | AP13: EF26 | AQ13: EF26 | AR13: EF26
A14: Overig | B14: Monumentale status | K14: Binnen 50 jaar niet, Binnen 100 jaar zouden de deuren evt moeten worden aangepast | AD14: EF17 | AE14: EF18/ EF19/ EF20 | AG14: EF21 | AH14: EF22/ EF23 | AL14: EF24 | AP14: EF26 | AQ14: EF26 | AR14: EF26
J22: Legenda | L22: Driver niet aanwezig | O22: Invloed driver beperkt of | S22: Invloed driver is | V22: Heeft invloed, kennisvraag
A23: Notities: | L23: of heeft geen invloed | O23: op te lossen binnen BenO | S23: een kennisvraag | V23: wanneer en oplossingsrichtingen
A25: Kpzss - hoe gaat de spuicapaciteit zich ontwikkelen in de toekomst met zss en hoe werkt dit zich uit in verschillende scenario's? (kieren).
A27: Faalkans vragen:
A28: Hoe wordt constructief falen meegenomen en geupdate ahv degradatie?
A29: Wat is een geschikte methodiek voor het bepalen van faalkansen in combinatie met veroudering?
A30: Wat is de rol van faalkans in ons assetmanagement? (onderdeel in functionele levensduur???)
A31: Zijn er nieuwe inzichten over het betrekken van menselijk handelen bij de faalkansbeschouwing?
A32: Hoe wordt het faalkansinstrument gebruikt?
A33: Weten we voldoende over ons watersysteem om effectief beheer uit te voeren en de faalkans te kunnen bepalen?

Sheet Driveroverzicht
A1: Categorie | B1: Type | C1: Toelichting | D1: Informatie | E1: Verwachte relevantie voor Object HV | F1: Toelichting | G1: Bron | H1: Samenhang andere NK's | J1: De schaal van relevantie (impact op het kunstwerk)
A2: Autonome situatie | B2: Huidige (en ontwerp) staat | C2: Wat waren/zijn de uitgangsposities van het ontwerp van de HV en weten we wat de status nu is? | D2: Bepaalde onderhoudsprojecten lopen achter op schema en zullen niet binnen planning kunnen worden afgerond, zoals W-delen en conservering van de segmentschuiven. Sinds het kierbesluit heeft de Haringvliet een extra functie. Werktuigbouwkundige delen worden meer belast en vragen extra aandacht in inspecties. Ook moet de RA (risico analyse) worden herzien door de extra functie. Snelheid is geboden omdat het contract van de opdrachtnemer (aannemer) ten einde loopt. | E2: Groot | F2: W-delen zijn essentieel voor het functioneren van de kering (hoog water keren en kieren). Om een goede faalkans af te geven, moet de onderliggende RA up-to-date zijn. Bij bruggen is een gewerkt aan een standaard voor bestaande bewegingswerken. Deze moet nog geplubliceerd worden, maar daar kunnen we na gaan welke issues er spelen bij bruggen en of deze relevant worden. | G2: FKR 2024-2 en 2025-1 | H2: - | J2: Klein | K2: Mogelijk klein | L2: Middel | M2: Mogelijk groot | N2: Groot
B3: Vermoeiing | C3: Afname sterkte door (af)wisselende belasting (periodieke belasting op de stalen delen, bijvoorbeeld door golven in combinatie met de waterstand) | D3: Er zijn meerdere aspecten waardoor er meer wisselende belastingen zijn dan in het ontwerp mee rekening is gehouden: -kierbesluit: meer open en dicht gaan van de kering -kierbesluit: langer open zijn van de kering, over een langere duur stroming door de kering (inclusief turbulentie) -mogelijk verandering in golfklimaat, zie drivers | E3: Mogelijk groot | F3: Onduidelijk in hoeverre hier rekening mee is gehouden in het ontwerp. Het is aannamelijk dat er geen rekening met vermoeiing is gehouden, omdat vermoeiing pas rond de jaren 90 werd opgenomen in normen. Wanneer corrossie optreed bij vermoeiingsgevoelige delen, kunnen deze degradatieprocessen elkaar versterken: corrossievermoeiing. Gezien de staat van de corrosiebescherming, is dit een aspect dat verdere aandacht behoeft. | G3: Expert judgement | H3: - | J3: Verwaarloosbare driver | K3: Nog onbekend welke invloed de driver precies heeft; minder prioriteit om uit te zoeken | L3: Relevante driver | M3: Nog onbekend welke invloed de driver precies heeft; meer prioriteit om uit te zoeken | N3: Zeer relevante driver
B4: Slijtage | C4: Eroderen (slijten) van materialen door het inzetten van de kering | D4: Door het kierbesluit worden werktuigbouwkundige delen meer ingezet. Hierdoor kan slijtage beinvloed worden. Dit moet worden meegenomen in inspectie- en onderhoud(sfrequentie). Ook zou er erosie van het beton kunnen optreden. | E4: Mogelijk klein | F4: Inspectie en tijdig onderhoud of vervanging | G4: Expert judgement/ TNO-rapport R10699 | H4: -
B5: Schade | C5: Calamiteit die zorgt voor lokale schade/verzwakking | D5: Door het kierbesluit hoopt vuil en brokstukken mogelijk op met schade tot gevolg tijdens het sluiten of openen. | E5: Mogelijk klein | F5: Onbekend is in hoeverre dit speelt bij de Haringvliet | G5: Expert judgement | H5: -
B6: Degradatie | C6: Algemene degradatie door verschillende processen die zorgen voor afname in sterkte van materialen in de kering | D6: Een ander degradatieproces dan slijtage, schade, corrosie. Hierbij valt te denken aan mechanische schade (door overbelasting), of schade door vervorming (door temp, vocht of zettingen). | E6: Mogelijk groot | F6: Voor de HV kan mechanische schade van belang zijn; schade door overbelasting en/of onvoldoende sterkte. De wanden rondom de vijzels vertonen namelijk scheuren die mogelijk te maken hebben met de krachtwerking in de constructie. Hoe nemen we dergelijke schade mee in de constructieve faalkans? Of is de constructieve staat een randvoorwaarden in de foutenboom? Schade door opgelegde en/of verhinderde vervormingen door vocht- of temperatuurseffecten kan toenemen door klimaatverandering. | G6: TNO-rapport R10699
B7: Corrosie | C7: Een vorm van degradatie; aantasting/roesten van staal onder invloed van stoffen in het water en/of de lucht. Corrosie is in deze uitwerking los beschouwd omdat dit voor de stormvloedkeringen een belangrijk degradatie proces is. | D7: Een verhoging van het zoutgehalte op het Haringvliet kan mogelijk leiden tot degradatie van de betonnen delen door corrosie van de wapening. Ook kan corrosie van de stalen delen aan de Haringvliet-zijde versnellen. @Greta lopend TNO onderzoek? Harry Weijs - zoutindriging beton - KpNK hoe degradatie tgv corrosie (beton, chloride indringing) mee te nemen in de faalkans feb 25 tussentijdse resultaten gepresenteerd. | E7: Mogelijk groot | F7: Ondanks de grote dekking wordt aangegeraden om choliride indringing te monitoren. Op een aantal plekken wordt extra gemonitord op chloride indringing. In de pijlers is al wat dekking weg, daar zie je plekken. Maar dat kan binnen BenO worden opgelost. Voor staal is de relevantie mogelijk groot vanwege de staat van de corrosiebescherming. Er is ook actieve cathodische bescherming en niet-actieve opofferingsanodes. Basis bescherming met coating is niet helemaal bij. Er zijn (veel) verschillende anti-corrsosie systemen maar ze moeten wel allemaal op orde zijn. Backup systemen zijn belangrijker door uitgesteld B&O. | G7: Expert judgement, DuMaCon, TNO-rapport R10699 | H7: -
B8: Driver | D8: Mogelijke of verwachte verandering | E8: Verwachte relevantie voor Object HV | F8: Toelichting | G8: Bron | H8: Samenhang andere NK's
A9: Klimaat- en natuurlijke processen | B9: Zeespiegelstijging | C9: Stijging van het gemiddelde zeeniveau | D9: 2050 +16 tot +38 cm; 2100 +26 tot +124 cm aan zee. | E9: Mogelijk groot | F9: Een verhogeing in zeespiegel zal resulteren in dat de kering vaker/sneller/langer dicht moet. Bovendien zullen er vaker hoogwaters plaatsvinden. Hierdoor is er minder tijd om te spuien wat kan resulteren in een verhoging van het waterniveau op de Haringvliet. Dit hangt sterk samen met de verwachte afvoer op de rivieren. Daarbij is de spuicapaciteit ook afhankelijk van het verval over de kering, en als de zeespiegel stijgt zal dit dus afnemen. Een ander effect is dat er minder tijd is voor het kieren. Zeespiegelstijging kan ook invloed hebben op de golfcondities bij de kering. Door de hogere sluitfrequentie zal vermoeiing eerder optreden. | G9: KNMI2023 | N9: v
B10: Verandering windklimaat | C10: Windsnelheid, windrichting, windextremen | D10: Voor Nederland wordt weinig verandering in windsnelheid en -richting verwacht in de projecties tot 2100. Bij buien zullen mogelijk sterkere windstoten en valwinden plaatsvinden. Daarnaast wordt er verwacht dat er 1 dag/jaar vaker wind uit richting Z-W komt en kan de gemiddelde windsnelheid in de winter een klein beetje hoger liggen (ongeveer +0.1 m/s). | E10: Mogelijk klein | F10: Windstoten kunnen zorgen voor een extra belasting op de schuiven? Het verwachte effect hiervan is momenteel onbekend. | G10: KNMI2023
B11: Verandering golfklimaat Noordzee | C11: Veranderingen in golfhoogte, - periode, en/of -richting | D11: In het kustgebied geen verwachte verandering in de projecties tot 2100. | E11: Mogelijk klein | F11: Er is vooralsnog geen verandering in golfklimaat voorspeld op de Noordzee. Mocht dit in de toekomst veranderen, zullen golven vooral invloed hebben op de schuiven en pijlers, waar golfbelasting het grootst is. De golven bepalen een belangrijk deel van de belastingen. | G11: Kust: DeWinter2012; DeWinter2013;
B12: Toename piekafvoer Maas & Rijn | C12: Toename van jaarlijkse piekwaarden | D12: 2050 +5 tot +10%; 2100 -2 tot +30% in jaarlijkse maxima van het debiet in de Rijn. Voor de Maas is dit -8% - 2% en -8 - 20%. Dit zorgt voor hogere waterstanden in de Haringlviet. | E12: Mogelijk groot | F12: Hogere afvoeren betekent dat er meer moet worden gespuit, om de maximale waterstand te waarborgen. Voornamelijk icm zeespiegelstijging kan dit een effect hebben. Bovendien zal er minder tijd voor kieren zijn. Bij een hoger spuidebiet is de stroomsnelheid ook hoger, wat er voor kan er voor zorgen dat de bodembescherming niet meer voldoet. Erosie van beton zal ook toenemen, zie D4. | G12: Deltares2023
B13: Toename frequentie hoogwater Maas & Rijn | C13: Toename van kans hoogwater op rivieren | D13: Met name in de winter wordt verwacht dat er gemiddeld meer afvoer gaat stromen door de rivieren in Nederland. Voor de Maas is dit tot 10% meer in 2050 en 30% in 2100 en minder voor de overige. Voor de Rijn is dit tot 15% in 2050 en 35% in 2100. Dit is voor het meest extreme KNMI scenario Hoognat. Het is niet geheel duidelijk hoe dit doorvertaald tot toename in frequentie hoogwater bij de HIJK | E13: Mogelijk groot | F13: De frequentie van hoogwater zal waarschijnlijk groot effect hebben op de HV. De HV sluit / opent hoe dan ook elke dag dus op sluit frequentie zal het geen effect hebben. Waar het wel effect op kan hebben is op het voorspuien. Wanneer er een hoogwater aankomt, kan er voorgespuit worden. Stel dat er meerdere hoogwaters achter elkaar komen, zou dit impact kunnen hebben op de hoeveelheid die er kan worden voorgespuit. De dreiging zit dan eigenlijk eerder in een langer durend hoogwater dan een hogere frequenties. | G13: Deltares2023
B14: Afname rivierafvoer (voornamelijk in de zomer) | C14: Afname van jaarlijks 7-daags minimum piekwaarden | D14: 2050 -5 tot -17%; 2100 -7 tot -32% voor 7-daags minimum op de Rijn, waar 90% van het water vandaan komt. | E14: Mogelijk groot | F14: Om het minimale waterpeil van 0mNAP bij Moerdijk te waarborgen kan er in tijden van droogte minder gespuit worden. Er kan dan wellicht niet gekierd worden, omdat anders de eis aan de maximale zout concentraties zal worden overschreden. Bij droogte komt het voor dat er maanden niet gekierd kan worden --> heeft direct invloed op de functie kieren. De zoutriolen worden dan als afvoer/spuien ingezet om te spuien. Zoutriolen kunnen tussen -10 en -12 afvoeren op het bekken. Onder de 1100m3 wordt gestopt met kieren, onder 900 bijna helemaal dicht. Wat er dan gespuid moet worden kan via de zoutriolen. Zout instroom moet beperkt worden voor innamepunten. | G14: Deltares2023
B15: Verandering neerslagpatronen | C15: Toename van de hoeveelheid (lokale) neerslag in het achterland leidt tot meer malen uit polders (bijv. hoosbuien) | D15: Winter 10 daags maximum per 10 jaar: 2050 verandering -2% tot +2%; 2100 verandering -2% tot +15%; Totale neerslag winter: 4-24% toename in 2100 Totale neerslag zomer: 2050 afname -2% tot -13%; 2100 afname -2% tot -29% Polderafvoer is de hoofdbron van de Hollandse IJssel. Deze neemt door een verandering in regen richting 2100 toe in winter en neemt af in zomer | E15: Klein | F15: Het effect van extra neerslag in de gebieden bovenstrooms van het gebied zijn meegenomen in de punten hierboven (want die zorgen effectief voor een grotere afvoer). De lokale neerslag zal relatief weinig bijdragen aan het totale debiet. Dit kan wel leiden tot verminderde waterkwaliteit in het Haringvliet door bijvoorbeeld lozing van overstorten, maar de rol van de HV wordt hierin verwaarloosbaar gezien. | G15: KNMI2023
B16: Toename luchttemperatuur | C16: Stijging van gemiddelde (en gem. dagminimum/maximum) | D16: Verschilt per scenario en per seizoen; 2050 +0,7 C tot +2,2 C; 2100 +0,7 C tot +5,4 C | E16: Mogelijk klein | F16: Hitte kan voor uitzetting zorgen van keringonderdelen, bijvoorbeeld de stalen schuiven. Andere aandachtspunten zijn de werktuigbouwkundige onderdelen en mogelijk hardware-ruimten. Tot 40 graden sowieso geen probleem. | G16: KNMI2023
B17: Verandering watertemperatuur | C17: Verandering van de gemiddelde temperatuur van het water rondom de HV | D17: Door opwarming van de aarde kan de watertemperatuur veranderen (in eerste instantie toenemen, als de golfstromen stoppen juist afnemen). | E17: Mogelijk klein | F17: Op basis van expert judgement wordt geschat dat dit geen/weinig invloed heeft op het functioneren van de kering of kan leiden tot versnelde veroudering van componenten. WEL een mogelijk effect op beleid voor ecologie. | G17: Nog nagaan bij collega's
B18: CO2-toename in de lucht | C18: Verandering CO2 concentratie in de lucht in parts per million (ppm) | D18: Alleen wereldwijde concentratie beschikbaar, huidig ~420 ppm; 2050 tot 600 ppm; 2100 tot 1100 ppm | E18: Mogelijk klein | F18: Een verhoging van CO2-concentratie kan in principe leiden tot aantasting van gewapend beton. CO2 zorgt voor corrosie (carbonatatie) van de bewapening. | G18: Vader21; KNMI'23 TNO-rapport R10699 | H18: Vader21; KNMI'23
B19: Bodemdaling | C19: Het inklinken van de bodem en daarmee het zakken van het maaiveld | E19: Klein | F19: De HV is volledig op een betonnen fundering gebouwd, waardoor verzakkingen ter plaatse van de sluizen niet optreden. Ter plaatste van de overgang naar de haringvlietdam wel. Het is onbekend of dit gebeurt/wordt verwacht. Vragen of hier een bron bekend is. Elk jaar wordt de deformatie gemonitord. Er vindt momenteel geen deformatie plaats op de HV. Voor zover bekend geen zettingen bekend (Wilbert van Maren? dijken dammen duinen club)
B20: Verzilting | C20: Zoutindringing in zowel grondwater als oppervlaktewateren (door open estuarium of door sluizen) | D20: Door het kierbesluit verandert de zout concentratie op het haringvliet voortdurend. | E20: Klein | F20: Door het kierbesluit van 2018 verandert de zout concentratie in het haringvliet voortdurend. Op de meeste plekken spoelt het zout water tijdens spuien (Q>2500m3/s) weer naar buiten. In sommige diepe kuilen blijft een deel van het zoute water hangen, waarbij het alleen bij erg hoge dichtheden wordt weggespoeld. De HV vormt een scheiding tussen zout en zoet water en is daarmee al dagelijks blootgesteld aan zout water. Een hogere zout concentratie binnen in het Haringvliet zal daardoor weinig tot geen effect hebben op de kering zelf (alhoewel om andere redenen ongewenst). | G20: Bureau waardenburg (2019)
B21: Verandering in sedimenttransport en bodemerosie | C21: Veranderingen absolute waterstand kunnen zorgen voor lokale knelpunten en veranderingen in de afvoerverdeling | E21: Klein | F21: Een verandering in sediment transport kan zorgen voor lokale erosie of sedimentatie. Dit kan de doorvaarhoogte (niet relevant voor HV) beinvloeden. Verder ligt er rondom de kering een bodembescherming. Lokale erosie ter plaatste van de overgang kan wel optreden. Als er extreme hoogwaters in het achterland zijn, is er meer sediment in suspensie. Ook wordt ander materiaal meegevoerd zoals bijvoorbeeld boomstammen wat tot schade aan de HV kan leiden
B22: Verandering afvoer verdeling rijn-maas monding | C22: Veranderingen in de afvoerverdeling van de Rijn-Maasmonding kunnen effect hebben op de doorstroming naar de Haringvlietsluizen. | E22: Mogelijk klein | F22: Door veranderingen in de morfologie van de Rijn-Maasmonding kan de afvoer veranderen, wat invloed kan hebben op achterwaartse verzilting, versterkte erosie en de spuivraag.
B23: Verandering in bodemligging haringvlietmonding | C23: Verandering van de (dynamische) morfologie aan de zeezijde van de haringvlietsluis | D23: De morfologische otnwikkelingen voor de HV zijn onzeker. Er zijn wel studies naar gedaan, zoals de studie van Arcadis waarin 3 scenarios zijn opgesteld voor de ontwikkeling van de voordelta. Hierin is het meest waarschijnlijke scenario de voordelta zal blijven verzanden, de kust breder wordt, en het geultje bij de Groene Punt helemaal dichtslibt. | E23: Mogelijk groot --> mogelijk klein | F23: Veranderingen in de morfologie kunnen een invloed hebben op de golfhoogte welke ter plaatste van de keringen optreden. Ook het moment van breken kan beinvloed worden. Mogelijke effecten hiervan zijn onbekend. | G23: Arcadis, 20
B24: Verandering getijslag op de noordzee | C24: Hogere laagwaters, lagere hoogwaters | D24: Er is een afname in het M2 getij geobserveerd op de noordzee over de afgelopen jaren. Op sommige locaties is de afname over de afgelopen jaren tot 3-4 cm. | E24: Klein | F24: Dit zou een mogelijk effect kunnen hebben op de spuitijden. Door de omvang (3-4 cm), valt dit echter binnen de onzekerheidsmarge van de voorspellingen.
B25: Verandering in biodiversiteit en ecosysteem | C25: Bijv. afname biodiversiteit en achteruitgang ecosysteem door veranderingen in waterkwaliteit of connectiviteit van gebieden | D25: Onbekend. Omdat de verwachte relevantie dusdanig klein is, is dit niet opgenomen als kennisvraag. | E25: Mogelijk klein | F25: mogelijk invloed op beleid. Verder niet. Marine aangroei, blauw en groenalgen. Vaker schoonmaken/conserveren het kan effect hebben op corrosie (snelheid). Ijzer-etende bacterie, MIC-bacterie, bij HV nog niet geconstateerd. Wel bij Terneuzen. | G25: assessment of m2 tidal amplitude changes in the north sea.pdf
A26: Socio-economische ontwikkelingen | B26: Verandering scheepvaartverkeer | C26: Een toename, in zowel intensiteit als scheepsgrootte, maar ook veranderingen in transportstrategie en type vracht | E26: Klein | F26: Als schepen een grotere diepgang krijgen in de toekomst, zou dit kunnen zorgen voor een hogere minimale waterstand op het haringvliet (een verandering aan de eisen), wat invloed zou kunnen hebben op het hele systeem.
B27: Verandering bebouwing en/of verhoging waarde bebouwd achterland | C27: Toename in aantal woningen in het binnendijks achterland en/of toename van de waarde van dit achterland. | D27: De huidige Nederlandse waterveiligheidsnormen zijn gebaseerd op een risico-aanpak (kans maal impact). Toename van de consequenties van overstromingen (impact) kan leiden tot hereiking van deze normen (maximale kansen). De normen zijn echter ruim gedefinieerd en ecomische groei is inbegrepen. | E27: Klein | F27: Het is onwaarschijnlijk dat verandering van bebouwing en/of waarde van het achterland op korte tot middellange termijn zal leiden tot andere eisen vanuit beleid. Samenhang met de driver "Strengere waterveiligheidseis …" onder Beleidskeuze.
B28: Verandering in benodigd beveiligingsniveau | C28: Cyber security threats en fysieke beveiliging | D28: Cybercrime, cyberspionage en cybersabotage kunnen systemen en processen verstoren, met grote gevolgen voor de volksgezondheid, veiligheid en economie. Dit is met de huidige internationale spanningen (2025) zeer relevant. Fysieke beveiliging is door dezelfde trend in internationale spanningen ook steeds meer van belang. | E28: Groot | F28: Voor het functioneren van de kering vormen fysieke en cyberaanvallen een bedreiging. Onduidelijk is wat hier realistisch (verder dan de huidige maatregelen)aan gedaan kan worden, maar dient in ieder geval te worden overwogen. Onder andere binnen de context van ISTORM is hier bij RWS al aandacht voor.
B29: Technische ontwikkelingen (software, materiaal) | C29: - | D29: Bijvoorbeeld veroudering van ICT waardoor het besturingssysteem niet meer aan een (nieuw/geupdate) informatie/input systeem kan worden verbonden of niet meer voldoet aan de cyber security eis. Of ontwikkeling van een nieuw product of systeem of uitvoeringsmethode met een langere levensduur, grotere betrouwbaarheid of makkelijke implementatie. | E29: Middel | F29: De verwachting is dat dit niet beperkend is voor einde levendsduur, maar is desondanks wel een grote onderhoudsopgave. Het zou ook kunnen voorkomen dat reserveonderdelen niet meer leverbaar zijn. Voorbeeld is de noodstroomaggregaat, reserveonderdelen zijn niet meer leverbaar. Dus er moet een nieuw systeem komen (anders gaat de faalkans aan de haal).
B30: Verandering situatie leverancier | C30: Onbeschikbaarheid noodzakelijk materiaal/materieel | D30: Het kan voorkomen dat bepaalde onderdelen of materialen niet meer leverbaar zijn. Dit is ook voor de toekomst niet uit te sluiten. | E30: Middel | F30: Het is voorgekomen dat keringspecifieke componenten of materialen niet meer leverbaar zijn. Dit blijft een aandachtspunt voor BenO, en heeft daarbij ook samenhang met de driver "Vertrek/pensionering kennisdragers". Navragen bij Niels Kuiken / Lenen olie van OSK/ brandstof/smeermiddel
B31: Vertrek/pensionering kennisdragers | C31: Kennis van personeel moet tijdig overgedragen kunnen worden om object specifieke kennis te borgen. Bij een groot verloop van personeel kan kennisoverdracht in het geding raken. | D31: Tot aan het einde van de ontwerplevensduur (oorspronkelijk 100 jaar, dus 2071) van de kering zullen nog meerdere medewerkers met pensioen gaan of vertrekken. | E31: Middel | F31: Hoewel dit niet direct tot einde levensduur zal leiden, is het een belangrijk aspect van de instandhouding van de kering en om te gaan met uitdagingen/kennisvragen gerelateerd aan einde levensduur. Kennisdelen (brengen en halen) binnen netwerken als ISTORM zal hier ook een nuttige rol bij hebben. Ook beleid omtrend personeelsbeleid - door bijvoorbeeld politiek - wijzigingen in contracten en contractvorm ; prestatiecontract dat aannemer ook verantwoordelijk is voor de beschikbaarheid van geleverd product, de prestatie ; basisonderhoud contract dan moet de aannemer x keer langskomen en staat laten zien - doe dit doe dat contract | G31: Expert Judgement
B32: Energietransitie | C32: Aanleg van winturbines en kabels | E32: Middel | F32: Mogelijke extra functie eisen door passerende kabels en aanpassing van de eigen energievoorziening. Kan effect hebben op de ecologie. | G32: Memo (Niels zoekt dit op)
A33: Beleidskeuze | B33: Ecologische waarde HV | C33: De open verbinding tussen het benedenrivierengebied en zee kan in de toekomst hoger gewaardeerd worden mbt ecologie. | D33: De open verbinding tussen de NWW en zee kan in de toekomst hoger gewaardeerd worden mbt ecologie. Dit is mogelijk een beleidskeuze. | E33: Mogelijk klein | F33: De HV is een gesloten kering in ruststand en daardoor niet gunstig voor ecologie. Sinds 2018 is het Kierbeleid gestart ten behoeve van de bevordering van de vismigratie. Dit houdt in dat de Haringvlietsluizen tijdens vloedsituaties deels open staan wanneer er niet gespuid wordt (‘kieren’). Mocht de ecologische waarde veranderen zouden je eisen kunnen veranderen aan het kieren. | G33: Kierbesluit2018
B34: Verandering onderhoudsbudget HV | C34: Mogelijke verandering economisch beleid o.b.v. regeringsbesluiten betreffend RWS | D34: Bezuinigingen voor verschillende ministeries zijn aangekondigd in het regeerprogramma van 2024. Eventuele gevolgen voor de HV (of andere stormvloedkeringen) zijn niet bekend. Verder in de toekomst kan dit een hele andere vorm krijgen. | E34: Middel | F34: In 2022 is het eerder voorgekomen dat het budget gehalveerd werd, vanwege te grote uitgaven op organisatieniveau (Rijkwaterstaat als geheel). Dit kan een rol spelen voor B&O, waardoor betrouwbaarheid van het functioneren van de kering in gevaar kan komen en op lange termijn dus ook de ETL en EFL. | G34: Rijksoverheid24
B35: Stikstofbeleid | C35: Stikstofuitstoot bij het opereren en onderhouden van de kering | D35: Aanscherpingen van maximale stikstofuitstoot bij bepaalde handelingen. | E35: Klein | F35: Voor het laten functioneren van de HV is het stikstofbeleid niet van belang. Voor onderhoud moet rekening gehouden worden dat er moet worden voldaan aan het stikstofbeleid. Met name de energievoorziening zal aan de stikstofeisen moeten voldoen, maar dit is voor de HV al elektrisch. Overigens, uitzonderingen kunnen gemaakt worden voor de kering als het onderhoud echt niet anders gedaan kan worden. Mochten er afspraken worden gemaakt over het gebruik van diesel agregraten, kan dit een effect hebben op de veiligheid van de functie van de kering. | G35: Deltares 2024a, expert judgement
B36: Verbod op gebruik materialen | C36: Mogelijk wordt de wetgeving aangescherpt voor het gebruik van bepaalde materialen, dat enkele materialen zal gaan verbieden (vanwege milieu en/of Arbo veiligheid) | D36: Te verwachten verandering is onbekend, maar kan grote gevolgen hebben als materialen met hele specifieke eigenschappen worden gebruikt in de kering. | E36: Klein | F36: Niet waarschijnlijk dat dit zal leiden tot einde levensduur, maar wel relevant voor BenO. Vergelijkbaar met "Verandering situatie leverancier" en "technische ontwikkelingen".
B37: Aanscherping arbo veiligheidsnormen | C37: Beperkingen voor de uitvoering van het onderhoud door aanscherpingen in de Arbo veiligheidseisen | D37: Aanscherping aan de arbo veiligheidseisen gedreven door veiligheid en duurzaamheid (bijv. Constructieve eisen (bijv. NEN-normen) of termijn afbouw stikstofuitstoot) | E37: Middel | F37: Voor het laten bedienen van de HV is een verandering in de arbo wetgeving niet van belang, wel onderhoud. De eisen die gesteld worden aan werkzaamheden staan onder continue verandering gedreven door verbetering van veiligheid evenals duurzaamheid. Aanpassingen in deze bouwnorm kunnen om aanpassingen vragen aan de huidige manier van het uitvoeren van werkzaamheden. Andere constructieve eisen of belastingnormen kunnen zorgen dat 1-op-1 vervangen van onderdelen niet volstaat. Het object is in een geheel andere tijd gebouwd, veiligheidsnormen worden bijgesteld en de kering is nog niet helemaal aangepast naar de nieuwste eisen en deze veranderingen gaan ook snel. Machine veiligheid, lokale bediening. Er is geen noodknop momenteel, als dat een eis wordt kan een probleem worden (ook voor de faalkans zou dat schuren). Meer mensen nodig voor hetzelfde werk, ook extra materieel, kosten verhogend. | G37: Deltares2024a, Deltares2024c, TraceKleeberg2023
